Workbook
Name VeteranMVPTeams: #REF!
Name ProspectGPMin: Variables!$D$15
Name ProspectMVPTeams: #REF!
Name RivalGPMin: Variables!$D$13
Name ContenderGPMin: Variables!$D$16
Name VeteranGPMin: Variables!$D$12
Name AmateurMVPTeams: #REF!
Name ChallengerGPMin: Variables!$D$14
Name PremierMVPTeams: #REF!
Name EliteGPMin: Variables!$D$11
Name AmateurGPMin: Variables!$D$17
Name PremierGPMin: Variables!$D$9
Name MasterMVPTeams: #REF!
Name MasterGPMin: Variables!$D$10
Name ChallengerMVPTeams: #REF!
Name ContenderMVPTeams: #REF!
Name EliteMVPTeams: #REF!
Name RivalMVPTeams: #REF!

Sheet Glossary
A1: Abbreviation | B1: Name | C1: Formula/Explanation | D1: Link
A2: Player | B2: Player
A3: Tier | B3: Tier
A4: Team(s) | B4: Team(s) | C4: All teams the player has played for in the tier (ordered from most recent (at the top) to least recent (at the bottom)).
A5: Franchise(s) | B5: Franchise(s) | C5: All franchises the player has played for in the tier (ordered from most recent (at the top) to least recent (at the bottom)).
A6: Conference | B6: Conference | C6: The conference the player has played the most in.
A7: RPV | B7: RSC Performance Value | C7: Average of SBV and IDR. Equal weight is given to both values
A8: SBV | B8: Stats-Based Value | C8: Standardize (Z-Score) NP/A, G/A, A/A, Sv/A, and S/A, then weighted-average them together, with their correlation to PWE serving as the weights. | D8: S23 RSC SBV
A9: IDR | B9: Index Derived Rating | C9: Take the player's Indexes (defined below), and their raw per game stats, and multiply them by the average of their correlation to win% and PWE, sum the weighted indexes, then find what standard deviation the player's value is at. Multiply that value by 25 and add 50, to make the scale more intuitive. An average player will have an IDR of around 50, and each standard deviation the player's score falls further away from average will be a 25 point increase or decrease. IDR was designed to factor in stats against, as well as strength of schedule. By also measuring your performance as ratios instead of just as raw per game stats you are not freely rewarded for getting 400 points against a team that normally gives up 400 points, and you aren't hurt for getting 150 points against a team that normally only gives up that many. It keeps track of both offensive and defensive stats, so what you let your opponents do is now also an important factor. you can't just ball chase your way to a high IDR in the same way that you can a high SBV. | D9: RSC S23 IDR
A10: GP | B10: Games Played | C10: W + L
A11: W | B11: Wins
A12: L | B12: Losses
A13: Win % | B13: Win Percentage | C13: W / GP
A14: MVPs | B14: Most Valuable Players | C14: Amount of times game MVP
A15: Pts | B15: Points
A16: PPG | B16: Points per Game
A17: Goals | B17: Goals
A18: GPG | B18: Goals per Game
A19: Assists | B19: Assists
A20: APG | B20: Assists per Game
A21: Saves | B21: Saves
A22: SvPG | B22: Saves per Game
A23: Shots | B23: Shots
A24: Shot % | B24: Shot Percentage | C24: Shot Percentage
A25: DI | B25: Demos Inflicted | C25: Number of times you murder an oppponent
A26: DT | B26: Demos Taken | C26: Number of times you are slain by the opposition

Sheet Sorted RPV
A1: Sort By | B1: All
A2: Sort By | B2: RPV
A3: Smaller = Better? | B3: FALSE
A5: {='Aggregate RPV'!A1} -> Tier | B5: RSC ID | C5: Name | D5: Team | E5: Conference | F5: SBV | G5: IDR | H5: RPV | I5: GP | J5: W | K5: L | L5: Win% | M5: MVPs | N5: Pts | O5: Goals | P5: Assists | Q5: Saves | R5: Shots | S5: Shot % | T5: PPG | U5: GPG | V5: APG | W5: SvPG | X5: ShPG | Y5: Cycles | Z5: Hat Tricks | AA5: Playmakers | AB5: Saviors | AC5: DI | AD5: DT
A6: =IFERROR(__xludf.DUMMYFUNCTION("SORT(FILTER({'Aggregate RPV'!A2:A3286,'Aggregate RPV'!B2:C3286,'Aggregate RPV'!D2:F3286,'Aggregate RPV'!H2:J3286},IF(B1=""All"",'Aggregate RPV'!B2:B3286<>"""",'Aggregate RPV'!A2:A3286=B1)),1,1,MATCH(B2,5:5,0),B3)"),"Amateur") -> Amateur | B6: =IFERROR(__xludf.DUMMYFUNCTION("""COMPUTED_VALUE"""),"RSC008201") -> RSC008201 | C6: =IFERROR(__xludf.DUMMYFUNCTION("""COMPUTED_VALUE"""),"CatalystNEMO") -> CatalystNEMO | D6: =IFERROR(__xludf.DUMMYFUNCTION("""COMPUTED_VALUE"""),"Bombers") -> Bombers | E6: =IFERROR(__xludf.DUMMYFUNCTION("""COMPUTED_VALUE"""),"N/A") -> N/A | F6: =IFERROR(__xludf.DUMMYFUNCTION("""COMPUTED_VALUE"""),152.0636508596478) -> 152.06365 | G6: =IFERROR(__xludf.DUMMYFUNCTION("""COMPUTED_VALUE"""),126.93443064018042) -> 126.93443 | H6: =IFERROR(__xludf.DUMMYFUNCTION("""COMPUTED_VALUE"""),139.49904074991412) -> 139.49904 | I6: =IFERROR(__xludf.DUMMYFUNCTION("""COMPUTED_VALUE"""),4.0) -> 4 | J6: =IFERROR(__xludf.DUMMYFUNCTION("IFERROR(FILTER(Stats!$F:$Z,(Stats!$A:$A=$A6)*(Stats!$B:$B=$B6)))"),3.0) -> 3 | K6: =IFERROR(__xludf.DUMMYFUNCTION("""COMPUTED_VALUE"""),1.0) -> 1 | L6: =IFERROR(__xludf.DUMMYFUNCTION("""COMPUTED_VALUE"""),0.75) -> 0.75 | M6: =IFERROR(__xludf.DUMMYFUNCTION("""COMPUTED_VALUE"""),2.0) -> 2 | N6: =IFERROR(__xludf.DUMMYFUNCTION("""COMPUTED_VALUE"""),1760.0) -> 1760 | O6: =IFERROR(__xludf.DUMMYFUNCTION("""COMPUTED_VALUE"""),6.0) -> 6 | P6: =IFERROR(__xludf.DUMMYFUNCTION("""COMPUTED_VALUE"""),5.0) -> 5 | Q6: =IFERROR(__xludf.DUMMYFUNCTION("""COMPUTED_VALUE"""),3.0) -> 3 | R6: =IFERROR(__xludf.DUMMYFUNCTION("""COMPUTED_VALUE"""),16.0) -> 16 | S6: =IFERROR(__xludf.DUMMYFUNCTION("""COMPUTED_VALUE"""),0.375) -> 0.375 | T6: =IFERROR(__xludf.DUMMYFUNCTION("""COMPUTED_VALUE"""),440.0) -> 440 | U6: =IFERROR(__xludf.DUMMYFUNCTION("""COMPUTED_VALUE"""),1.5) -> 1.5 | V6: =IFERROR(__xludf.DUMMYFUNCTION("""COMPUTED_VALUE"""),1.25) -> 1.25 | W6: =IFERROR(__xludf.DUMMYFUNCTION("""COMPUTED_VALUE"""),0.75) -> 0.75 | X6: =IFERROR(__xludf.DUMMYFUNCTION("""COMPUTED_VALUE"""),4.0) -> 4 | Y6: =IFERROR(__xludf.DUMMYFUNCTION("""COMPUTED_VALUE"""),2.0) -> 2 | Z6: =IFERROR(__xludf.DUMMYFUNCTION("""COMPUTED_VALUE"""),0.0) -> 0 | AA6: =IFERROR(__xludf.DUMMYFUNCTION("""COMPUTED_VALUE"""),0.0) -> 0 | AB6: =IFERROR(__xludf.DUMMYFUNCTION("""COMPUTED_VALUE"""),0.0) -> 0 | AC6: =IFERROR(__xludf.DUMMYFUNCTION("""COMPUTED_VALUE"""),2.0) -> 2 | AD6: =IFERROR(__xludf.DUMMYFUNCTION("""COMPUTED_VALUE"""),5.0) -> 5
A7: =IFERROR(__xludf.DUMMYFUNCTION("""COMPUTED_VALUE"""),"Amateur") -> Amateur | B7: =IFERROR(__xludf.DUMMYFUNCTION("""COMPUTED_VALUE"""),"RSC008541") -> RSC008541 | C7: =IFERROR(__xludf.DUMMYFUNCTION("""COMPUTED_VALUE"""),"Jito1017") -> Jito1017 | D7: =IFERROR(__xludf.DUMMYFUNCTION("""COMPUTED_VALUE"""),"Electric Eels Winter Fresh Garlic Knots") -> Electric Eels Winter Fresh Garlic Knots | E7: =IFERROR(__xludf.DUMMYFUNCTION("""COMPUTED_VALUE"""),"N/A N/A N/A") -> N/A N/A N/A | F7: =IFERROR(__xludf.DUMMYFUNCTION("""COMPUTED_VALUE"""),131.21159464877658) -> 131.21159 | G7: =IFERROR(__xludf.DUMMYFUNCTION("""COMPUTED_VALUE"""),98.55238766449756) -> 98.552388 | H7: =IFERROR(__xludf.DUMMYFUNCTION("""COMPUTED_VALUE"""),114.88199115663707) -> 114.88199 | I7: =IFERROR(__xludf.DUMMYFUNCTION("""COMPUTED_VALUE"""),16.0) -> 16 | J7: =IFERROR(__xludf.DUMMYFUNCTION("IFERROR(FILTER(Stats!$F:$Z,(Stats!$A:$A=$A7)*(Stats!$B:$B=$B7)))"),12.0) -> 12 | K7: =IFERROR(__xludf.DUMMYFUNCTION("""COMPUTED_VALUE"""),4.0) -> 4 | L7: =IFERROR(__xludf.DUMMYFUNCTION("""COMPUTED_VALUE"""),0.75) -> 0.75 | M7: =IFERROR(__xludf.DUMMYFUNCTION("""COMPUTED_VALUE"""),8.0) -> 8 | N7: =IFERROR(__xludf.DUMMYFUNCTION("""COMPUTED_VALUE"""),7003.0) -> 7003 | O7: =IFERROR(__xludf.DUMMYFUNCTION("""COMPUTED_VALUE"""),23.0) -> 23 | P7: =IFERROR(__xludf.DUMMYFUNCTION("""COMPUTED_VALUE"""),14.0) -> 14 | Q7: =IFERROR(__xludf.DUMMYFUNCTION("""COMPUTED_VALUE"""),13.0) -> 13 | R7: =IFERROR(__xludf.DUMMYFUNCTION("""COMPUTED_VALUE"""),51.0) -> 51 | S7: =IFERROR(__xludf.DUMMYFUNCTION("""COMPUTED_VALUE"""),0.45098039215686275) -> 0.45098039 | T7: =IFERROR(__xludf.DUMMYFUNCTION("""COMPUTED_VALUE"""),437.6875) -> 437.6875 | U7: =IFERROR(__xludf.DUMMYFUNCTION("""COMPUTED_VALUE"""),1.4375) -> 1.4375 | V7: =IFERROR(__xludf.DUMMYFUNCTION("""COMPUTED_VALUE"""),0.875) -> 0.875 | W7: =IFERROR(__xludf.DUMMYFUNCTION("""COMPUTED_VALUE"""),0.8125) -> 0.8125 | X7: =IFERROR(__xludf.DUMMYFUNCTION("""COMPUTED_VALUE"""),3.1875) -> 3.1875 | Y7: =IFERROR(__xludf.DUMMYFUNCTION("""COMPUTED_VALUE"""),6.0) -> 6 | Z7: =IFERROR(__xludf.DUMMYFUNCTION("""COMPUTED_VALUE"""),3.0) -> 3 | AA7: =IFERROR(__xludf.DUMMYFUNCTION("""COMPUTED_VALUE"""),0.0) -> 0 | AB7: =IFERROR(__xludf.DUMMYFUNCTION("""COMPUTED_VALUE"""),0.0) -> 0 | AC7: =IFERROR(__xludf.DUMMYFUNCTION("""COMPUTED_VALUE"""),14.0) -> 14 | AD7: =IFERROR(__xludf.DUMMYFUNCTION("""COMPUTED_VALUE"""),15.0) -> 15
A8: =IFERROR(__xludf.DUMMYFUNCTION("""COMPUTED_VALUE"""),"Amateur") -> Amateur | B8: =IFERROR(__xludf.DUMMYFUNCTION("""COMPUTED_VALUE"""),"RSC008178") -> RSC008178 | C8: =IFERROR(__xludf.DUMMYFUNCTION("""COMPUTED_VALUE"""),"Bigwigglystylezz") -> Bigwigglystylezz | D8: =IFERROR(__xludf.DUMMYFUNCTION("""COMPUTED_VALUE"""),"Winter Fresh") -> Winter Fresh | E8: =IFERROR(__xludf.DUMMYFUNCTION("""COMPUTED_VALUE"""),"N/A") -> N/A | F8: =IFERROR(__xludf.DUMMYFUNCTION("""COMPUTED_VALUE"""),81.69571187198164) -> 81.695712 | G8: =IFERROR(__xludf.DUMMYFUNCTION("""COMPUTED_VALUE"""),73.67911949155078) -> 73.679119 | H8: =IFERROR(__xludf.DUMMYFUNCTION("""COMPUTED_VALUE"""),77.68741568176621) -> 77.687416 | I8: =IFERROR(__xludf.DUMMYFUNCTION("""COMPUTED_VALUE"""),43.0) -> 43 | J8: =IFERROR(__xludf.DUMMYFUNCTION("IFERROR(FILTER(Stats!$F:$Z,(Stats!$A:$A=$A8)*(Stats!$B:$B=$B8)))"),26.0) -> 26 | K8: =IFERROR(__xludf.DUMMYFUNCTION("""COMPUTED_VALUE"""),17.0) -> 17 | L8: =IFERROR(__xludf.DUMMYFUNCTION("""COMPUTED_VALUE"""),0.6046511627906976) -> 0.60465116 | M8: =IFERROR(__xludf.DUMMYFUNCTION("""COMPUTED_VALUE"""),13.0) -> 13 | N8: =IFERROR(__xludf.DUMMYFUNCTION("""COMPUTED_VALUE"""),15291.0) -> 15291 | O8: =IFERROR(__xludf.DUMMYFUNCTION("""COMPUTED_VALUE"""),48.0) -> 48 | P8: =IFERROR(__xludf.DUMMYFUNCTION("""COMPUTED_VALUE"""),23.0) -> 23 | Q8: =IFERROR(__xludf.DUMMYFUNCTION("""COMPUTED_VALUE"""),37.0) -> 37 | R8: =IFERROR(__xludf.DUMMYFUNCTION("""COMPUTED_VALUE"""),112.0) -> 112 | S8: =IFERROR(__xludf.DUMMYFUNCTION("""COMPUTED_VALUE"""),0.42857142857142855) -> 0.42857143 | T8: =IFERROR(__xludf.DUMMYFUNCTION("""COMPUTED_VALUE"""),355.6046511627907) -> 355.60465 | U8: =IFERROR(__xludf.DUMMYFUNCTION("""COMPUTED_VALUE"""),1.1162790697674418) -> 1.1162791 | V8: =IFERROR(__xludf.DUMMYFUNCTION("""COMPUTED_VALUE"""),0.5348837209302325) -> 0.53488372 | W8: =IFERROR(__xludf.DUMMYFUNCTION("""COMPUTED_VALUE"""),0.8604651162790697) -> 0.86046512 | X8: =IFERROR(__xludf.DUMMYFUNCTION("""COMPUTED_VALUE"""),2.604651162790698) -> 2.6046512 | Y8: =IFERROR(__xludf.DUMMYFUNCTION("""COMPUTED_VALUE"""),6.0) -> 6 | Z8: =IFERROR(__xludf.DUMMYFUNCTION("""COMPUTED_VALUE"""),4.0) -> 4 | AA8: =IFERROR(__xludf.DUMMYFUNCTION("""COMPUTED_VALUE"""),3.0) -> 3 | AB8: =IFERROR(__xludf.DUMMYFUNCTION("""COMPUTED_VALUE"""),0.0) -> 0 | AC8: =IFERROR(__xludf.DUMMYFUNCTION("""COMPUTED_VALUE"""),30.0) -> 30 | AD8: =IFERROR(__xludf.DUMMYFUNCTION("""COMPUTED_VALUE"""),24.0) -> 24
A9: =IFERROR(__xludf.DUMMYFUNCTION("""COMPUTED_VALUE"""),"Amateur") -> Amateur | B9: =IFERROR(__xludf.DUMMYFUNCTION("""COMPUTED_VALUE"""),"RSC007468") -> RSC007468 | C9: =IFERROR(__xludf.DUMMYFUNCTION("""COMPUTED_VALUE"""),"im_link42") -> im_link42 | D9: =IFERROR(__xludf.DUMMYFUNCTION("""COMPUTED_VALUE"""),"Kappa") -> Kappa | E9: =IFERROR(__xludf.DUMMYFUNCTION("""COMPUTED_VALUE"""),"N/A") -> N/A | F9: =IFERROR(__xludf.DUMMYFUNCTION("""COMPUTED_VALUE"""),80.84796465516943) -> 80.847965 | G9: =IFERROR(__xludf.DUMMYFUNCTION("""COMPUTED_VALUE"""),67.6451175197777) -> 67.645118 | H9: =IFERROR(__xludf.DUMMYFUNCTION("""COMPUTED_VALUE"""),74.24654108747356) -> 74.246541 | I9: =IFERROR(__xludf.DUMMYFUNCTION("""COMPUTED_VALUE"""),46.0) -> 46 | J9: =IFERROR(__xludf.DUMMYFUNCTION("IFERROR(FILTER(Stats!$F:$Z,(Stats!$A:$A=$A9)*(Stats!$B:$B=$B9)))"),20.0) -> 20 | K9: =IFERROR(__xludf.DUMMYFUNCTION("""COMPUTED_VALUE"""),26.0) -> 26 | L9: =IFERROR(__xludf.DUMMYFUNCTION("""COMPUTED_VALUE"""),0.43478260869565216) -> 0.43478261 | M9: =IFERROR(__xludf.DUMMYFUNCTION("""COMPUTED_VALUE"""),14.0) -> 14 | N9: =IFERROR(__xludf.DUMMYFUNCTION("""COMPUTED_VALUE"""),17796.0) -> 17796 | O9: =IFERROR(__xludf.DUMMYFUNCTION("""COMPUTED_VALUE"""),46.0) -> 46 | P9: =IFERROR(__xludf.DUMMYFUNCTION("""COMPUTED_VALUE"""),20.0) -> 20 | Q9: =IFERROR(__xludf.DUMMYFUNCTION("""COMPUTED_VALUE"""),74.0) -> 74 | R9: =IFERROR(__xludf.DUMMYFUNCTION("""COMPUTED_VALUE"""),126.0) -> 126 | S9: =IFERROR(__xludf.DUMMYFUNCTION("""COMPUTED_VALUE"""),0.36507936507936506) -> 0.36507937 | T9: =IFERROR(__xludf.DUMMYFUNCTION("""COMPUTED_VALUE"""),386.8695652173913) -> 386.86957 | U9: =IFERROR(__xludf.DUMMYFUNCTION("""COMPUTED_VALUE"""),1.0) -> 1 | V9: =IFERROR(__xludf.DUMMYFUNCTION("""COMPUTED_VALUE"""),0.43478260869565216) -> 0.43478261 | W9: =IFERROR(__xludf.DUMMYFUNCTION("""COMPUTED_VALUE"""),1.608695652173913) -> 1.6086957 | X9: =IFERROR(__xludf.DUMMYFUNCTION("""COMPUTED_VALUE"""),2.739130434782609) -> 2.7391304 | Y9: =IFERROR(__xludf.DUMMYFUNCTION("""COMPUTED_VALUE"""),12.0) -> 12 | Z9: =IFERROR(__xludf.DUMMYFUNCTION("""COMPUTED_VALUE"""),2.0) -> 2 | AA9: =IFERROR(__xludf.DUMMYFUNCTION("""COMPUTED_VALUE"""),0.0) -> 0 | AB9: =IFERROR(__xludf.DUMMYFUNCTION("""COMPUTED_VALUE"""),7.0) -> 7 | AC9: =IFERROR(__xludf.DUMMYFUNCTION("""COMPUTED_VALUE"""),25.0) -> 25 | AD9: =IFERROR(__xludf.DUMMYFUNCTION("""COMPUTED_VALUE"""),34.0) -> 34
A10: =IFERROR(__xludf.DUMMYFUNCTION("""COMPUTED_VALUE"""),"Amateur") -> Amateur | B10: =IFERROR(__xludf.DUMMYFUNCTION("""COMPUTED_VALUE"""),"RSC007621") -> RSC007621 | C10: =IFERROR(__xludf.DUMMYFUNCTION("""COMPUTED_VALUE"""),"Classy-God57") -> Classy-God57 | D10: =IFERROR(__xludf.DUMMYFUNCTION("""COMPUTED_VALUE"""),"Winter Fresh") -> Winter Fresh | E10: =IFERROR(__xludf.DUMMYFUNCTION("""COMPUTED_VALUE"""),"N/A") -> N/A | F10: =IFERROR(__xludf.DUMMYFUNCTION("""COMPUTED_VALUE"""),75.87398555719933) -> 75.873986 | G10: =IFERROR(__xludf.DUMMYFUNCTION("""COMPUTED_VALUE"""),71.38544653711753) -> 71.385447 | H10: =IFERROR(__xludf.DUMMYFUNCTION("""COMPUTED_VALUE"""),73.62971604715844) -> 73.629716 | I10: =IFERROR(__xludf.DUMMYFUNCTION("""COMPUTED_VALUE"""),47.0) -> 47 | J10: =IFERROR(__xludf.DUMMYFUNCTION("IFERROR(FILTER(Stats!$F:$Z,(Stats!$A:$A=$A10)*(Stats!$B:$B=$B10)))"),30.0) -> 30 | K10: =IFERROR(__xludf.DUMMYFUNCTION("""COMPUTED_VALUE"""),17.0) -> 17 | L10: =IFERROR(__xludf.DUMMYFUNCTION("""COMPUTED_VALUE"""),0.6382978723404256) -> 0.63829787 | M10: =IFERROR(__xludf.DUMMYFUNCTION("""COMPUTED_VALUE"""),6.0) -> 6 | N10: =IFERROR(__xludf.DUMMYFUNCTION("""COMPUTED_VALUE"""),15486.0) -> 15486 | O10: =IFERROR(__xludf.DUMMYFUNCTION("""COMPUTED_VALUE"""),43.0) -> 43 | P10: =IFERROR(__xludf.DUMMYFUNCTION("""COMPUTED_VALUE"""),27.0) -> 27 | Q10: =IFERROR(__xludf.DUMMYFUNCTION("""COMPUTED_VALUE"""),41.0) -> 41 | R10: =IFERROR(__xludf.DUMMYFUNCTION("""COMPUTED_VALUE"""),139.0) -> 139 | S10: =IFERROR(__xludf.DUMMYFUNCTION("""COMPUTED_VALUE"""),0.30935251798561153) -> 0.30935252 | T10: =IFERROR(__xludf.DUMMYFUNCTION("""COMPUTED_VALUE"""),329.48936170212767) -> 329.48936 | U10: =IFERROR(__xludf.DUMMYFUNCTION("""COMPUTED_VALUE"""),0.9148936170212766) -> 0.91489362 | V10: =IFERROR(__xludf.DUMMYFUNCTION("""COMPUTED_VALUE"""),0.574468085106383) -> 0.57446809 | W10: =IFERROR(__xludf.DUMMYFUNCTION("""COMPUTED_VALUE"""),0.8723404255319149) -> 0.87234043 | X10: =IFERROR(__xludf.DUMMYFUNCTION("""COMPUTED_VALUE"""),2.9574468085106385) -> 2.9574468 | Y10: =IFERROR(__xludf.DUMMYFUNCTION("""COMPUTED_VALUE"""),6.0) -> 6 | Z10: =IFERROR(__xludf.DUMMYFUNCTION("""COMPUTED_VALUE"""),2.0) -> 2 | AA10: =IFERROR(__xludf.DUMMYFUNCTION("""COMPUTED_VALUE"""),0.0) -> 0 | AB10: =IFERROR(__xludf.DUMMYFUNCTION("""COMPUTED_VALUE"""),3.0) -> 3 | AC10: =IFERROR(__xludf.DUMMYFUNCTION("""COMPUTED_VALUE"""),20.0) -> 20 | AD10: =IFERROR(__xludf.DUMMYFUNCTION("""COMPUTED_VALUE"""),45.0) -> 45
A11: =IFERROR(__xludf.DUMMYFUNCTION("""COMPUTED_VALUE"""),"Amateur") -> Amateur | B11: =IFERROR(__xludf.DUMMYFUNCTION("""COMPUTED_VALUE"""),"RSC007571") -> RSC007571 | C11: =IFERROR(__xludf.DUMMYFUNCTION("""COMPUTED_VALUE"""),"StephM2_") -> StephM2_ | D11: =IFERROR(__xludf.DUMMYFUNCTION("""COMPUTED_VALUE"""),"Garlic Knots") -> Garlic Knots | E11: =IFERROR(__xludf.DUMMYFUNCTION("""COMPUTED_VALUE"""),"N/A") -> N/A | F11: =IFERROR(__xludf.DUMMYFUNCTION("""COMPUTED_VALUE"""),76.58843761915671) -> 76.588438 | G11: =IFERROR(__xludf.DUMMYFUNCTION("""COMPUTED_VALUE"""),67.59713632398024) -> 67.597136 | H11: =IFERROR(__xludf.DUMMYFUNCTION("""COMPUTED_VALUE"""),72.09278697156847) -> 72.092787 | I11: =IFERROR(__xludf.DUMMYFUNCTION("""COMPUTED_VALUE"""),47.0) -> 47 | J11: =IFERROR(__xludf.DUMMYFUNCTION("IFERROR(FILTER(Stats!$F:$Z,(Stats!$A:$A=$A11)*(Stats!$B:$B=$B11)))"),21.0) -> 21 | K11: =IFERROR(__xludf.DUMMYFUNCTION("""COMPUTED_VALUE"""),26.0) -> 26 | L11: =IFERROR(__xludf.DUMMYFUNCTION("""COMPUTED_VALUE"""),0.44680851063829785) -> 0.44680851 | M11: =IFERROR(__xludf.DUMMYFUNCTION("""COMPUTED_VALUE"""),13.0) -> 13 | N11: =IFERROR(__xludf.DUMMYFUNCTION("""COMPUTED_VALUE"""),17651.0) -> 17651 | O11: =IFERROR(__xludf.DUMMYFUNCTION("""COMPUTED_VALUE"""),42.0) -> 42 | P11: =IFERROR(__xludf.DUMMYFUNCTION("""COMPUTED_VALUE"""),22.0) -> 22 | Q11: =IFERROR(__xludf.DUMMYFUNCTION("""COMPUTED_VALUE"""),65.0) -> 65 | R11: =IFERROR(__xludf.DUMMYFUNCTION("""COMPUTED_VALUE"""),133.0) -> 133 | S11: =IFERROR(__xludf.DUMMYFUNCTION("""COMPUTED_VALUE"""),0.3157894736842105) -> 0.31578947 | T11: =IFERROR(__xludf.DUMMYFUNCTION("""COMPUTED_VALUE"""),375.5531914893617) -> 375.55319 | U11: =IFERROR(__xludf.DUMMYFUNCTION("""COMPUTED_VALUE"""),0.8936170212765957) -> 0.89361702 | V11: =IFERROR(__xludf.DUMMYFUNCTION("""COMPUTED_VALUE"""),0.46808510638297873) -> 0.46808511 | W11: =IFERROR(__xludf.DUMMYFUNCTION("""COMPUTED_VALUE"""),1.3829787234042554) -> 1.3829787 | X11: =IFERROR(__xludf.DUMMYFUNCTION("""COMPUTED_VALUE"""),2.8297872340425534) -> 2.8297872 | Y11: =IFERROR(__xludf.DUMMYFUNCTION("""COMPUTED_VALUE"""),10.0) -> 10 | Z11: =IFERROR(__xludf.DUMMYFUNCTION("""COMPUTED_VALUE"""),4.0) -> 4 | AA11: =IFERROR(__xludf.DUMMYFUNCTION("""COMPUTED_VALUE"""),0.0) -> 0 | AB11: =IFERROR(__xludf.DUMMYFUNCTION("""COMPUTED_VALUE"""),9.0) -> 9 | AC11: =IFERROR(__xludf.DUMMYFUNCTION("""COMPUTED_VALUE"""),61.0) -> 61 | AD11: =IFERROR(__xludf.DUMMYFUNCTION("""COMPUTED_VALUE"""),24.0) -> 24
A12: =IFERROR(__xludf.DUMMYFUNCTION("""COMPUTED_VALUE"""),"Amateur") -> Amateur | B12: =IFERROR(__xludf.DUMMYFUNCTION("""COMPUTED_VALUE"""),"RSC000086") -> RSC000086 | C12: =IFERROR(__xludf.DUMMYFUNCTION("""COMPUTED_VALUE"""),"Stale Popcorn") -> Stale Popcorn | D12: =IFERROR(__xludf.DUMMYFUNCTION("""COMPUTED_VALUE"""),"Winter Fresh HR Violation") -> Winter Fresh HR Violation | E12: =IFERROR(__xludf.DUMMYFUNCTION("""COMPUTED_VALUE"""),"N/A N/A") -> N/A N/A | F12: =IFERROR(__xludf.DUMMYFUNCTION("""COMPUTED_VALUE"""),70.94856001035916) -> 70.94856 | G12: =IFERROR(__xludf.DUMMYFUNCTION("""COMPUTED_VALUE"""),66.9422663409696) -> 66.942266 | H12: =IFERROR(__xludf.DUMMYFUNCTION("""COMPUTED_VALUE"""),68.94541317566438) -> 68.945413 | I12: =IFERROR(__xludf.DUMMYFUNCTION("""COMPUTED_VALUE"""),32.0) -> 32 | J12: =IFERROR(__xludf.DUMMYFUNCTION("IFERROR(FILTER(Stats!$F:$Z,(Stats!$A:$A=$A12)*(Stats!$B:$B=$B12)))"),15.0) -> 15 | K12: =IFERROR(__xludf.DUMMYFUNCTION("""COMPUTED_VALUE"""),17.0) -> 17 | L12: =IFERROR(__xludf.DUMMYFUNCTION("""COMPUTED_VALUE"""),0.46875) -> 0.46875 | M12: =IFERROR(__xludf.DUMMYFUNCTION("""COMPUTED_VALUE"""),7.0) -> 7 | N12: =IFERROR(__xludf.DUMMYFUNCTION("""COMPUTED_VALUE"""),10264.0) -> 10264 | O12: =IFERROR(__xludf.DUMMYFUNCTION("""COMPUTED_VALUE"""),30.0) -> 30 | P12: =IFERROR(__xludf.DUMMYFUNCTION("""COMPUTED_VALUE"""),15.0) -> 15 | Q12: =IFERROR(__xludf.DUMMYFUNCTION("""COMPUTED_VALUE"""),21.0) -> 21 | R12: =IFERROR(__xludf.DUMMYFUNCTION("""COMPUTED_VALUE"""),103.0) -> 103 | S12: =IFERROR(__xludf.DUMMYFUNCTION("""COMPUTED_VALUE"""),0.2912621359223301) -> 0.29126214 | T12: =IFERROR(__xludf.DUMMYFUNCTION("""COMPUTED_VALUE"""),320.75) -> 320.75 | U12: =IFERROR(__xludf.DUMMYFUNCTION("""COMPUTED_VALUE"""),0.9375) -> 0.9375 | V12: =IFERROR(__xludf.DUMMYFUNCTION("""COMPUTED_VALUE"""),0.46875) -> 0.46875 | W12: =IFERROR(__xludf.DUMMYFUNCTION("""COMPUTED_VALUE"""),0.65625) -> 0.65625 | X12: =IFERROR(__xludf.DUMMYFUNCTION("""COMPUTED_VALUE"""),3.21875) -> 3.21875 | Y12: =IFERROR(__xludf.DUMMYFUNCTION("""COMPUTED_VALUE"""),3.0) -> 3 | Z12: =IFERROR(__xludf.DUMMYFUNCTION("""COMPUTED_VALUE"""),3.0) -> 3 | AA12: =IFERROR(__xludf.DUMMYFUNCTION("""COMPUTED_VALUE"""),0.0) -> 0 | AB12: =IFERROR(__xludf.DUMMYFUNCTION("""COMPUTED_VALUE"""),1.0) -> 1 | AC12: =IFERROR(__xludf.DUMMYFUNCTION("""COMPUTED_VALUE"""),50.0) -> 50 | AD12: =IFERROR(__xludf.DUMMYFUNCTION("""COMPUTED_VALUE"""),20.0) -> 20
A13: =IFERROR(__xludf.DUMMYFUNCTION("""COMPUTED_VALUE"""),"Amateur") -> Amateur | B13: =IFERROR(__xludf.DUMMYFUNCTION("""COMPUTED_VALUE"""),"RSC008441") -> RSC008441 | C13: =IFERROR(__xludf.DUMMYFUNCTION("""COMPUTED_VALUE"""),"Izumi._._.") -> Izumi._._. | D13: =IFERROR(__xludf.DUMMYFUNCTION("""COMPUTED_VALUE"""),"HR Violation") -> HR Violation | E13: =IFERROR(__xludf.DUMMYFUNCTION("""COMPUTED_VALUE"""),"N/A") -> N/A | F13: =IFERROR(__xludf.DUMMYFUNCTION("""COMPUTED_VALUE"""),73.11410936672084) -> 73.114109 | G13: =IFERROR(__xludf.DUMMYFUNCTION("""COMPUTED_VALUE"""),64.08128424845688) -> 64.081284 | H13: =IFERROR(__xludf.DUMMYFUNCTION("""COMPUTED_VALUE"""),68.59769680758886) -> 68.597697 | I13: =IFERROR(__xludf.DUMMYFUNCTION("""COMPUTED_VALUE"""),56.0) -> 56 | J13: =IFERROR(__xludf.DUMMYFUNCTION("IFERROR(FILTER(Stats!$F:$Z,(Stats!$A:$A=$A13)*(Stats!$B:$B=$B13)))"),27.0) -> 27 | K13: =IFERROR(__xludf.DUMMYFUNCTION("""COMPUTED_VALUE"""),29.0) -> 29 | L13: =IFERROR(__xludf.DUMMYFUNCTION("""COMPUTED_VALUE"""),0.48214285714285715) -> 0.48214286 | M13: =IFERROR(__xludf.DUMMYFUNCTION("""COMPUTED_VALUE"""),13.0) -> 13 | N13: =IFERROR(__xludf.DUMMYFUNCTION("""COMPUTED_VALUE"""),19855.0) -> 19855 | O13: =IFERROR(__xludf.DUMMYFUNCTION("""COMPUTED_VALUE"""),52.0) -> 52 | P13: =IFERROR(__xludf.DUMMYFUNCTION("""COMPUTED_VALUE"""),25.0) -> 25 | Q13: =IFERROR(__xludf.DUMMYFUNCTION("""COMPUTED_VALUE"""),71.0) -> 71 | R13: =IFERROR(__xludf.DUMMYFUNCTION("""COMPUTED_VALUE"""),146.0) -> 146 | S13: =IFERROR(__xludf.DUMMYFUNCTION("""COMPUTED_VALUE"""),0.3561643835616438) -> 0.35616438 | T13: =IFERROR(__xludf.DUMMYFUNCTION("""COMPUTED_VALUE"""),354.55357142857144) -> 354.55357 | U13: =IFERROR(__xludf.DUMMYFUNCTION("""COMPUTED_VALUE"""),0.9285714285714286) -> 0.92857143 | V13: =IFERROR(__xludf.DUMMYFUNCTION("""COMPUTED_VALUE"""),0.44642857142857145) -> 0.44642857 | W13: =IFERROR(__xludf.DUMMYFUNCTION("""COMPUTED_VALUE"""),1.2678571428571428) -> 1.2678571 | X13: =IFERROR(__xludf.DUMMYFUNCTION("""COMPUTED_VALUE"""),2.607142857142857) -> 2.6071429 | Y13: =IFERROR(__xludf.DUMMYFUNCTION("""COMPUTED_VALUE"""),7.0) -> 7 | Z13: =IFERROR(__xludf.DUMMYFUNCTION("""COMPUTED_VALUE"""),0.0) -> 0 | AA13: =IFERROR(__xludf.DUMMYFUNCTION("""COMPUTED_VALUE"""),0.0) -> 0 | AB13: =IFERROR(__xludf.DUMMYFUNCTION("""COMPUTED_VALUE"""),9.0) -> 9 | AC13: =IFERROR(__xludf.DUMMYFUNCTION("""COMPUTED_VALUE"""),17.0) -> 17 | AD13: =IFERROR(__xludf.DUMMYFUNCTION("""COMPUTED_VALUE"""),42.0) -> 42
A14: =IFERROR(__xludf.DUMMYFUNCTION("""COMPUTED_VALUE"""),"Amateur") -> Amateur | B14: =IFERROR(__xludf.DUMMYFUNCTION("""COMPUTED_VALUE"""),"RSC000963") -> RSC000963 | C14: =IFERROR(__xludf.DUMMYFUNCTION("""COMPUTED_VALUE"""),"Sup3rm4n") -> Sup3rm4n | D14: =IFERROR(__xludf.DUMMYFUNCTION("""COMPUTED_VALUE"""),"Bombers") -> Bombers | E14: =IFERROR(__xludf.DUMMYFUNCTION("""COMPUTED_VALUE"""),"N/A") -> N/A | F14: =IFERROR(__xludf.DUMMYFUNCTION("""COMPUTED_VALUE"""),69.69412017105158) -> 69.69412 | G14: =IFERROR(__xludf.DUMMYFUNCTION("""COMPUTED_VALUE"""),67.41423923974222) -> 67.414239 | H14: =IFERROR(__xludf.DUMMYFUNCTION("""COMPUTED_VALUE"""),68.5541797053969) -> 68.55418 | I14: =IFERROR(__xludf.DUMMYFUNCTION("""COMPUTED_VALUE"""),55.0) -> 55 | J14: =IFERROR(__xludf.DUMMYFUNCTION("IFERROR(FILTER(Stats!$F:$Z,(Stats!$A:$A=$A14)*(Stats!$B:$B=$B14)))"),38.0) -> 38 | K14: =IFERROR(__xludf.DUMMYFUNCTION("""COMPUTED_VALUE"""),17.0) -> 17 | L14: =IFERROR(__xludf.DUMMYFUNCTION("""COMPUTED_VALUE"""),0.6909090909090909) -> 0.69090909 | M14: =IFERROR(__xludf.DUMMYFUNCTION("""COMPUTED_VALUE"""),16.0) -> 16 | N14: =IFERROR(__xludf.DUMMYFUNCTION("""COMPUTED_VALUE"""),18891.0) -> 18891 | O14: =IFERROR(__xludf.DUMMYFUNCTION("""COMPUTED_VALUE"""),54.0) -> 54 | P14: =IFERROR(__xludf.DUMMYFUNCTION("""COMPUTED_VALUE"""),24.0) -> 24 | Q14: =IFERROR(__xludf.DUMMYFUNCTION("""COMPUTED_VALUE"""),49.0) -> 49 | R14: =IFERROR(__xludf.DUMMYFUNCTION("""COMPUTED_VALUE"""),159.0) -> 159 | S14: =IFERROR(__xludf.DUMMYFUNCTION("""COMPUTED_VALUE"""),0.33962264150943394) -> 0.33962264 | T14: =IFERROR(__xludf.DUMMYFUNCTION("""COMPUTED_VALUE"""),343.4727272727273) -> 343.47273 | U14: =IFERROR(__xludf.DUMMYFUNCTION("""COMPUTED_VALUE"""),0.9818181818181818) -> 0.98181818 | V14: =IFERROR(__xludf.DUMMYFUNCTION("""COMPUTED_VALUE"""),0.43636363636363634) -> 0.43636364 | W14: =IFERROR(__xludf.DUMMYFUNCTION("""COMPUTED_VALUE"""),0.8909090909090909) -> 0.89090909 | X14: =IFERROR(__xludf.DUMMYFUNCTION("""COMPUTED_VALUE"""),2.890909090909091) -> 2.8909091 | Y14: =IFERROR(__xludf.DUMMYFUNCTION("""COMPUTED_VALUE"""),10.0) -> 10 | Z14: =IFERROR(__xludf.DUMMYFUNCTION("""COMPUTED_VALUE"""),5.0) -> 5 | AA14: =IFERROR(__xludf.DUMMYFUNCTION("""COMPUTED_VALUE"""),0.0) -> 0 | AB14: =IFERROR(__xludf.DUMMYFUNCTION("""COMPUTED_VALUE"""),4.0) -> 4 | AC14: =IFERROR(__xludf.DUMMYFUNCTION("""COMPUTED_VALUE"""),45.0) -> 45 | AD14: =IFERROR(__xludf.DUMMYFUNCTION("""COMPUTED_VALUE"""),43.0) -> 43
A15: =IFERROR(__xludf.DUMMYFUNCTION("""COMPUTED_VALUE"""),"Amateur") -> Amateur | B15: =IFERROR(__xludf.DUMMYFUNCTION("""COMPUTED_VALUE"""),"RSC008227") -> RSC008227 | C15: =IFERROR(__xludf.DUMMYFUNCTION("""COMPUTED_VALUE"""),"batman") -> batman | D15: =IFERROR(__xludf.DUMMYFUNCTION("""COMPUTED_VALUE"""),"Electric Eels") -> Electric Eels | E15: =IFERROR(__xludf.DUMMYFUNCTION("""COMPUTED_VALUE"""),"N/A") -> N/A | F15: =IFERROR(__xludf.DUMMYFUNCTION("""COMPUTED_VALUE"""),71.51301738215024) -> 71.513017 | G15: =IFERROR(__xludf.DUMMYFUNCTION("""COMPUTED_VALUE"""),62.75653641242059) -> 62.756536 | H15: =IFERROR(__xludf.DUMMYFUNCTION("""COMPUTED_VALUE"""),67.1347768972854) -> 67.134777 | I15: =IFERROR(__xludf.DUMMYFUNCTION("""COMPUTED_VALUE"""),12.0) -> 12 | J15: =IFERROR(__xludf.DUMMYFUNCTION("IFERROR(FILTER(Stats!$F:$Z,(Stats!$A:$A=$A15)*(Stats!$B:$B=$B15)))"),8.0) -> 8 | K15: =IFERROR(__xludf.DUMMYFUNCTION("""COMPUTED_VALUE"""),4.0) -> 4 | L15: =IFERROR(__xludf.DUMMYFUNCTION("""COMPUTED_VALUE"""),0.6666666666666666) -> 0.66666667 | M15: =IFERROR(__xludf.DUMMYFUNCTION("""COMPUTED_VALUE"""),1.0) -> 1 | N15: =IFERROR(__xludf.DUMMYFUNCTION("""COMPUTED_VALUE"""),4076.0) -> 4076 | O15: =IFERROR(__xludf.DUMMYFUNCTION("""COMPUTED_VALUE"""),8.0) -> 8 | P15: =IFERROR(__xludf.DUMMYFUNCTION("""COMPUTED_VALUE"""),9.0) -> 9 | Q15: =IFERROR(__xludf.DUMMYFUNCTION("""COMPUTED_VALUE"""),15.0) -> 15 | R15: =IFERROR(__xludf.DUMMYFUNCTION("""COMPUTED_VALUE"""),26.0) -> 26 | S15: =IFERROR(__xludf.DUMMYFUNCTION("""COMPUTED_VALUE"""),0.3076923076923077) -> 0.30769231 | T15: =IFERROR(__xludf.DUMMYFUNCTION("""COMPUTED_VALUE"""),339.6666666666667) -> 339.66667 | U15: =IFERROR(__xludf.DUMMYFUNCTION("""COMPUTED_VALUE"""),0.6666666666666666) -> 0.66666667 | V15: =IFERROR(__xludf.DUMMYFUNCTION("""COMPUTED_VALUE"""),0.75) -> 0.75 | W15: =IFERROR(__xludf.DUMMYFUNCTION("""COMPUTED_VALUE"""),1.25) -> 1.25 | X15: =IFERROR(__xludf.DUMMYFUNCTION("""COMPUTED_VALUE"""),2.1666666666666665) -> 2.1666667 | Y15: =IFERROR(__xludf.DUMMYFUNCTION("""COMPUTED_VALUE"""),2.0) -> 2 | Z15: =IFERROR(__xludf.DUMMYFUNCTION("""COMPUTED_VALUE"""),1.0) -> 1 | AA15: =IFERROR(__xludf.DUMMYFUNCTION("""COMPUTED_VALUE"""),0.0) -> 0 | AB15: =IFERROR(__xludf.DUMMYFUNCTION("""COMPUTED_VALUE"""),2.0) -> 2 | AC15: =IFERROR(__xludf.DUMMYFUNCTION("""COMPUTED_VALUE"""),9.0) -> 9 | AD15: =IFERROR(__xludf.DUMMYFUNCTION("""COMPUTED_VALUE"""),14.0) -> 14
A16: =IFERROR(__xludf.DUMMYFUNCTION("""COMPUTED_VALUE"""),"Amateur") -> Amateur | B16: =IFERROR(__xludf.DUMMYFUNCTION("""COMPUTED_VALUE"""),"RSC008136") -> RSC008136 | C16: =IFERROR(__xludf.DUMMYFUNCTION("""COMPUTED_VALUE"""),"GeneralLeigh91") -> GeneralLeigh91 | D16: =IFERROR(__xludf.DUMMYFUNCTION("""COMPUTED_VALUE"""),"Winter Fresh Chimera") -> Winter Fresh Chimera | E16: =IFERROR(__xludf.DUMMYFUNCTION("""COMPUTED_VALUE"""),"N/A N/A") -> N/A N/A | F16: =IFERROR(__xludf.DUMMYFUNCTION("""COMPUTED_VALUE"""),62.23499587117157) -> 62.234996 | G16: =IFERROR(__xludf.DUMMYFUNCTION("""COMPUTED_VALUE"""),66.60528714472376) -> 66.605287 | H16: =IFERROR(__xludf.DUMMYFUNCTION("""COMPUTED_VALUE"""),64.42014150794766) -> 64.420142 | I16: =IFERROR(__xludf.DUMMYFUNCTION("""COMPUTED_VALUE"""),50.0) -> 50 | J16: =IFERROR(__xludf.DUMMYFUNCTION("IFERROR(FILTER(Stats!$F:$Z,(Stats!$A:$A=$A16)*(Stats!$B:$B=$B16)))"),31.0) -> 31 | K16: =IFERROR(__xludf.DUMMYFUNCTION("""COMPUTED_VALUE"""),19.0) -> 19 | L16: =IFERROR(__xludf.DUMMYFUNCTION("""COMPUTED_VALUE"""),0.62) -> 0.62 | M16: =IFERROR(__xludf.DUMMYFUNCTION("""COMPUTED_VALUE"""),11.0) -> 11 | N16: =IFERROR(__xludf.DUMMYFUNCTION("""COMPUTED_VALUE"""),17383.0) -> 17383 | O16: =IFERROR(__xludf.DUMMYFUNCTION("""COMPUTED_VALUE"""),48.0) -> 48 | P16: =IFERROR(__xludf.DUMMYFUNCTION("""COMPUTED_VALUE"""),29.0) -> 29 | Q16: =IFERROR(__xludf.DUMMYFUNCTION("""COMPUTED_VALUE"""),63.0) -> 63 | R16: =IFERROR(__xludf.DUMMYFUNCTION("""COMPUTED_VALUE"""),121.0) -> 121 | S16: =IFERROR(__xludf.DUMMYFUNCTION("""COMPUTED_VALUE"""),0.39669421487603307) -> 0.39669421 | T16: =IFERROR(__xludf.DUMMYFUNCTION("""COMPUTED_VALUE"""),347.66) -> 347.66 | U16: =IFERROR(__xludf.DUMMYFUNCTION("""COMPUTED_VALUE"""),0.96) -> 0.96 | V16: =IFERROR(__xludf.DUMMYFUNCTION("""COMPUTED_VALUE"""),0.58) -> 0.58 | W16: =IFERROR(__xludf.DUMMYFUNCTION("""COMPUTED_VALUE"""),1.26) -> 1.26 | X16: =IFERROR(__xludf.DUMMYFUNCTION("""COMPUTED_VALUE"""),2.42) -> 2.42 | Y16: =IFERROR(__xludf.DUMMYFUNCTION("""COMPUTED_VALUE"""),7.0) -> 7 | Z16: =IFERROR(__xludf.DUMMYFUNCTION("""COMPUTED_VALUE"""),4.0) -> 4 | AA16: =IFERROR(__xludf.DUMMYFUNCTION("""COMPUTED_VALUE"""),2.0) -> 2 | AB16: =IFERROR(__xludf.DUMMYFUNCTION("""COMPUTED_VALUE"""),7.0) -> 7 | AC16: =IFERROR(__xludf.DUMMYFUNCTION("""COMPUTED_VALUE"""),32.0) -> 32 | AD16: =IFERROR(__xludf.DUMMYFUNCTION("""COMPUTED_VALUE"""),33.0) -> 33
A17: =IFERROR(__xludf.DUMMYFUNCTION("""COMPUTED_VALUE"""),"Amateur") -> Amateur | B17: =IFERROR(__xludf.DUMMYFUNCTION("""COMPUTED_VALUE"""),"RSC008092") -> RSC008092 | C17: =IFERROR(__xludf.DUMMYFUNCTION("""COMPUTED_VALUE"""),"ImPodz") -> ImPodz | D17: =IFERROR(__xludf.DUMMYFUNCTION("""COMPUTED_VALUE"""),"Electric Eels") -> Electric Eels | E17: =IFERROR(__xludf.DUMMYFUNCTION("""COMPUTED_VALUE"""),"N/A") -> N/A | F17: =IFERROR(__xludf.DUMMYFUNCTION("""COMPUTED_VALUE"""),64.13553882675204) -> 64.135539 | G17: =IFERROR(__xludf.DUMMYFUNCTION("""COMPUTED_VALUE"""),59.7024205811802) -> 59.702421 | H17: =IFERROR(__xludf.DUMMYFUNCTION("""COMPUTED_VALUE"""),61.918979703966116) -> 61.91898 | I17: =IFERROR(__xludf.DUMMYFUNCTION("""COMPUTED_VALUE"""),28.0) -> 28 | J17: =IFERROR(__xludf.DUMMYFUNCTION("IFERROR(FILTER(Stats!$F:$Z,(Stats!$A:$A=$A17)*(Stats!$B:$B=$B17)))"),13.0) -> 13 | K17: =IFERROR(__xludf.DUMMYFUNCTION("""COMPUTED_VALUE"""),15.0) -> 15 | L17: =IFERROR(__xludf.DUMMYFUNCTION("""COMPUTED_VALUE"""),0.4642857142857143) -> 0.46428571 | M17: =IFERROR(__xludf.DUMMYFUNCTION("""COMPUTED_VALUE"""),6.0) -> 6 | N17: =IFERROR(__xludf.DUMMYFUNCTION("""COMPUTED_VALUE"""),10042.0) -> 10042 | O17: =IFERROR(__xludf.DUMMYFUNCTION("""COMPUTED_VALUE"""),24.0) -> 24 | P17: =IFERROR(__xludf.DUMMYFUNCTION("""COMPUTED_VALUE"""),11.0) -> 11 | Q17: =IFERROR(__xludf.DUMMYFUNCTION("""COMPUTED_VALUE"""),36.0) -> 36 | R17: =IFERROR(__xludf.DUMMYFUNCTION("""COMPUTED_VALUE"""),66.0) -> 66 | S17: =IFERROR(__xludf.DUMMYFUNCTION("""COMPUTED_VALUE"""),0.36363636363636365) -> 0.36363636 | T17: =IFERROR(__xludf.DUMMYFUNCTION("""COMPUTED_VALUE"""),358.64285714285717) -> 358.64286 | U17: =IFERROR(__xludf.DUMMYFUNCTION("""COMPUTED_VALUE"""),0.8571428571428571) -> 0.85714286 | V17: =IFERROR(__xludf.DUMMYFUNCTION("""COMPUTED_VALUE"""),0.39285714285714285) -> 0.39285714 | W17: =IFERROR(__xludf.DUMMYFUNCTION("""COMPUTED_VALUE"""),1.2857142857142858) -> 1.2857143 | X17: =IFERROR(__xludf.DUMMYFUNCTION("""COMPUTED_VALUE"""),2.357142857142857) -> 2.3571429 | Y17: =IFERROR(__xludf.DUMMYFUNCTION("""COMPUTED_VALUE"""),2.0) -> 2 | Z17: =IFERROR(__xludf.DUMMYFUNCTION("""COMPUTED_VALUE"""),3.0) -> 3 | AA17: =IFERROR(__xludf.DUMMYFUNCTION("""COMPUTED_VALUE"""),0.0) -> 0 | AB17: =IFERROR(__xludf.DUMMYFUNCTION("""COMPUTED_VALUE"""),4.0) -> 4 | AC17: =IFERROR(__xludf.DUMMYFUNCTION("""COMPUTED_VALUE"""),21.0) -> 21 | AD17: =IFERROR(__xludf.DUMMYFUNCTION("""COMPUTED_VALUE"""),14.0) -> 14
A18: =IFERROR(__xludf.DUMMYFUNCTION("""COMPUTED_VALUE"""),"Amateur") -> Amateur | B18: =IFERROR(__xludf.DUMMYFUNCTION("""COMPUTED_VALUE"""),"RSC007270") -> RSC007270 | C18: =IFERROR(__xludf.DUMMYFUNCTION("""COMPUTED_VALUE"""),"D0pey killer") -> D0pey killer | D18: =IFERROR(__xludf.DUMMYFUNCTION("""COMPUTED_VALUE"""),"Electric Eels") -> Electric Eels | E18: =IFERROR(__xludf.DUMMYFUNCTION("""COMPUTED_VALUE"""),"N/A") -> N/A | F18: =IFERROR(__xludf.DUMMYFUNCTION("""COMPUTED_VALUE"""),64.03248701807968) -> 64.032487 | G18: =IFERROR(__xludf.DUMMYFUNCTION("""COMPUTED_VALUE"""),59.51264956267918) -> 59.51265 | H18: =IFERROR(__xludf.DUMMYFUNCTION("""COMPUTED_VALUE"""),61.772568290379425) -> 61.772568 | I18: =IFERROR(__xludf.DUMMYFUNCTION("""COMPUTED_VALUE"""),48.0) -> 48 | J18: =IFERROR(__xludf.DUMMYFUNCTION("IFERROR(FILTER(Stats!$F:$Z,(Stats!$A:$A=$A18)*(Stats!$B:$B=$B18)))"),24.0) -> 24 | K18: =IFERROR(__xludf.DUMMYFUNCTION("""COMPUTED_VALUE"""),24.0) -> 24 | L18: =IFERROR(__xludf.DUMMYFUNCTION("""COMPUTED_VALUE"""),0.5) -> 0.5 | M18: =IFERROR(__xludf.DUMMYFUNCTION("""COMPUTED_VALUE"""),4.0) -> 4 | N18: =IFERROR(__xludf.DUMMYFUNCTION("""COMPUTED_VALUE"""),15443.0) -> 15443 | O18: =IFERROR(__xludf.DUMMYFUNCTION("""COMPUTED_VALUE"""),35.0) -> 35 | P18: =IFERROR(__xludf.DUMMYFUNCTION("""COMPUTED_VALUE"""),24.0) -> 24 | Q18: =IFERROR(__xludf.DUMMYFUNCTION("""COMPUTED_VALUE"""),49.0) -> 49 | R18: =IFERROR(__xludf.DUMMYFUNCTION("""COMPUTED_VALUE"""),118.0) -> 118 | S18: =IFERROR(__xludf.DUMMYFUNCTION("""COMPUTED_VALUE"""),0.2966101694915254) -> 0.29661017 | T18: =IFERROR(__xludf.DUMMYFUNCTION("""COMPUTED_VALUE"""),321.7291666666667) -> 321.72917 | U18: =IFERROR(__xludf.DUMMYFUNCTION("""COMPUTED_VALUE"""),0.7291666666666666) -> 0.72916667 | V18: =IFERROR(__xludf.DUMMYFUNCTION("""COMPUTED_VALUE"""),0.5) -> 0.5 | W18: =IFERROR(__xludf.DUMMYFUNCTION("""COMPUTED_VALUE"""),1.0208333333333333) -> 1.0208333 | X18: =IFERROR(__xludf.DUMMYFUNCTION("""COMPUTED_VALUE"""),2.4583333333333335) -> 2.4583333 | Y18: =IFERROR(__xludf.DUMMYFUNCTION("""COMPUTED_VALUE"""),7.0) -> 7 | Z18: =IFERROR(__xludf.DUMMYFUNCTION("""COMPUTED_VALUE"""),2.0) -> 2 | AA18: =IFERROR(__xludf.DUMMYFUNCTION("""COMPUTED_VALUE"""),2.0) -> 2 | AB18: =IFERROR(__xludf.DUMMYFUNCTION("""COMPUTED_VALUE"""),7.0) -> 7 | AC18: =IFERROR(__xludf.DUMMYFUNCTION("""COMPUTED_VALUE"""),43.0) -> 43 | AD18: =IFERROR(__xludf.DUMMYFUNCTION("""COMPUTED_VALUE"""),33.0) -> 33
A19: =IFERROR(__xludf.DUMMYFUNCTION("""COMPUTED_VALUE"""),"Amateur") -> Amateur | B19: =IFERROR(__xludf.DUMMYFUNCTION("""COMPUTED_VALUE"""),"RSC008193") -> RSC008193 | C19: =IFERROR(__xludf.DUMMYFUNCTION("""COMPUTED_VALUE"""),"RL Camaro") -> RL Camaro | D19: =IFERROR(__xludf.DUMMYFUNCTION("""COMPUTED_VALUE"""),"Chimera") -> Chimera | E19: =IFERROR(__xludf.DUMMYFUNCTION("""COMPUTED_VALUE"""),"N/A") -> N/A | F19: =IFERROR(__xludf.DUMMYFUNCTION("""COMPUTED_VALUE"""),58.53108837612528) -> 58.531088 | G19: =IFERROR(__xludf.DUMMYFUNCTION("""COMPUTED_VALUE"""),59.46436549120326) -> 59.464365 | H19: =IFERROR(__xludf.DUMMYFUNCTION("""COMPUTED_VALUE"""),58.99772693366427) -> 58.997727 | I19: =IFERROR(__xludf.DUMMYFUNCTION("""COMPUTED_VALUE"""),51.0) -> 51 | J19: =IFERROR(__xludf.DUMMYFUNCTION("IFERROR(FILTER(Stats!$F:$Z,(Stats!$A:$A=$A19)*(Stats!$B:$B=$B19)))"),27.0) -> 27 | K19: =IFERROR(__xludf.DUMMYFUNCTION("""COMPUTED_VALUE"""),24.0) -> 24 | L19: =IFERROR(__xludf.DUMMYFUNCTION("""COMPUTED_VALUE"""),0.5294117647058824) -> 0.52941176 | M19: =IFERROR(__xludf.DUMMYFUNCTION("""COMPUTED_VALUE"""),10.0) -> 10 | N19: =IFERROR(__xludf.DUMMYFUNCTION("""COMPUTED_VALUE"""),16903.0) -> 16903 | O19: =IFERROR(__xludf.DUMMYFUNCTION("""COMPUTED_VALUE"""),46.0) -> 46 | P19: =IFERROR(__xludf.DUMMYFUNCTION("""COMPUTED_VALUE"""),24.0) -> 24 | Q19: =IFERROR(__xludf.DUMMYFUNCTION("""COMPUTED_VALUE"""),40.0) -> 40 | R19: =IFERROR(__xludf.DUMMYFUNCTION("""COMPUTED_VALUE"""),117.0) -> 117 | S19: =IFERROR(__xludf.DUMMYFUNCTION("""COMPUTED_VALUE"""),0.39316239316239315) -> 0.39316239 | T19: =IFERROR(__xludf.DUMMYFUNCTION("""COMPUTED_VALUE"""),331.4313725490196) -> 331.43137 | U19: =IFERROR(__xludf.DUMMYFUNCTION("""COMPUTED_VALUE"""),0.9019607843137255) -> 0.90196078 | V19: =IFERROR(__xludf.DUMMYFUNCTION("""COMPUTED_VALUE"""),0.47058823529411764) -> 0.47058824 | W19: =IFERROR(__xludf.DUMMYFUNCTION("""COMPUTED_VALUE"""),0.7843137254901961) -> 0.78431373 | X19: =IFERROR(__xludf.DUMMYFUNCTION("""COMPUTED_VALUE"""),2.2941176470588234) -> 2.2941176 | Y19: =IFERROR(__xludf.DUMMYFUNCTION("""COMPUTED_VALUE"""),4.0) -> 4 | Z19: =IFERROR(__xludf.DUMMYFUNCTION("""COMPUTED_VALUE"""),3.0) -> 3 | AA19: =IFERROR(__xludf.DUMMYFUNCTION("""COMPUTED_VALUE"""),0.0) -> 0 | AB19: =IFERROR(__xludf.DUMMYFUNCTION("""COMPUTED_VALUE"""),3.0) -> 3 | AC19: =IFERROR(__xludf.DUMMYFUNCTION("""COMPUTED_VALUE"""),23.0) -> 23 | AD19: =IFERROR(__xludf.DUMMYFUNCTION("""COMPUTED_VALUE"""),34.0) -> 34
A20: =IFERROR(__xludf.DUMMYFUNCTION("""COMPUTED_VALUE"""),"Amateur") -> Amateur | B20: =IFERROR(__xludf.DUMMYFUNCTION("""COMPUTED_VALUE"""),"RSC007852") -> RSC007852 | C20: =IFERROR(__xludf.DUMMYFUNCTION("""COMPUTED_VALUE"""),"Medicmac121") -> Medicmac121 | D20: =IFERROR(__xludf.DUMMYFUNCTION("""COMPUTED_VALUE"""),"Garlic Knots") -> Garlic Knots | E20: =IFERROR(__xludf.DUMMYFUNCTION("""COMPUTED_VALUE"""),"N/A") -> N/A | F20: =IFERROR(__xludf.DUMMYFUNCTION("""COMPUTED_VALUE"""),55.6750799410066) -> 55.67508 | G20: =IFERROR(__xludf.DUMMYFUNCTION("""COMPUTED_VALUE"""),59.29091412043735) -> 59.290914 | H20: =IFERROR(__xludf.DUMMYFUNCTION("""COMPUTED_VALUE"""),57.482997030721975) -> 57.482997 | I20: =IFERROR(__xludf.DUMMYFUNCTION("""COMPUTED_VALUE"""),44.0) -> 44 | J20: =IFERROR(__xludf.DUMMYFUNCTION("IFERROR(FILTER(Stats!$F:$Z,(Stats!$A:$A=$A20)*(Stats!$B:$B=$B20)))"),20.0) -> 20 | K20: =IFERROR(__xludf.DUMMYFUNCTION("""COMPUTED_VALUE"""),24.0) -> 24 | L20: =IFERROR(__xludf.DUMMYFUNCTION("""COMPUTED_VALUE"""),0.45454545454545453) -> 0.45454545 | M20: =IFERROR(__xludf.DUMMYFUNCTION("""COMPUTED_VALUE"""),5.0) -> 5 | N20: =IFERROR(__xludf.DUMMYFUNCTION("""COMPUTED_VALUE"""),13777.0) -> 13777 | O20: =IFERROR(__xludf.DUMMYFUNCTION("""COMPUTED_VALUE"""),37.0) -> 37 | P20: =IFERROR(__xludf.DUMMYFUNCTION("""COMPUTED_VALUE"""),19.0) -> 19 | Q20: =IFERROR(__xludf.DUMMYFUNCTION("""COMPUTED_VALUE"""),32.0) -> 32 | R20: =IFERROR(__xludf.DUMMYFUNCTION("""COMPUTED_VALUE"""),120.0) -> 120 | S20: =IFERROR(__xludf.DUMMYFUNCTION("""COMPUTED_VALUE"""),0.30833333333333335) -> 0.30833333 | T20: =IFERROR(__xludf.DUMMYFUNCTION("""COMPUTED_VALUE"""),313.1136363636364) -> 313.11364 | U20: =IFERROR(__xludf.DUMMYFUNCTION("""COMPUTED_VALUE"""),0.8409090909090909) -> 0.84090909 | V20: =IFERROR(__xludf.DUMMYFUNCTION("""COMPUTED_VALUE"""),0.4318181818181818) -> 0.43181818 | W20: =IFERROR(__xludf.DUMMYFUNCTION("""COMPUTED_VALUE"""),0.7272727272727273) -> 0.72727273 | X20: =IFERROR(__xludf.DUMMYFUNCTION("""COMPUTED_VALUE"""),2.727272727272727) -> 2.7272727 | Y20: =IFERROR(__xludf.DUMMYFUNCTION("""COMPUTED_VALUE"""),5.0) -> 5 | Z20: =IFERROR(__xludf.DUMMYFUNCTION("""COMPUTED_VALUE"""),3.0) -> 3 | AA20: =IFERROR(__xludf.DUMMYFUNCTION("""COMPUTED_VALUE"""),0.0) -> 0 | AB20: =IFERROR(__xludf.DUMMYFUNCTION("""COMPUTED_VALUE"""),3.0) -> 3 | AC20: =IFERROR(__xludf.DUMMYFUNCTION("""COMPUTED_VALUE"""),59.0) -> 59 | AD20: =IFERROR(__xludf.DUMMYFUNCTION("""COMPUTED_VALUE"""),26.0) -> 26
A21: =IFERROR(__xludf.DUMMYFUNCTION("""COMPUTED_VALUE"""),"Amateur") -> Amateur | B21: =IFERROR(__xludf.DUMMYFUNCTION("""COMPUTED_VALUE"""),"RSC002713") -> RSC002713 | C21: =IFERROR(__xludf.DUMMYFUNCTION("""COMPUTED_VALUE"""),"TimmyIU20") -> TimmyIU20 | D21: =IFERROR(__xludf.DUMMYFUNCTION("""COMPUTED_VALUE"""),"Winter Fresh Electric Eels") -> Winter Fresh Electric Eels | E21: =IFERROR(__xludf.DUMMYFUNCTION("""COMPUTED_VALUE"""),"N/A N/A") -> N/A N/A | F21: =IFERROR(__xludf.DUMMYFUNCTION("""COMPUTED_VALUE"""),53.93122557704734) -> 53.931226 | G21: =IFERROR(__xludf.DUMMYFUNCTION("""COMPUTED_VALUE"""),57.864552560707395) -> 57.864553 | H21: =IFERROR(__xludf.DUMMYFUNCTION("""COMPUTED_VALUE"""),55.89788906887737) -> 55.897889 | I21: =IFERROR(__xludf.DUMMYFUNCTION("""COMPUTED_VALUE"""),32.0) -> 32 | J21: =IFERROR(__xludf.DUMMYFUNCTION("IFERROR(FILTER(Stats!$F:$Z,(Stats!$A:$A=$A21)*(Stats!$B:$B=$B21)))"),22.0) -> 22 | K21: =IFERROR(__xludf.DUMMYFUNCTION("""COMPUTED_VALUE"""),10.0) -> 10 | L21: =IFERROR(__xludf.DUMMYFUNCTION("""COMPUTED_VALUE"""),0.6875) -> 0.6875 | M21: =IFERROR(__xludf.DUMMYFUNCTION("""COMPUTED_VALUE"""),7.0) -> 7 | N21: =IFERROR(__xludf.DUMMYFUNCTION("""COMPUTED_VALUE"""),10408.0) -> 10408 | O21: =IFERROR(__xludf.DUMMYFUNCTION("""COMPUTED_VALUE"""),30.0) -> 30 | P21: =IFERROR(__xludf.DUMMYFUNCTION("""COMPUTED_VALUE"""),11.0) -> 11 | Q21: =IFERROR(__xludf.DUMMYFUNCTION("""COMPUTED_VALUE"""),30.0) -> 30 | R21: =IFERROR(__xludf.DUMMYFUNCTION("""COMPUTED_VALUE"""),79.0) -> 79 | S21: =IFERROR(__xludf.DUMMYFUNCTION("""COMPUTED_VALUE"""),0.379746835443038) -> 0.37974684 | T21: =IFERROR(__xludf.DUMMYFUNCTION("""COMPUTED_VALUE"""),325.25) -> 325.25 | U21: =IFERROR(__xludf.DUMMYFUNCTION("""COMPUTED_VALUE"""),0.9375) -> 0.9375 | V21: =IFERROR(__xludf.DUMMYFUNCTION("""COMPUTED_VALUE"""),0.34375) -> 0.34375 | W21: =IFERROR(__xludf.DUMMYFUNCTION("""COMPUTED_VALUE"""),0.9375) -> 0.9375 | X21: =IFERROR(__xludf.DUMMYFUNCTION("""COMPUTED_VALUE"""),2.46875) -> 2.46875 | Y21: =IFERROR(__xludf.DUMMYFUNCTION("""COMPUTED_VALUE"""),3.0) -> 3 | Z21: =IFERROR(__xludf.DUMMYFUNCTION("""COMPUTED_VALUE"""),1.0) -> 1 | AA21: =IFERROR(__xludf.DUMMYFUNCTION("""COMPUTED_VALUE"""),0.0) -> 0 | AB21: =IFERROR(__xludf.DUMMYFUNCTION("""COMPUTED_VALUE"""),2.0) -> 2 | AC21: =IFERROR(__xludf.DUMMYFUNCTION("""COMPUTED_VALUE"""),15.0) -> 15 | AD21: =IFERROR(__xludf.DUMMYFUNCTION("""COMPUTED_VALUE"""),33.0) -> 33
A22: =IFERROR(__xludf.DUMMYFUNCTION("""COMPUTED_VALUE"""),"Amateur") -> Amateur | B22: =IFERROR(__xludf.DUMMYFUNCTION("""COMPUTED_VALUE"""),"RSC007581") -> RSC007581 | C22: =IFERROR(__xludf.DUMMYFUNCTION("""COMPUTED_VALUE"""),"Wrecklessjay02") -> Wrecklessjay02 | D22: =IFERROR(__xludf.DUMMYFUNCTION("""COMPUTED_VALUE"""),"Bombers") -> Bombers | E22: =IFERROR(__xludf.DUMMYFUNCTION("""COMPUTED_VALUE"""),"N/A") -> N/A | F22: =IFERROR(__xludf.DUMMYFUNCTION("""COMPUTED_VALUE"""),54.2014102094929) -> 54.20141 | G22: =IFERROR(__xludf.DUMMYFUNCTION("""COMPUTED_VALUE"""),56.90245359791163) -> 56.902454 | H22: =IFERROR(__xludf.DUMMYFUNCTION("""COMPUTED_VALUE"""),55.55193190370227) -> 55.551932 | I22: =IFERROR(__xludf.DUMMYFUNCTION("""COMPUTED_VALUE"""),47.0) -> 47 | J22: =IFERROR(__xludf.DUMMYFUNCTION("IFERROR(FILTER(Stats!$F:$Z,(Stats!$A:$A=$A22)*(Stats!$B:$B=$B22)))"),34.0) -> 34 | K22: =IFERROR(__xludf.DUMMYFUNCTION("""COMPUTED_VALUE"""),13.0) -> 13 | L22: =IFERROR(__xludf.DUMMYFUNCTION("""COMPUTED_VALUE"""),0.723404255319149) -> 0.72340426 | M22: =IFERROR(__xludf.DUMMYFUNCTION("""COMPUTED_VALUE"""),7.0) -> 7 | N22: =IFERROR(__xludf.DUMMYFUNCTION("""COMPUTED_VALUE"""),13812.0) -> 13812 | O22: =IFERROR(__xludf.DUMMYFUNCTION("""COMPUTED_VALUE"""),29.0) -> 29 | P22: =IFERROR(__xludf.DUMMYFUNCTION("""COMPUTED_VALUE"""),27.0) -> 27 | Q22: =IFERROR(__xludf.DUMMYFUNCTION("""COMPUTED_VALUE"""),40.0) -> 40 | R22: =IFERROR(__xludf.DUMMYFUNCTION("""COMPUTED_VALUE"""),106.0) -> 106 | S22: =IFERROR(__xludf.DUMMYFUNCTION("""COMPUTED_VALUE"""),0.27358490566037735) -> 0.27358491 | T22: =IFERROR(__xludf.DUMMYFUNCTION("""COMPUTED_VALUE"""),293.8723404255319) -> 293.87234 | U22: =IFERROR(__xludf.DUMMYFUNCTION("""COMPUTED_VALUE"""),0.6170212765957447) -> 0.61702128 | V22: =IFERROR(__xludf.DUMMYFUNCTION("""COMPUTED_VALUE"""),0.574468085106383) -> 0.57446809 | W22: =IFERROR(__xludf.DUMMYFUNCTION("""COMPUTED_VALUE"""),0.851063829787234) -> 0.85106383 | X22: =IFERROR(__xludf.DUMMYFUNCTION("""COMPUTED_VALUE"""),2.25531914893617) -> 2.2553191 | Y22: =IFERROR(__xludf.DUMMYFUNCTION("""COMPUTED_VALUE"""),2.0) -> 2 | Z22: =IFERROR(__xludf.DUMMYFUNCTION("""COMPUTED_VALUE"""),2.0) -> 2 | AA22: =IFERROR(__xludf.DUMMYFUNCTION("""COMPUTED_VALUE"""),1.0) -> 1 | AB22: =IFERROR(__xludf.DUMMYFUNCTION("""COMPUTED_VALUE"""),2.0) -> 2 | AC22: =IFERROR(__xludf.DUMMYFUNCTION("""COMPUTED_VALUE"""),39.0) -> 39 | AD22: =IFERROR(__xludf.DUMMYFUNCTION("""COMPUTED_VALUE"""),30.0) -> 30
A23: =IFERROR(__xludf.DUMMYFUNCTION("""COMPUTED_VALUE"""),"Amateur") -> Amateur | B23: =IFERROR(__xludf.DUMMYFUNCTION("""COMPUTED_VALUE"""),"RSC006375") -> RSC006375 | C23: =IFERROR(__xludf.DUMMYFUNCTION("""COMPUTED_VALUE"""),"Rich-Rollin6060") -> Rich-Rollin6060 | D23: =IFERROR(__xludf.DUMMYFUNCTION("""COMPUTED_VALUE"""),"Garlic Knots") -> Garlic Knots | E23: =IFERROR(__xludf.DUMMYFUNCTION("""COMPUTED_VALUE"""),"N/A") -> N/A | F23: =IFERROR(__xludf.DUMMYFUNCTION("""COMPUTED_VALUE"""),54.59217446996295) -> 54.592174 | G23: =IFERROR(__xludf.DUMMYFUNCTION("""COMPUTED_VALUE"""),55.72317975002479) -> 55.72318 | H23: =IFERROR(__xludf.DUMMYFUNCTION("""COMPUTED_VALUE"""),55.15767710999387) -> 55.157677 | I23: =IFERROR(__xludf.DUMMYFUNCTION("""COMPUTED_VALUE"""),42.0) -> 42 | J23: =IFERROR(__xludf.DUMMYFUNCTION("IFERROR(FILTER(Stats!$F:$Z,(Stats!$A:$A=$A23)*(Stats!$B:$B=$B23)))"),23.0) -> 23 | K23: =IFERROR(__xludf.DUMMYFUNCTION("""COMPUTED_VALUE"""),19.0) -> 19 | L23: =IFERROR(__xludf.DUMMYFUNCTION("""COMPUTED_VALUE"""),0.5476190476190477) -> 0.54761905 | M23: =IFERROR(__xludf.DUMMYFUNCTION("""COMPUTED_VALUE"""),4.0) -> 4 | N23: =IFERROR(__xludf.DUMMYFUNCTION("""COMPUTED_VALUE"""),11869.0) -> 11869 | O23: =IFERROR(__xludf.DUMMYFUNCTION("""COMPUTED_VALUE"""),33.0) -> 33 | P23: =IFERROR(__xludf.DUMMYFUNCTION("""COMPUTED_VALUE"""),22.0) -> 22 | Q23: =IFERROR(__xludf.DUMMYFUNCTION("""COMPUTED_VALUE"""),17.0) -> 17 | R23: =IFERROR(__xludf.DUMMYFUNCTION("""COMPUTED_VALUE"""),101.0) -> 101 | S23: =IFERROR(__xludf.DUMMYFUNCTION("""COMPUTED_VALUE"""),0.32673267326732675) -> 0.32673267 | T23: =IFERROR(__xludf.DUMMYFUNCTION("""COMPUTED_VALUE"""),282.5952380952381) -> 282.59524 | U23: =IFERROR(__xludf.DUMMYFUNCTION("""COMPUTED_VALUE"""),0.7857142857142857) -> 0.78571429 | V23: =IFERROR(__xludf.DUMMYFUNCTION("""COMPUTED_VALUE"""),0.5238095238095238) -> 0.52380952 | W23: =IFERROR(__xludf.DUMMYFUNCTION("""COMPUTED_VALUE"""),0.40476190476190477) -> 0.4047619 | X23: =IFERROR(__xludf.DUMMYFUNCTION("""COMPUTED_VALUE"""),2.4047619047619047) -> 2.4047619 | Y23: =IFERROR(__xludf.DUMMYFUNCTION("""COMPUTED_VALUE"""),4.0) -> 4 | Z23: =IFERROR(__xludf.DUMMYFUNCTION("""COMPUTED_VALUE"""),2.0) -> 2 | AA23: =IFERROR(__xludf.DUMMYFUNCTION("""COMPUTED_VALUE"""),0.0) -> 0 | AB23: =IFERROR(__xludf.DUMMYFUNCTION("""COMPUTED_VALUE"""),0.0) -> 0 | AC23: =IFERROR(__xludf.DUMMYFUNCTION("""COMPUTED_VALUE"""),54.0) -> 54 | AD23: =IFERROR(__xludf.DUMMYFUNCTION("""COMPUTED_VALUE"""),41.0) -> 41
A24: =IFERROR(__xludf.DUMMYFUNCTION("""COMPUTED_VALUE"""),"Amateur") -> Amateur | B24: =IFERROR(__xludf.DUMMYFUNCTION("""COMPUTED_VALUE"""),"RSC007161") -> RSC007161 | C24: =IFERROR(__xludf.DUMMYFUNCTION("""COMPUTED_VALUE"""),"MrAnderpants") -> MrAnderpants | D24: =IFERROR(__xludf.DUMMYFUNCTION("""COMPUTED_VALUE"""),"Winter Fresh Electric Eels Garlic Knots") -> Winter Fresh Electric Eels Garlic Knots | E24: =IFERROR(__xludf.DUMMYFUNCTION("""COMPUTED_VALUE"""),"N/A N/A N/A") -> N/A N/A N/A | F24: =IFERROR(__xludf.DUMMYFUNCTION("""COMPUTED_VALUE"""),58.43703465921884) -> 58.437035 | G24: =IFERROR(__xludf.DUMMYFUNCTION("""COMPUTED_VALUE"""),48.72013659312971) -> 48.720137 | H24: =IFERROR(__xludf.DUMMYFUNCTION("""COMPUTED_VALUE"""),53.578585626174274) -> 53.578586 | I24: =IFERROR(__xludf.DUMMYFUNCTION("""COMPUTED_VALUE"""),11.0) -> 11 | J24: =IFERROR(__xludf.DUMMYFUNCTION("IFERROR(FILTER(Stats!$F:$Z,(Stats!$A:$A=$A24)*(Stats!$B:$B=$B24)))"),5.0) -> 5 | K24: =IFERROR(__xludf.DUMMYFUNCTION("""COMPUTED_VALUE"""),6.0) -> 6 | L24: =IFERROR(__xludf.DUMMYFUNCTION("""COMPUTED_VALUE"""),0.45454545454545453) -> 0.45454545 | M24: =IFERROR(__xludf.DUMMYFUNCTION("""COMPUTED_VALUE"""),2.0) -> 2 | N24: =IFERROR(__xludf.DUMMYFUNCTION("""COMPUTED_VALUE"""),3510.0) -> 3510 | O24: =IFERROR(__xludf.DUMMYFUNCTION("""COMPUTED_VALUE"""),11.0) -> 11 | P24: =IFERROR(__xludf.DUMMYFUNCTION("""COMPUTED_VALUE"""),4.0) -> 4 | Q24: =IFERROR(__xludf.DUMMYFUNCTION("""COMPUTED_VALUE"""),11.0) -> 11 | R24: =IFERROR(__xludf.DUMMYFUNCTION("""COMPUTED_VALUE"""),22.0) -> 22 | S24: =IFERROR(__xludf.DUMMYFUNCTION("""COMPUTED_VALUE"""),0.5) -> 0.5 | T24: =IFERROR(__xludf.DUMMYFUNCTION("""COMPUTED_VALUE"""),319.09090909090907) -> 319.09091 | U24: =IFERROR(__xludf.DUMMYFUNCTION("""COMPUTED_VALUE"""),1.0) -> 1 | V24: =IFERROR(__xludf.DUMMYFUNCTION("""COMPUTED_VALUE"""),0.36363636363636365) -> 0.36363636 | W24: =IFERROR(__xludf.DUMMYFUNCTION("""COMPUTED_VALUE"""),1.0) -> 1 | X24: =IFERROR(__xludf.DUMMYFUNCTION("""COMPUTED_VALUE"""),2.0) -> 2 | Y24: =IFERROR(__xludf.DUMMYFUNCTION("""COMPUTED_VALUE"""),0.0) -> 0 | Z24: =IFERROR(__xludf.DUMMYFUNCTION("""COMPUTED_VALUE"""),0.0) -> 0 | AA24: =IFERROR(__xludf.DUMMYFUNCTION("""COMPUTED_VALUE"""),0.0) -> 0 | AB24: =IFERROR(__xludf.DUMMYFUNCTION("""COMPUTED_VALUE"""),0.0) -> 0 | AC24: =IFERROR(__xludf.DUMMYFUNCTION("""COMPUTED_VALUE"""),14.0) -> 14 | AD24: =IFERROR(__xludf.DUMMYFUNCTION("""COMPUTED_VALUE"""),9.0) -> 9
A25: =IFERROR(__xludf.DUMMYFUNCTION("""COMPUTED_VALUE"""),"Amateur") -> Amateur | B25: =IFERROR(__xludf.DUMMYFUNCTION("""COMPUTED_VALUE"""),"RSC000654") -> RSC000654 | C25: =IFERROR(__xludf.DUMMYFUNCTION("""COMPUTED_VALUE"""),"Rocci") -> Rocci | D25: =IFERROR(__xludf.DUMMYFUNCTION("""COMPUTED_VALUE"""),"Electric Eels") -> Electric Eels | E25: =IFERROR(__xludf.DUMMYFUNCTION("""COMPUTED_VALUE"""),"N/A") -> N/A | F25: =IFERROR(__xludf.DUMMYFUNCTION("""COMPUTED_VALUE"""),67.97782190763397) -> 67.977822 | G25: =IFERROR(__xludf.DUMMYFUNCTION("""COMPUTED_VALUE"""),38.4757798476672) -> 38.47578 | H25: =IFERROR(__xludf.DUMMYFUNCTION("""COMPUTED_VALUE"""),53.22680087765058) -> 53.226801 | I25: =IFERROR(__xludf.DUMMYFUNCTION("""COMPUTED_VALUE"""),4.0) -> 4 | J25: =IFERROR(__xludf.DUMMYFUNCTION("IFERROR(FILTER(Stats!$F:$Z,(Stats!$A:$A=$A25)*(Stats!$B:$B=$B25)))"),2.0) -> 2 | K25: =IFERROR(__xludf.DUMMYFUNCTION("""COMPUTED_VALUE"""),2.0) -> 2 | L25: =IFERROR(__xludf.DUMMYFUNCTION("""COMPUTED_VALUE"""),0.5) -> 0.5 | M25: =IFERROR(__xludf.DUMMYFUNCTION("""COMPUTED_VALUE"""),2.0) -> 2 | N25: =IFERROR(__xludf.DUMMYFUNCTION("""COMPUTED_VALUE"""),1118.0) -> 1118 | O25: =IFERROR(__xludf.DUMMYFUNCTION("""COMPUTED_VALUE"""),2.0) -> 2 | P25: =IFERROR(__xludf.DUMMYFUNCTION("""COMPUTED_VALUE"""),1.0) -> 1 | Q25: =IFERROR(__xludf.DUMMYFUNCTION("""COMPUTED_VALUE"""),6.0) -> 6 | R25: =IFERROR(__xludf.DUMMYFUNCTION("""COMPUTED_VALUE"""),5.0) -> 5 | S25: =IFERROR(__xludf.DUMMYFUNCTION("""COMPUTED_VALUE"""),0.4) -> 0.4 | T25: =IFERROR(__xludf.DUMMYFUNCTION("""COMPUTED_VALUE"""),279.5) -> 279.5 | U25: =IFERROR(__xludf.DUMMYFUNCTION("""COMPUTED_VALUE"""),0.5) -> 0.5 | V25: =IFERROR(__xludf.DUMMYFUNCTION("""COMPUTED_VALUE"""),0.25) -> 0.25 | W25: =IFERROR(__xludf.DUMMYFUNCTION("""COMPUTED_VALUE"""),1.5) -> 1.5 | X25: =IFERROR(__xludf.DUMMYFUNCTION("""COMPUTED_VALUE"""),1.25) -> 1.25 | Y25: =IFERROR(__xludf.DUMMYFUNCTION("""COMPUTED_VALUE"""),1.0) -> 1 | Z25: =IFERROR(__xludf.DUMMYFUNCTION("""COMPUTED_VALUE"""),0.0) -> 0 | AA25: =IFERROR(__xludf.DUMMYFUNCTION("""COMPUTED_VALUE"""),0.0) -> 0 | AB25: =IFERROR(__xludf.DUMMYFUNCTION("""COMPUTED_VALUE"""),1.0) -> 1 | AC25: =IFERROR(__xludf.DUMMYFUNCTION("""COMPUTED_VALUE"""),1.0) -> 1 | AD25: =IFERROR(__xludf.DUMMYFUNCTION("""COMPUTED_VALUE"""),0.0) -> 0
A26: =IFERROR(__xludf.DUMMYFUNCTION("""COMPUTED_VALUE"""),"Amateur") -> Amateur | B26: =IFERROR(__xludf.DUMMYFUNCTION("""COMPUTED_VALUE"""),"RSC008327") -> RSC008327 | C26: =IFERROR(__xludf.DUMMYFUNCTION("""COMPUTED_VALUE"""),"tempo_rl_ttv") -> tempo_rl_ttv | D26: =IFERROR(__xludf.DUMMYFUNCTION("""COMPUTED_VALUE"""),"Winter Fresh") -> Winter Fresh | E26: =IFERROR(__xludf.DUMMYFUNCTION("""COMPUTED_VALUE"""),"N/A") -> N/A | F26: =IFERROR(__xludf.DUMMYFUNCTION("""COMPUTED_VALUE"""),52.18672684751736) -> 52.186727 | G26: =IFERROR(__xludf.DUMMYFUNCTION("""COMPUTED_VALUE"""),52.56746177606754) -> 52.567462 | H26: =IFERROR(__xludf.DUMMYFUNCTION("""COMPUTED_VALUE"""),52.37709431179245) -> 52.377094 | I26: =IFERROR(__xludf.DUMMYFUNCTION("""COMPUTED_VALUE"""),36.0) -> 36 | J26: =IFERROR(__xludf.DUMMYFUNCTION("IFERROR(FILTER(Stats!$F:$Z,(Stats!$A:$A=$A26)*(Stats!$B:$B=$B26)))"),22.0) -> 22 | K26: =IFERROR(__xludf.DUMMYFUNCTION("""COMPUTED_VALUE"""),14.0) -> 14 | L26: =IFERROR(__xludf.DUMMYFUNCTION("""COMPUTED_VALUE"""),0.6111111111111112) -> 0.61111111 | M26: =IFERROR(__xludf.DUMMYFUNCTION("""COMPUTED_VALUE"""),9.0) -> 9 | N26: =IFERROR(__xludf.DUMMYFUNCTION("""COMPUTED_VALUE"""),10858.0) -> 10858 | O26: =IFERROR(__xludf.DUMMYFUNCTION("""COMPUTED_VALUE"""),28.0) -> 28 | P26: =IFERROR(__xludf.DUMMYFUNCTION("""COMPUTED_VALUE"""),14.0) -> 14 | Q26: =IFERROR(__xludf.DUMMYFUNCTION("""COMPUTED_VALUE"""),32.0) -> 32 | R26: =IFERROR(__xludf.DUMMYFUNCTION("""COMPUTED_VALUE"""),75.0) -> 75 | S26: =IFERROR(__xludf.DUMMYFUNCTION("""COMPUTED_VALUE"""),0.37333333333333335) -> 0.37333333 | T26: =IFERROR(__xludf.DUMMYFUNCTION("""COMPUTED_VALUE"""),301.6111111111111) -> 301.61111 | U26: =IFERROR(__xludf.DUMMYFUNCTION("""COMPUTED_VALUE"""),0.7777777777777778) -> 0.77777778 | V26: =IFERROR(__xludf.DUMMYFUNCTION("""COMPUTED_VALUE"""),0.3888888888888889) -> 0.38888889 | W26: =IFERROR(__xludf.DUMMYFUNCTION("""COMPUTED_VALUE"""),0.8888888888888888) -> 0.88888889 | X26: =IFERROR(__xludf.DUMMYFUNCTION("""COMPUTED_VALUE"""),2.0833333333333335) -> 2.0833333 | Y26: =IFERROR(__xludf.DUMMYFUNCTION("""COMPUTED_VALUE"""),5.0) -> 5 | Z26: =IFERROR(__xludf.DUMMYFUNCTION("""COMPUTED_VALUE"""),2.0) -> 2 | AA26: =IFERROR(__xludf.DUMMYFUNCTION("""COMPUTED_VALUE"""),0.0) -> 0 | AB26: =IFERROR(__xludf.DUMMYFUNCTION("""COMPUTED_VALUE"""),4.0) -> 4 | AC26: =IFERROR(__xludf.DUMMYFUNCTION("""COMPUTED_VALUE"""),51.0) -> 51 | AD26: =IFERROR(__xludf.DUMMYFUNCTION("""COMPUTED_VALUE"""),24.0) -> 24
A27: =IFERROR(__xludf.DUMMYFUNCTION("""COMPUTED_VALUE"""),"Amateur") -> Amateur | B27: =IFERROR(__xludf.DUMMYFUNCTION("""COMPUTED_VALUE"""),"RSC008130") -> RSC008130 | C27: =IFERROR(__xludf.DUMMYFUNCTION("""COMPUTED_VALUE"""),"BeardedFrodo1") -> BeardedFrodo1 | D27: =IFERROR(__xludf.DUMMYFUNCTION("""COMPUTED_VALUE"""),"Bombers") -> Bombers | E27: =IFERROR(__xludf.DUMMYFUNCTION("""COMPUTED_VALUE"""),"N/A") -> N/A | F27: =IFERROR(__xludf.DUMMYFUNCTION("""COMPUTED_VALUE"""),48.96800980931988) -> 48.96801 | G27: =IFERROR(__xludf.DUMMYFUNCTION("""COMPUTED_VALUE"""),55.56976004363583) -> 55.56976 | H27: =IFERROR(__xludf.DUMMYFUNCTION("""COMPUTED_VALUE"""),52.26888492647785) -> 52.268885 | I27: =IFERROR(__xludf.DUMMYFUNCTION("""COMPUTED_VALUE"""),55.0) -> 55 | J27: =IFERROR(__xludf.DUMMYFUNCTION("IFERROR(FILTER(Stats!$F:$Z,(Stats!$A:$A=$A27)*(Stats!$B:$B=$B27)))"),38.0) -> 38 | K27: =IFERROR(__xludf.DUMMYFUNCTION("""COMPUTED_VALUE"""),17.0) -> 17 | L27: =IFERROR(__xludf.DUMMYFUNCTION("""COMPUTED_VALUE"""),0.6909090909090909) -> 0.69090909 | M27: =IFERROR(__xludf.DUMMYFUNCTION("""COMPUTED_VALUE"""),13.0) -> 13 | N27: =IFERROR(__xludf.DUMMYFUNCTION("""COMPUTED_VALUE"""),16424.0) -> 16424 | O27: =IFERROR(__xludf.DUMMYFUNCTION("""COMPUTED_VALUE"""),44.0) -> 44 | P27: =IFERROR(__xludf.DUMMYFUNCTION("""COMPUTED_VALUE"""),23.0) -> 23 | Q27: =IFERROR(__xludf.DUMMYFUNCTION("""COMPUTED_VALUE"""),51.0) -> 51 | R27: =IFERROR(__xludf.DUMMYFUNCTION("""COMPUTED_VALUE"""),124.0) -> 124 | S27: =IFERROR(__xludf.DUMMYFUNCTION("""COMPUTED_VALUE"""),0.3548387096774194) -> 0.35483871 | T27: =IFERROR(__xludf.DUMMYFUNCTION("""COMPUTED_VALUE"""),298.6181818181818) -> 298.61818 | U27: =IFERROR(__xludf.DUMMYFUNCTION("""COMPUTED_VALUE"""),0.8) -> 0.8 | V27: =IFERROR(__xludf.DUMMYFUNCTION("""COMPUTED_VALUE"""),0.41818181818181815) -> 0.41818182 | W27: =IFERROR(__xludf.DUMMYFUNCTION("""COMPUTED_VALUE"""),0.9272727272727272) -> 0.92727273 | X27: =IFERROR(__xludf.DUMMYFUNCTION("""COMPUTED_VALUE"""),2.2545454545454544) -> 2.2545455 | Y27: =IFERROR(__xludf.DUMMYFUNCTION("""COMPUTED_VALUE"""),5.0) -> 5 | Z27: =IFERROR(__xludf.DUMMYFUNCTION("""COMPUTED_VALUE"""),2.0) -> 2 | AA27: =IFERROR(__xludf.DUMMYFUNCTION("""COMPUTED_VALUE"""),1.0) -> 1 | AB27: =IFERROR(__xludf.DUMMYFUNCTION("""COMPUTED_VALUE"""),1.0) -> 1 | AC27: =IFERROR(__xludf.DUMMYFUNCTION("""COMPUTED_VALUE"""),27.0) -> 27 | AD27: =IFERROR(__xludf.DUMMYFUNCTION("""COMPUTED_VALUE"""),36.0) -> 36
A28: =IFERROR(__xludf.DUMMYFUNCTION("""COMPUTED_VALUE"""),"Amateur") -> Amateur | B28: =IFERROR(__xludf.DUMMYFUNCTION("""COMPUTED_VALUE"""),"RSC004462") -> RSC004462 | C28: =IFERROR(__xludf.DUMMYFUNCTION("""COMPUTED_VALUE"""),"Bbcomedian") -> Bbcomedian | D28: =IFERROR(__xludf.DUMMYFUNCTION("""COMPUTED_VALUE"""),"Kappa") -> Kappa | E28: =IFERROR(__xludf.DUMMYFUNCTION("""COMPUTED_VALUE"""),"N/A") -> N/A | F28: =IFERROR(__xludf.DUMMYFUNCTION("""COMPUTED_VALUE"""),46.804496438714466) -> 46.804496 | G28: =IFERROR(__xludf.DUMMYFUNCTION("""COMPUTED_VALUE"""),49.05231144007971) -> 49.052311 | H28: =IFERROR(__xludf.DUMMYFUNCTION("""COMPUTED_VALUE"""),47.928403939397086) -> 47.928404 | I28: =IFERROR(__xludf.DUMMYFUNCTION("""COMPUTED_VALUE"""),55.0) -> 55 | J28: =IFERROR(__xludf.DUMMYFUNCTION("IFERROR(FILTER(Stats!$F:$Z,(Stats!$A:$A=$A28)*(Stats!$B:$B=$B28)))"),24.0) -> 24 | K28: =IFERROR(__xludf.DUMMYFUNCTION("""COMPUTED_VALUE"""),31.0) -> 31 | L28: =IFERROR(__xludf.DUMMYFUNCTION("""COMPUTED_VALUE"""),0.43636363636363634) -> 0.43636364 | M28: =IFERROR(__xludf.DUMMYFUNCTION("""COMPUTED_VALUE"""),6.0) -> 6 | N28: =IFERROR(__xludf.DUMMYFUNCTION("""COMPUTED_VALUE"""),16188.0) -> 16188 | O28: =IFERROR(__xludf.DUMMYFUNCTION("""COMPUTED_VALUE"""),43.0) -> 43 | P28: =IFERROR(__xludf.DUMMYFUNCTION("""COMPUTED_VALUE"""),25.0) -> 25 | Q28: =IFERROR(__xludf.DUMMYFUNCTION("""COMPUTED_VALUE"""),61.0) -> 61 | R28: =IFERROR(__xludf.DUMMYFUNCTION("""COMPUTED_VALUE"""),89.0) -> 89 | S28: =IFERROR(__xludf.DUMMYFUNCTION("""COMPUTED_VALUE"""),0.48314606741573035) -> 0.48314607 | T28: =IFERROR(__xludf.DUMMYFUNCTION("""COMPUTED_VALUE"""),294.3272727272727) -> 294.32727 | U28: =IFERROR(__xludf.DUMMYFUNCTION("""COMPUTED_VALUE"""),0.7818181818181819) -> 0.78181818 | V28: =IFERROR(__xludf.DUMMYFUNCTION("""COMPUTED_VALUE"""),0.45454545454545453) -> 0.45454545 | W28: =IFERROR(__xludf.DUMMYFUNCTION("""COMPUTED_VALUE"""),1.1090909090909091) -> 1.1090909 | X28: =IFERROR(__xludf.DUMMYFUNCTION("""COMPUTED_VALUE"""),1.6181818181818182) -> 1.6181818 | Y28: =IFERROR(__xludf.DUMMYFUNCTION("""COMPUTED_VALUE"""),6.0) -> 6 | Z28: =IFERROR(__xludf.DUMMYFUNCTION("""COMPUTED_VALUE"""),1.0) -> 1 | AA28: =IFERROR(__xludf.DUMMYFUNCTION("""COMPUTED_VALUE"""),1.0) -> 1 | AB28: =IFERROR(__xludf.DUMMYFUNCTION("""COMPUTED_VALUE"""),8.0) -> 8 | AC28: =IFERROR(__xludf.DUMMYFUNCTION("""COMPUTED_VALUE"""),16.0) -> 16 | AD28: =IFERROR(__xludf.DUMMYFUNCTION("""COMPUTED_VALUE"""),41.0) -> 41
A29: =IFERROR(__xludf.DUMMYFUNCTION("""COMPUTED_VALUE"""),"Amateur") -> Amateur | B29: =IFERROR(__xludf.DUMMYFUNCTION("""COMPUTED_VALUE"""),"RSC007573") -> RSC007573 | C29: =IFERROR(__xludf.DUMMYFUNCTION("""COMPUTED_VALUE"""),"zag_42") -> zag_42 | D29: =IFERROR(__xludf.DUMMYFUNCTION("""COMPUTED_VALUE"""),"Garlic Knots") -> Garlic Knots | E29: =IFERROR(__xludf.DUMMYFUNCTION("""COMPUTED_VALUE"""),"N/A") -> N/A | F29: =IFERROR(__xludf.DUMMYFUNCTION("""COMPUTED_VALUE"""),44.616689583932) -> 44.61669 | G29: =IFERROR(__xludf.DUMMYFUNCTION("""COMPUTED_VALUE"""),49.252886413310996) -> 49.252886 | H29: =IFERROR(__xludf.DUMMYFUNCTION("""COMPUTED_VALUE"""),46.9347879986215) -> 46.934788 | I29: =IFERROR(__xludf.DUMMYFUNCTION("""COMPUTED_VALUE"""),27.0) -> 27 | J29: =IFERROR(__xludf.DUMMYFUNCTION("IFERROR(FILTER(Stats!$F:$Z,(Stats!$A:$A=$A29)*(Stats!$B:$B=$B29)))"),12.0) -> 12 | K29: =IFERROR(__xludf.DUMMYFUNCTION("""COMPUTED_VALUE"""),15.0) -> 15 | L29: =IFERROR(__xludf.DUMMYFUNCTION("""COMPUTED_VALUE"""),0.4444444444444444) -> 0.44444444 | M29: =IFERROR(__xludf.DUMMYFUNCTION("""COMPUTED_VALUE"""),0.0) -> 0 | N29: =IFERROR(__xludf.DUMMYFUNCTION("""COMPUTED_VALUE"""),6727.0) -> 6727 | O29: =IFERROR(__xludf.DUMMYFUNCTION("""COMPUTED_VALUE"""),15.0) -> 15 | P29: =IFERROR(__xludf.DUMMYFUNCTION("""COMPUTED_VALUE"""),18.0) -> 18 | Q29: =IFERROR(__xludf.DUMMYFUNCTION("""COMPUTED_VALUE"""),18.0) -> 18 | R29: =IFERROR(__xludf.DUMMYFUNCTION("""COMPUTED_VALUE"""),38.0) -> 38 | S29: =IFERROR(__xludf.DUMMYFUNCTION("""COMPUTED_VALUE"""),0.39473684210526316) -> 0.39473684 | T29: =IFERROR(__xludf.DUMMYFUNCTION("""COMPUTED_VALUE"""),249.14814814814815) -> 249.14815 | U29: =IFERROR(__xludf.DUMMYFUNCTION("""COMPUTED_VALUE"""),0.5555555555555556) -> 0.55555556 | V29: =IFERROR(__xludf.DUMMYFUNCTION("""COMPUTED_VALUE"""),0.6666666666666666) -> 0.66666667 | W29: =IFERROR(__xludf.DUMMYFUNCTION("""COMPUTED_VALUE"""),0.6666666666666666) -> 0.66666667 | X29: =IFERROR(__xludf.DUMMYFUNCTION("""COMPUTED_VALUE"""),1.4074074074074074) -> 1.4074074 | Y29: =IFERROR(__xludf.DUMMYFUNCTION("""COMPUTED_VALUE"""),1.0) -> 1 | Z29: =IFERROR(__xludf.DUMMYFUNCTION("""COMPUTED_VALUE"""),0.0) -> 0 | AA29: =IFERROR(__xludf.DUMMYFUNCTION("""COMPUTED_VALUE"""),1.0) -> 1 | AB29: =IFERROR(__xludf.DUMMYFUNCTION("""COMPUTED_VALUE"""),0.0) -> 0 | AC29: =IFERROR(__xludf.DUMMYFUNCTION("""COMPUTED_VALUE"""),9.0) -> 9 | AD29: =IFERROR(__xludf.DUMMYFUNCTION("""COMPUTED_VALUE"""),25.0) -> 25
A30: =IFERROR(__xludf.DUMMYFUNCTION("""COMPUTED_VALUE"""),"Amateur") -> Amateur | B30: =IFERROR(__xludf.DUMMYFUNCTION("""COMPUTED_VALUE"""),"RSC008131") -> RSC008131 | C30: =IFERROR(__xludf.DUMMYFUNCTION("""COMPUTED_VALUE"""),"chrisofspades") -> chrisofspades | D30: =IFERROR(__xludf.DUMMYFUNCTION("""COMPUTED_VALUE"""),"HR Violation") -> HR Violation | E30: =IFERROR(__xludf.DUMMYFUNCTION("""COMPUTED_VALUE"""),"N/A") -> N/A | F30: =IFERROR(__xludf.DUMMYFUNCTION("""COMPUTED_VALUE"""),44.15908093947458) -> 44.159081 | G30: =IFERROR(__xludf.DUMMYFUNCTION("""COMPUTED_VALUE"""),45.22767462395146) -> 45.227675 | H30: =IFERROR(__xludf.DUMMYFUNCTION("""COMPUTED_VALUE"""),44.69337778171302) -> 44.693378 | I30: =IFERROR(__xludf.DUMMYFUNCTION("""COMPUTED_VALUE"""),36.0) -> 36 | J30: =IFERROR(__xludf.DUMMYFUNCTION("IFERROR(FILTER(Stats!$F:$Z,(Stats!$A:$A=$A30)*(Stats!$B:$B=$B30)))"),19.0) -> 19 | K30: =IFERROR(__xludf.DUMMYFUNCTION("""COMPUTED_VALUE"""),17.0) -> 17 | L30: =IFERROR(__xludf.DUMMYFUNCTION("""COMPUTED_VALUE"""),0.5277777777777778) -> 0.52777778 | M30: =IFERROR(__xludf.DUMMYFUNCTION("""COMPUTED_VALUE"""),2.0) -> 2 | N30: =IFERROR(__xludf.DUMMYFUNCTION("""COMPUTED_VALUE"""),9944.0) -> 9944 | O30: =IFERROR(__xludf.DUMMYFUNCTION("""COMPUTED_VALUE"""),19.0) -> 19 | P30: =IFERROR(__xludf.DUMMYFUNCTION("""COMPUTED_VALUE"""),18.0) -> 18 | Q30: =IFERROR(__xludf.DUMMYFUNCTION("""COMPUTED_VALUE"""),36.0) -> 36 | R30: =IFERROR(__xludf.DUMMYFUNCTION("""COMPUTED_VALUE"""),58.0) -> 58 | S30: =IFERROR(__xludf.DUMMYFUNCTION("""COMPUTED_VALUE"""),0.3275862068965517) -> 0.32758621 | T30: =IFERROR(__xludf.DUMMYFUNCTION("""COMPUTED_VALUE"""),276.22222222222223) -> 276.22222 | U30: =IFERROR(__xludf.DUMMYFUNCTION("""COMPUTED_VALUE"""),0.5277777777777778) -> 0.52777778 | V30: =IFERROR(__xludf.DUMMYFUNCTION("""COMPUTED_VALUE"""),0.5) -> 0.5 | W30: =IFERROR(__xludf.DUMMYFUNCTION("""COMPUTED_VALUE"""),1.0) -> 1 | X30: =IFERROR(__xludf.DUMMYFUNCTION("""COMPUTED_VALUE"""),1.6111111111111112) -> 1.6111111 | Y30: =IFERROR(__xludf.DUMMYFUNCTION("""COMPUTED_VALUE"""),4.0) -> 4 | Z30: =IFERROR(__xludf.DUMMYFUNCTION("""COMPUTED_VALUE"""),1.0) -> 1 | AA30: =IFERROR(__xludf.DUMMYFUNCTION("""COMPUTED_VALUE"""),0.0) -> 0 | AB30: =IFERROR(__xludf.DUMMYFUNCTION("""COMPUTED_VALUE"""),3.0) -> 3 | AC30: =IFERROR(__xludf.DUMMYFUNCTION("""COMPUTED_VALUE"""),17.0) -> 17 | AD30: =IFERROR(__xludf.DUMMYFUNCTION("""COMPUTED_VALUE"""),23.0) -> 23
A31: =IFERROR(__xludf.DUMMYFUNCTION("""COMPUTED_VALUE"""),"Amateur") -> Amateur | B31: =IFERROR(__xludf.DUMMYFUNCTION("""COMPUTED_VALUE"""),"RSC008419") -> RSC008419 | C31: =IFERROR(__xludf.DUMMYFUNCTION("""COMPUTED_VALUE"""),"iSilently") -> iSilently | D31: =IFERROR(__xludf.DUMMYFUNCTION("""COMPUTED_VALUE"""),"Chimera") -> Chimera | E31: =IFERROR(__xludf.DUMMYFUNCTION("""COMPUTED_VALUE"""),"N/A") -> N/A | F31: =IFERROR(__xludf.DUMMYFUNCTION("""COMPUTED_VALUE"""),43.17651051169967) -> 43.176511 | G31: =IFERROR(__xludf.DUMMYFUNCTION("""COMPUTED_VALUE"""),46.117868291511904) -> 46.117868 | H31: =IFERROR(__xludf.DUMMYFUNCTION("""COMPUTED_VALUE"""),44.647189401605786) -> 44.647189 | I31: =IFERROR(__xludf.DUMMYFUNCTION("""COMPUTED_VALUE"""),45.0) -> 45 | J31: =IFERROR(__xludf.DUMMYFUNCTION("IFERROR(FILTER(Stats!$F:$Z,(Stats!$A:$A=$A31)*(Stats!$B:$B=$B31)))"),26.0) -> 26 | K31: =IFERROR(__xludf.DUMMYFUNCTION("""COMPUTED_VALUE"""),19.0) -> 19 | L31: =IFERROR(__xludf.DUMMYFUNCTION("""COMPUTED_VALUE"""),0.5777777777777777) -> 0.57777778 | M31: =IFERROR(__xludf.DUMMYFUNCTION("""COMPUTED_VALUE"""),7.0) -> 7 | N31: =IFERROR(__xludf.DUMMYFUNCTION("""COMPUTED_VALUE"""),14892.0) -> 14892 | O31: =IFERROR(__xludf.DUMMYFUNCTION("""COMPUTED_VALUE"""),31.0) -> 31 | P31: =IFERROR(__xludf.DUMMYFUNCTION("""COMPUTED_VALUE"""),12.0) -> 12 | Q31: =IFERROR(__xludf.DUMMYFUNCTION("""COMPUTED_VALUE"""),77.0) -> 77 | R31: =IFERROR(__xludf.DUMMYFUNCTION("""COMPUTED_VALUE"""),93.0) -> 93 | S31: =IFERROR(__xludf.DUMMYFUNCTION("""COMPUTED_VALUE"""),0.3333333333333333) -> 0.33333333 | T31: =IFERROR(__xludf.DUMMYFUNCTION("""COMPUTED_VALUE"""),330.93333333333334) -> 330.93333 | U31: =IFERROR(__xludf.DUMMYFUNCTION("""COMPUTED_VALUE"""),0.6888888888888889) -> 0.68888889 | V31: =IFERROR(__xludf.DUMMYFUNCTION("""COMPUTED_VALUE"""),0.26666666666666666) -> 0.26666667 | W31: =IFERROR(__xludf.DUMMYFUNCTION("""COMPUTED_VALUE"""),1.711111111111111) -> 1.7111111 | X31: =IFERROR(__xludf.DUMMYFUNCTION("""COMPUTED_VALUE"""),2.066666666666667) -> 2.0666667 | Y31: =IFERROR(__xludf.DUMMYFUNCTION("""COMPUTED_VALUE"""),3.0) -> 3 | Z31: =IFERROR(__xludf.DUMMYFUNCTION("""COMPUTED_VALUE"""),1.0) -> 1 | AA31: =IFERROR(__xludf.DUMMYFUNCTION("""COMPUTED_VALUE"""),0.0) -> 0 | AB31: =IFERROR(__xludf.DUMMYFUNCTION("""COMPUTED_VALUE"""),10.0) -> 10 | AC31: =IFERROR(__xludf.DUMMYFUNCTION("""COMPUTED_VALUE"""),44.0) -> 44 | AD31: =IFERROR(__xludf.DUMMYFUNCTION("""COMPUTED_VALUE"""),24.0) -> 24
A32: =IFERROR(__xludf.DUMMYFUNCTION("""COMPUTED_VALUE"""),"Amateur") -> Amateur | B32: =IFERROR(__xludf.DUMMYFUNCTION("""COMPUTED_VALUE"""),"RSC008083") -> RSC008083 | C32: =IFERROR(__xludf.DUMMYFUNCTION("""COMPUTED_VALUE"""),"Rocketgirl_32") -> Rocketgirl_32 | D32: =IFERROR(__xludf.DUMMYFUNCTION("""COMPUTED_VALUE"""),"Legionaries") -> Legionaries | E32: =IFERROR(__xludf.DUMMYFUNCTION("""COMPUTED_VALUE"""),"N/A") -> N/A | F32: =IFERROR(__xludf.DUMMYFUNCTION("""COMPUTED_VALUE"""),44.453903579860835) -> 44.453904 | G32: =IFERROR(__xludf.DUMMYFUNCTION("""COMPUTED_VALUE"""),39.203007185875975) -> 39.203007 | H32: =IFERROR(__xludf.DUMMYFUNCTION("""COMPUTED_VALUE"""),41.828455382868405) -> 41.828455 | I32: =IFERROR(__xludf.DUMMYFUNCTION("""COMPUTED_VALUE"""),55.0) -> 55 | J32: =IFERROR(__xludf.DUMMYFUNCTION("IFERROR(FILTER(Stats!$F:$Z,(Stats!$A:$A=$A32)*(Stats!$B:$B=$B32)))"),13.0) -> 13 | K32: =IFERROR(__xludf.DUMMYFUNCTION("""COMPUTED_VALUE"""),42.0) -> 42 | L32: =IFERROR(__xludf.DUMMYFUNCTION("""COMPUTED_VALUE"""),0.23636363636363636) -> 0.23636364 | M32: =IFERROR(__xludf.DUMMYFUNCTION("""COMPUTED_VALUE"""),8.0) -> 8 | N32: =IFERROR(__xludf.DUMMYFUNCTION("""COMPUTED_VALUE"""),17476.0) -> 17476 | O32: =IFERROR(__xludf.DUMMYFUNCTION("""COMPUTED_VALUE"""),36.0) -> 36 | P32: =IFERROR(__xludf.DUMMYFUNCTION("""COMPUTED_VALUE"""),10.0) -> 10 | Q32: =IFERROR(__xludf.DUMMYFUNCTION("""COMPUTED_VALUE"""),84.0) -> 84 | R32: =IFERROR(__xludf.DUMMYFUNCTION("""COMPUTED_VALUE"""),121.0) -> 121 | S32: =IFERROR(__xludf.DUMMYFUNCTION("""COMPUTED_VALUE"""),0.2975206611570248) -> 0.29752066 | T32: =IFERROR(__xludf.DUMMYFUNCTION("""COMPUTED_VALUE"""),317.74545454545455) -> 317.74545 | U32: =IFERROR(__xludf.DUMMYFUNCTION("""COMPUTED_VALUE"""),0.6545454545454545) -> 0.65454545 | V32: =IFERROR(__xludf.DUMMYFUNCTION("""COMPUTED_VALUE"""),0.18181818181818182) -> 0.18181818 | W32: =IFERROR(__xludf.DUMMYFUNCTION("""COMPUTED_VALUE"""),1.5272727272727273) -> 1.5272727 | X32: =IFERROR(__xludf.DUMMYFUNCTION("""COMPUTED_VALUE"""),2.2) -> 2.2 | Y32: =IFERROR(__xludf.DUMMYFUNCTION("""COMPUTED_VALUE"""),3.0) -> 3 | Z32: =IFERROR(__xludf.DUMMYFUNCTION("""COMPUTED_VALUE"""),1.0) -> 1 | AA32: =IFERROR(__xludf.DUMMYFUNCTION("""COMPUTED_VALUE"""),0.0) -> 0 | AB32: =IFERROR(__xludf.DUMMYFUNCTION("""COMPUTED_VALUE"""),11.0) -> 11 | AC32: =IFERROR(__xludf.DUMMYFUNCTION("""COMPUTED_VALUE"""),27.0) -> 27 | AD32: =IFERROR(__xludf.DUMMYFUNCTION("""COMPUTED_VALUE"""),47.0) -> 47
A33: =IFERROR(__xludf.DUMMYFUNCTION("""COMPUTED_VALUE"""),"Amateur") -> Amateur | B33: =IFERROR(__xludf.DUMMYFUNCTION("""COMPUTED_VALUE"""),"RSC007216") -> RSC007216 | C33: =IFERROR(__xludf.DUMMYFUNCTION("""COMPUTED_VALUE"""),"ASAPxLEG") -> ASAPxLEG | D33: =IFERROR(__xludf.DUMMYFUNCTION("""COMPUTED_VALUE"""),"Kappa") -> Kappa | E33: =IFERROR(__xludf.DUMMYFUNCTION("""COMPUTED_VALUE"""),"N/A") -> N/A | F33: =IFERROR(__xludf.DUMMYFUNCTION("""COMPUTED_VALUE"""),40.18903633607552) -> 40.189036 | G33: =IFERROR(__xludf.DUMMYFUNCTION("""COMPUTED_VALUE"""),41.58982015505339) -> 41.58982 | H33: =IFERROR(__xludf.DUMMYFUNCTION("""COMPUTED_VALUE"""),40.88942824556445) -> 40.889428 | I33: =IFERROR(__xludf.DUMMYFUNCTION("""COMPUTED_VALUE"""),51.0) -> 51 | J33: =IFERROR(__xludf.DUMMYFUNCTION("IFERROR(FILTER(Stats!$F:$Z,(Stats!$A:$A=$A33)*(Stats!$B:$B=$B33)))"),23.0) -> 23 | K33: =IFERROR(__xludf.DUMMYFUNCTION("""COMPUTED_VALUE"""),28.0) -> 28 | L33: =IFERROR(__xludf.DUMMYFUNCTION("""COMPUTED_VALUE"""),0.45098039215686275) -> 0.45098039 | M33: =IFERROR(__xludf.DUMMYFUNCTION("""COMPUTED_VALUE"""),4.0) -> 4 | N33: =IFERROR(__xludf.DUMMYFUNCTION("""COMPUTED_VALUE"""),13363.0) -> 13363 | O33: =IFERROR(__xludf.DUMMYFUNCTION("""COMPUTED_VALUE"""),25.0) -> 25 | P33: =IFERROR(__xludf.DUMMYFUNCTION("""COMPUTED_VALUE"""),27.0) -> 27 | Q33: =IFERROR(__xludf.DUMMYFUNCTION("""COMPUTED_VALUE"""),45.0) -> 45 | R33: =IFERROR(__xludf.DUMMYFUNCTION("""COMPUTED_VALUE"""),69.0) -> 69 | S33: =IFERROR(__xludf.DUMMYFUNCTION("""COMPUTED_VALUE"""),0.36231884057971014) -> 0.36231884 | T33: =IFERROR(__xludf.DUMMYFUNCTION("""COMPUTED_VALUE"""),262.01960784313724) -> 262.01961 | U33: =IFERROR(__xludf.DUMMYFUNCTION("""COMPUTED_VALUE"""),0.49019607843137253) -> 0.49019608 | V33: =IFERROR(__xludf.DUMMYFUNCTION("""COMPUTED_VALUE"""),0.5294117647058824) -> 0.52941176 | W33: =IFERROR(__xludf.DUMMYFUNCTION("""COMPUTED_VALUE"""),0.8823529411764706) -> 0.88235294 | X33: =IFERROR(__xludf.DUMMYFUNCTION("""COMPUTED_VALUE"""),1.3529411764705883) -> 1.3529412 | Y33: =IFERROR(__xludf.DUMMYFUNCTION("""COMPUTED_VALUE"""),3.0) -> 3 | Z33: =IFERROR(__xludf.DUMMYFUNCTION("""COMPUTED_VALUE"""),1.0) -> 1 | AA33: =IFERROR(__xludf.DUMMYFUNCTION("""COMPUTED_VALUE"""),1.0) -> 1 | AB33: =IFERROR(__xludf.DUMMYFUNCTION("""COMPUTED_VALUE"""),1.0) -> 1 | AC33: =IFERROR(__xludf.DUMMYFUNCTION("""COMPUTED_VALUE"""),26.0) -> 26 | AD33: =IFERROR(__xludf.DUMMYFUNCTION("""COMPUTED_VALUE"""),35.0) -> 35
A34: =IFERROR(__xludf.DUMMYFUNCTION("""COMPUTED_VALUE"""),"Amateur") -> Amateur | B34: =IFERROR(__xludf.DUMMYFUNCTION("""COMPUTED_VALUE"""),"RSC006137") -> RSC006137 | C34: =IFERROR(__xludf.DUMMYFUNCTION("""COMPUTED_VALUE"""),"FULLBL00DN8V") -> FULLBL00DN8V | D34: =IFERROR(__xludf.DUMMYFUNCTION("""COMPUTED_VALUE"""),"Electric Eels") -> Electric Eels | E34: =IFERROR(__xludf.DUMMYFUNCTION("""COMPUTED_VALUE"""),"N/A") -> N/A | F34: =IFERROR(__xludf.DUMMYFUNCTION("""COMPUTED_VALUE"""),33.883042535929505) -> 33.883043 | G34: =IFERROR(__xludf.DUMMYFUNCTION("""COMPUTED_VALUE"""),41.43308901386139) -> 41.433089 | H34: =IFERROR(__xludf.DUMMYFUNCTION("""COMPUTED_VALUE"""),37.65806577489545) -> 37.658066 | I34: =IFERROR(__xludf.DUMMYFUNCTION("""COMPUTED_VALUE"""),28.0) -> 28 | J34: =IFERROR(__xludf.DUMMYFUNCTION("IFERROR(FILTER(Stats!$F:$Z,(Stats!$A:$A=$A34)*(Stats!$B:$B=$B34)))"),13.0) -> 13 | K34: =IFERROR(__xludf.DUMMYFUNCTION("""COMPUTED_VALUE"""),15.0) -> 15 | L34: =IFERROR(__xludf.DUMMYFUNCTION("""COMPUTED_VALUE"""),0.4642857142857143) -> 0.46428571 | M34: =IFERROR(__xludf.DUMMYFUNCTION("""COMPUTED_VALUE"""),5.0) -> 5 | N34: =IFERROR(__xludf.DUMMYFUNCTION("""COMPUTED_VALUE"""),7237.0) -> 7237 | O34: =IFERROR(__xludf.DUMMYFUNCTION("""COMPUTED_VALUE"""),15.0) -> 15 | P34: =IFERROR(__xludf.DUMMYFUNCTION("""COMPUTED_VALUE"""),11.0) -> 11 | Q34: =IFERROR(__xludf.DUMMYFUNCTION("""COMPUTED_VALUE"""),30.0) -> 30 | R34: =IFERROR(__xludf.DUMMYFUNCTION("""COMPUTED_VALUE"""),49.0) -> 49 | S34: =IFERROR(__xludf.DUMMYFUNCTION("""COMPUTED_VALUE"""),0.30612244897959184) -> 0.30612245 | T34: =IFERROR(__xludf.DUMMYFUNCTION("""COMPUTED_VALUE"""),258.4642857142857) -> 258.46429 | U34: =IFERROR(__xludf.DUMMYFUNCTION("""COMPUTED_VALUE"""),0.5357142857142857) -> 0.53571429 | V34: =IFERROR(__xludf.DUMMYFUNCTION("""COMPUTED_VALUE"""),0.39285714285714285) -> 0.39285714 | W34: =IFERROR(__xludf.DUMMYFUNCTION("""COMPUTED_VALUE"""),1.0714285714285714) -> 1.0714286 | X34: =IFERROR(__xludf.DUMMYFUNCTION("""COMPUTED_VALUE"""),1.75) -> 1.75 | Y34: =IFERROR(__xludf.DUMMYFUNCTION("""COMPUTED_VALUE"""),3.0) -> 3 | Z34: =IFERROR(__xludf.DUMMYFUNCTION("""COMPUTED_VALUE"""),2.0) -> 2 | AA34: =IFERROR(__xludf.DUMMYFUNCTION("""COMPUTED_VALUE"""),0.0) -> 0 | AB34: =IFERROR(__xludf.DUMMYFUNCTION("""COMPUTED_VALUE"""),3.0) -> 3 | AC34: =IFERROR(__xludf.DUMMYFUNCTION("""COMPUTED_VALUE"""),19.0) -> 19 | AD34: =IFERROR(__xludf.DUMMYFUNCTION("""COMPUTED_VALUE"""),10.0) -> 10
A35: =IFERROR(__xludf.DUMMYFUNCTION("""COMPUTED_VALUE"""),"Amateur") -> Amateur | B35: =IFERROR(__xludf.DUMMYFUNCTION("""COMPUTED_VALUE"""),"RSC007921") -> RSC007921 | C35: =IFERROR(__xludf.DUMMYFUNCTION("""COMPUTED_VALUE"""),"sXCyBeast") -> sXCyBeast | D35: =IFERROR(__xludf.DUMMYFUNCTION("""COMPUTED_VALUE"""),"HR Violation") -> HR Violation | E35: =IFERROR(__xludf.DUMMYFUNCTION("""COMPUTED_VALUE"""),"N/A") -> N/A | F35: =IFERROR(__xludf.DUMMYFUNCTION("""COMPUTED_VALUE"""),30.355736398311503) -> 30.355736 | G35: =IFERROR(__xludf.DUMMYFUNCTION("""COMPUTED_VALUE"""),40.44978159359282) -> 40.449782 | H35: =IFERROR(__xludf.DUMMYFUNCTION("""COMPUTED_VALUE"""),35.40275899595216) -> 35.402759 | I35: =IFERROR(__xludf.DUMMYFUNCTION("""COMPUTED_VALUE"""),56.0) -> 56 | J35: =IFERROR(__xludf.DUMMYFUNCTION("IFERROR(FILTER(Stats!$F:$Z,(Stats!$A:$A=$A35)*(Stats!$B:$B=$B35)))"),27.0) -> 27 | K35: =IFERROR(__xludf.DUMMYFUNCTION("""COMPUTED_VALUE"""),29.0) -> 29 | L35: =IFERROR(__xludf.DUMMYFUNCTION("""COMPUTED_VALUE"""),0.48214285714285715) -> 0.48214286 | M35: =IFERROR(__xludf.DUMMYFUNCTION("""COMPUTED_VALUE"""),7.0) -> 7 | N35: =IFERROR(__xludf.DUMMYFUNCTION("""COMPUTED_VALUE"""),14400.0) -> 14400 | O35: =IFERROR(__xludf.DUMMYFUNCTION("""COMPUTED_VALUE"""),31.0) -> 31 | P35: =IFERROR(__xludf.DUMMYFUNCTION("""COMPUTED_VALUE"""),21.0) -> 21 | Q35: =IFERROR(__xludf.DUMMYFUNCTION("""COMPUTED_VALUE"""),66.0) -> 66 | R35: =IFERROR(__xludf.DUMMYFUNCTION("""COMPUTED_VALUE"""),93.0) -> 93 | S35: =IFERROR(__xludf.DUMMYFUNCTION("""COMPUTED_VALUE"""),0.3333333333333333) -> 0.33333333 | T35: =IFERROR(__xludf.DUMMYFUNCTION("""COMPUTED_VALUE"""),257.14285714285717) -> 257.14286 | U35: =IFERROR(__xludf.DUMMYFUNCTION("""COMPUTED_VALUE"""),0.5535714285714286) -> 0.55357143 | V35: =IFERROR(__xludf.DUMMYFUNCTION("""COMPUTED_VALUE"""),0.375) -> 0.375 | W35: =IFERROR(__xludf.DUMMYFUNCTION("""COMPUTED_VALUE"""),1.1785714285714286) -> 1.1785714 | X35: =IFERROR(__xludf.DUMMYFUNCTION("""COMPUTED_VALUE"""),1.6607142857142858) -> 1.6607143 | Y35: =IFERROR(__xludf.DUMMYFUNCTION("""COMPUTED_VALUE"""),8.0) -> 8 | Z35: =IFERROR(__xludf.DUMMYFUNCTION("""COMPUTED_VALUE"""),1.0) -> 1 | AA35: =IFERROR(__xludf.DUMMYFUNCTION("""COMPUTED_VALUE"""),1.0) -> 1 | AB35: =IFERROR(__xludf.DUMMYFUNCTION("""COMPUTED_VALUE"""),5.0) -> 5 | AC35: =IFERROR(__xludf.DUMMYFUNCTION("""COMPUTED_VALUE"""),61.0) -> 61 | AD35: =IFERROR(__xludf.DUMMYFUNCTION("""COMPUTED_VALUE"""),36.0) -> 36
A36: =IFERROR(__xludf.DUMMYFUNCTION("""COMPUTED_VALUE"""),"Amateur") -> Amateur | B36: =IFERROR(__xludf.DUMMYFUNCTION("""COMPUTED_VALUE"""),"RSC007462") -> RSC007462 | C36: =IFERROR(__xludf.DUMMYFUNCTION("""COMPUTED_VALUE"""),"Lil DizNick") -> Lil DizNick | D36: =IFERROR(__xludf.DUMMYFUNCTION("""COMPUTED_VALUE"""),"Winter Fresh") -> Winter Fresh | E36: =IFERROR(__xludf.DUMMYFUNCTION("""COMPUTED_VALUE"""),"N/A") -> N/A | F36: =IFERROR(__xludf.DUMMYFUNCTION("""COMPUTED_VALUE"""),35.230219589530975) -> 35.23022 | G36: =IFERROR(__xludf.DUMMYFUNCTION("""COMPUTED_VALUE"""),30.15896447794128) -> 30.158964 | H36: =IFERROR(__xludf.DUMMYFUNCTION("""COMPUTED_VALUE"""),32.69459203373613) -> 32.694592 | I36: =IFERROR(__xludf.DUMMYFUNCTION("""COMPUTED_VALUE"""),4.0) -> 4 | J36: =IFERROR(__xludf.DUMMYFUNCTION("IFERROR(FILTER(Stats!$F:$Z,(Stats!$A:$A=$A36)*(Stats!$B:$B=$B36)))"),0.0) -> 0 | K36: =IFERROR(__xludf.DUMMYFUNCTION("""COMPUTED_VALUE"""),4.0) -> 4 | L36: =IFERROR(__xludf.DUMMYFUNCTION("""COMPUTED_VALUE"""),0.0) -> 0 | M36: =IFERROR(__xludf.DUMMYFUNCTION("""COMPUTED_VALUE"""),0.0) -> 0 | N36: =IFERROR(__xludf.DUMMYFUNCTION("""COMPUTED_VALUE"""),1077.0) -> 1077 | O36: =IFERROR(__xludf.DUMMYFUNCTION("""COMPUTED_VALUE"""),2.0) -> 2 | P36: =IFERROR(__xludf.DUMMYFUNCTION("""COMPUTED_VALUE"""),1.0) -> 1 | Q36: =IFERROR(__xludf.DUMMYFUNCTION("""COMPUTED_VALUE"""),4.0) -> 4 | R36: =IFERROR(__xludf.DUMMYFUNCTION("""COMPUTED_VALUE"""),7.0) -> 7 | S36: =IFERROR(__xludf.DUMMYFUNCTION("""COMPUTED_VALUE"""),0.2857142857142857) -> 0.28571429 | T36: =IFERROR(__xludf.DUMMYFUNCTION("""COMPUTED_VALUE"""),269.25) -> 269.25 | U36: =IFERROR(__xludf.DUMMYFUNCTION("""COMPUTED_VALUE"""),0.5) -> 0.5 | V36: =IFERROR(__xludf.DUMMYFUNCTION("""COMPUTED_VALUE"""),0.25) -> 0.25 | W36: =IFERROR(__xludf.DUMMYFUNCTION("""COMPUTED_VALUE"""),1.0) -> 1 | X36: =IFERROR(__xludf.DUMMYFUNCTION("""COMPUTED_VALUE"""),1.75) -> 1.75 | Y36: =IFERROR(__xludf.DUMMYFUNCTION("""COMPUTED_VALUE"""),0.0) -> 0 | Z36: =IFERROR(__xludf.DUMMYFUNCTION("""COMPUTED_VALUE"""),0.0) -> 0 | AA36: =IFERROR(__xludf.DUMMYFUNCTION("""COMPUTED_VALUE"""),0.0) -> 0 | AB36: =IFERROR(__xludf.DUMMYFUNCTION("""COMPUTED_VALUE"""),0.0) -> 0 | AC36: =IFERROR(__xludf.DUMMYFUNCTION("""COMPUTED_VALUE"""),5.0) -> 5 | AD36: =IFERROR(__xludf.DUMMYFUNCTION("""COMPUTED_VALUE"""),8.0) -> 8
A37: =IFERROR(__xludf.DUMMYFUNCTION("""COMPUTED_VALUE"""),"Amateur") -> Amateur | B37: =IFERROR(__xludf.DUMMYFUNCTION("""COMPUTED_VALUE"""),"RSC000323") -> RSC000323 | C37: =IFERROR(__xludf.DUMMYFUNCTION("""COMPUTED_VALUE"""),"Styk75") -> Styk75 | D37: =IFERROR(__xludf.DUMMYFUNCTION("""COMPUTED_VALUE"""),"Legionaries") -> Legionaries | E37: =IFERROR(__xludf.DUMMYFUNCTION("""COMPUTED_VALUE"""),"N/A") -> N/A | F37: =IFERROR(__xludf.DUMMYFUNCTION("""COMPUTED_VALUE"""),24.570478544163738) -> 24.570479 | G37: =IFERROR(__xludf.DUMMYFUNCTION("""COMPUTED_VALUE"""),29.31093525791619) -> 29.310935 | H37: =IFERROR(__xludf.DUMMYFUNCTION("""COMPUTED_VALUE"""),26.940706901039963) -> 26.940707 | I37: =IFERROR(__xludf.DUMMYFUNCTION("""COMPUTED_VALUE"""),49.0) -> 49 | J37: =IFERROR(__xludf.DUMMYFUNCTION("IFERROR(FILTER(Stats!$F:$Z,(Stats!$A:$A=$A37)*(Stats!$B:$B=$B37)))"),13.0) -> 13 | K37: =IFERROR(__xludf.DUMMYFUNCTION("""COMPUTED_VALUE"""),36.0) -> 36 | L37: =IFERROR(__xludf.DUMMYFUNCTION("""COMPUTED_VALUE"""),0.2653061224489796) -> 0.26530612 | M37: =IFERROR(__xludf.DUMMYFUNCTION("""COMPUTED_VALUE"""),4.0) -> 4 | N37: =IFERROR(__xludf.DUMMYFUNCTION("""COMPUTED_VALUE"""),12519.0) -> 12519 | O37: =IFERROR(__xludf.DUMMYFUNCTION("""COMPUTED_VALUE"""),19.0) -> 19 | P37: =IFERROR(__xludf.DUMMYFUNCTION("""COMPUTED_VALUE"""),14.0) -> 14 | Q37: =IFERROR(__xludf.DUMMYFUNCTION("""COMPUTED_VALUE"""),54.0) -> 54 | R37: =IFERROR(__xludf.DUMMYFUNCTION("""COMPUTED_VALUE"""),81.0) -> 81 | S37: =IFERROR(__xludf.DUMMYFUNCTION("""COMPUTED_VALUE"""),0.2345679012345679) -> 0.2345679 | T37: =IFERROR(__xludf.DUMMYFUNCTION("""COMPUTED_VALUE"""),255.48979591836735) -> 255.4898 | U37: =IFERROR(__xludf.DUMMYFUNCTION("""COMPUTED_VALUE"""),0.3877551020408163) -> 0.3877551 | V37: =IFERROR(__xludf.DUMMYFUNCTION("""COMPUTED_VALUE"""),0.2857142857142857) -> 0.28571429 | W37: =IFERROR(__xludf.DUMMYFUNCTION("""COMPUTED_VALUE"""),1.1020408163265305) -> 1.1020408 | X37: =IFERROR(__xludf.DUMMYFUNCTION("""COMPUTED_VALUE"""),1.653061224489796) -> 1.6530612 | Y37: =IFERROR(__xludf.DUMMYFUNCTION("""COMPUTED_VALUE"""),2.0) -> 2 | Z37: =IFERROR(__xludf.DUMMYFUNCTION("""COMPUTED_VALUE"""),2.0) -> 2 | AA37: =IFERROR(__xludf.DUMMYFUNCTION("""COMPUTED_VALUE"""),0.0) -> 0 | AB37: =IFERROR(__xludf.DUMMYFUNCTION("""COMPUTED_VALUE"""),5.0) -> 5 | AC37: =IFERROR(__xludf.DUMMYFUNCTION("""COMPUTED_VALUE"""),20.0) -> 20 | AD37: =IFERROR(__xludf.DUMMYFUNCTION("""COMPUTED_VALUE"""),45.0) -> 45
A38: =IFERROR(__xludf.DUMMYFUNCTION("""COMPUTED_VALUE"""),"Amateur") -> Amateur | B38: =IFERROR(__xludf.DUMMYFUNCTION("""COMPUTED_VALUE"""),"RSC005472") -> RSC005472 | C38: =IFERROR(__xludf.DUMMYFUNCTION("""COMPUTED_VALUE"""),"EngynGameOver") -> EngynGameOver | D38: =IFERROR(__xludf.DUMMYFUNCTION("""COMPUTED_VALUE"""),"Legionaries") -> Legionaries | E38: =IFERROR(__xludf.DUMMYFUNCTION("""COMPUTED_VALUE"""),"N/A") -> N/A | F38: =IFERROR(__xludf.DUMMYFUNCTION("""COMPUTED_VALUE"""),21.199162832317825) -> 21.199163 | G38: =IFERROR(__xludf.DUMMYFUNCTION("""COMPUTED_VALUE"""),31.413022189205922) -> 31.413022 | H38: =IFERROR(__xludf.DUMMYFUNCTION("""COMPUTED_VALUE"""),26.30609251076187) -> 26.306093 | I38: =IFERROR(__xludf.DUMMYFUNCTION("""COMPUTED_VALUE"""),21.0) -> 21 | J38: =IFERROR(__xludf.DUMMYFUNCTION("IFERROR(FILTER(Stats!$F:$Z,(Stats!$A:$A=$A38)*(Stats!$B:$B=$B38)))"),7.0) -> 7 | K38: =IFERROR(__xludf.DUMMYFUNCTION("""COMPUTED_VALUE"""),14.0) -> 14 | L38: =IFERROR(__xludf.DUMMYFUNCTION("""COMPUTED_VALUE"""),0.3333333333333333) -> 0.33333333 | M38: =IFERROR(__xludf.DUMMYFUNCTION("""COMPUTED_VALUE"""),0.0) -> 0 | N38: =IFERROR(__xludf.DUMMYFUNCTION("""COMPUTED_VALUE"""),5105.0) -> 5105 | O38: =IFERROR(__xludf.DUMMYFUNCTION("""COMPUTED_VALUE"""),8.0) -> 8 | P38: =IFERROR(__xludf.DUMMYFUNCTION("""COMPUTED_VALUE"""),8.0) -> 8 | Q38: =IFERROR(__xludf.DUMMYFUNCTION("""COMPUTED_VALUE"""),27.0) -> 27 | R38: =IFERROR(__xludf.DUMMYFUNCTION("""COMPUTED_VALUE"""),20.0) -> 20 | S38: =IFERROR(__xludf.DUMMYFUNCTION("""COMPUTED_VALUE"""),0.4) -> 0.4 | T38: =IFERROR(__xludf.DUMMYFUNCTION("""COMPUTED_VALUE"""),243.0952380952381) -> 243.09524 | U38: =IFERROR(__xludf.DUMMYFUNCTION("""COMPUTED_VALUE"""),0.38095238095238093) -> 0.38095238 | V38: =IFERROR(__xludf.DUMMYFUNCTION("""COMPUTED_VALUE"""),0.38095238095238093) -> 0.38095238 | W38: =IFERROR(__xludf.DUMMYFUNCTION("""COMPUTED_VALUE"""),1.2857142857142858) -> 1.2857143 | X38: =IFERROR(__xludf.DUMMYFUNCTION("""COMPUTED_VALUE"""),0.9523809523809523) -> 0.95238095 | Y38: =IFERROR(__xludf.DUMMYFUNCTION("""COMPUTED_VALUE"""),0.0) -> 0 | Z38: =IFERROR(__xludf.DUMMYFUNCTION("""COMPUTED_VALUE"""),0.0) -> 0 | AA38: =IFERROR(__xludf.DUMMYFUNCTION("""COMPUTED_VALUE"""),0.0) -> 0 | AB38: =IFERROR(__xludf.DUMMYFUNCTION("""COMPUTED_VALUE"""),4.0) -> 4 | AC38: =IFERROR(__xludf.DUMMYFUNCTION("""COMPUTED_VALUE"""),14.0) -> 14 | AD38: =IFERROR(__xludf.DUMMYFUNCTION("""COMPUTED_VALUE"""),25.0) -> 25
A39: =IFERROR(__xludf.DUMMYFUNCTION("""COMPUTED_VALUE"""),"Amateur") -> Amateur | B39: =IFERROR(__xludf.DUMMYFUNCTION("""COMPUTED_VALUE"""),"RSC008213") -> RSC008213 | C39: =IFERROR(__xludf.DUMMYFUNCTION("""COMPUTED_VALUE"""),"SeargD") -> SeargD | D39: =IFERROR(__xludf.DUMMYFUNCTION("""COMPUTED_VALUE"""),"Legionaries") -> Legionaries | E39: =IFERROR(__xludf.DUMMYFUNCTION("""COMPUTED_VALUE"""),"N/A") -> N/A | F39: =IFERROR(__xludf.DUMMYFUNCTION("""COMPUTED_VALUE"""),22.820213277870728) -> 22.820213 | G39: =IFERROR(__xludf.DUMMYFUNCTION("""COMPUTED_VALUE"""),28.723774346762678) -> 28.723774 | H39: =IFERROR(__xludf.DUMMYFUNCTION("""COMPUTED_VALUE"""),25.7719938123167) -> 25.771994 | I39: =IFERROR(__xludf.DUMMYFUNCTION("""COMPUTED_VALUE"""),40.0) -> 40 | J39: =IFERROR(__xludf.DUMMYFUNCTION("IFERROR(FILTER(Stats!$F:$Z,(Stats!$A:$A=$A39)*(Stats!$B:$B=$B39)))"),9.0) -> 9 | K39: =IFERROR(__xludf.DUMMYFUNCTION("""COMPUTED_VALUE"""),31.0) -> 31 | L39: =IFERROR(__xludf.DUMMYFUNCTION("""COMPUTED_VALUE"""),0.225) -> 0.225 | M39: =IFERROR(__xludf.DUMMYFUNCTION("""COMPUTED_VALUE"""),2.0) -> 2 | N39: =IFERROR(__xludf.DUMMYFUNCTION("""COMPUTED_VALUE"""),9586.0) -> 9586 | O39: =IFERROR(__xludf.DUMMYFUNCTION("""COMPUTED_VALUE"""),18.0) -> 18 | P39: =IFERROR(__xludf.DUMMYFUNCTION("""COMPUTED_VALUE"""),12.0) -> 12 | Q39: =IFERROR(__xludf.DUMMYFUNCTION("""COMPUTED_VALUE"""),35.0) -> 35 | R39: =IFERROR(__xludf.DUMMYFUNCTION("""COMPUTED_VALUE"""),59.0) -> 59 | S39: =IFERROR(__xludf.DUMMYFUNCTION("""COMPUTED_VALUE"""),0.3050847457627119) -> 0.30508475 | T39: =IFERROR(__xludf.DUMMYFUNCTION("""COMPUTED_VALUE"""),239.65) -> 239.65 | U39: =IFERROR(__xludf.DUMMYFUNCTION("""COMPUTED_VALUE"""),0.45) -> 0.45 | V39: =IFERROR(__xludf.DUMMYFUNCTION("""COMPUTED_VALUE"""),0.3) -> 0.3 | W39: =IFERROR(__xludf.DUMMYFUNCTION("""COMPUTED_VALUE"""),0.875) -> 0.875 | X39: =IFERROR(__xludf.DUMMYFUNCTION("""COMPUTED_VALUE"""),1.475) -> 1.475 | Y39: =IFERROR(__xludf.DUMMYFUNCTION("""COMPUTED_VALUE"""),2.0) -> 2 | Z39: =IFERROR(__xludf.DUMMYFUNCTION("""COMPUTED_VALUE"""),0.0) -> 0 | AA39: =IFERROR(__xludf.DUMMYFUNCTION("""COMPUTED_VALUE"""),0.0) -> 0 | AB39: =IFERROR(__xludf.DUMMYFUNCTION("""COMPUTED_VALUE"""),3.0) -> 3 | AC39: =IFERROR(__xludf.DUMMYFUNCTION("""COMPUTED_VALUE"""),17.0) -> 17 | AD39: =IFERROR(__xludf.DUMMYFUNCTION("""COMPUTED_VALUE"""),34.0) -> 34
A40: =IFERROR(__xludf.DUMMYFUNCTION("""COMPUTED_VALUE"""),"Amateur") -> Amateur | B40: =IFERROR(__xludf.DUMMYFUNCTION("""COMPUTED_VALUE"""),"RSC008402") -> RSC008402 | C40: =IFERROR(__xludf.DUMMYFUNCTION("""COMPUTED_VALUE"""),"TTV/DucksNotKeys") -> TTV/DucksNotKeys | D40: =IFERROR(__xludf.DUMMYFUNCTION("""COMPUTED_VALUE"""),"Chimera") -> Chimera | E40: =IFERROR(__xludf.DUMMYFUNCTION("""COMPUTED_VALUE"""),"N/A") -> N/A | F40: =IFERROR(__xludf.DUMMYFUNCTION("""COMPUTED_VALUE"""),18.788859598271056) -> 18.78886 | G40: =IFERROR(__xludf.DUMMYFUNCTION("""COMPUTED_VALUE"""),27.646460537045737) -> 27.646461 | H40: =IFERROR(__xludf.DUMMYFUNCTION("""COMPUTED_VALUE"""),23.217660067658397) -> 23.21766 | I40: =IFERROR(__xludf.DUMMYFUNCTION("""COMPUTED_VALUE"""),14.0) -> 14 | J40: =IFERROR(__xludf.DUMMYFUNCTION("IFERROR(FILTER(Stats!$F:$Z,(Stats!$A:$A=$A40)*(Stats!$B:$B=$B40)))"),4.0) -> 4 | K40: =IFERROR(__xludf.DUMMYFUNCTION("""COMPUTED_VALUE"""),10.0) -> 10 | L40: =IFERROR(__xludf.DUMMYFUNCTION("""COMPUTED_VALUE"""),0.2857142857142857) -> 0.28571429 | M40: =IFERROR(__xludf.DUMMYFUNCTION("""COMPUTED_VALUE"""),1.0) -> 1 | N40: =IFERROR(__xludf.DUMMYFUNCTION("""COMPUTED_VALUE"""),3008.0) -> 3008 | O40: =IFERROR(__xludf.DUMMYFUNCTION("""COMPUTED_VALUE"""),4.0) -> 4 | P40: =IFERROR(__xludf.DUMMYFUNCTION("""COMPUTED_VALUE"""),5.0) -> 5 | Q40: =IFERROR(__xludf.DUMMYFUNCTION("""COMPUTED_VALUE"""),11.0) -> 11 | R40: =IFERROR(__xludf.DUMMYFUNCTION("""COMPUTED_VALUE"""),25.0) -> 25 | S40: =IFERROR(__xludf.DUMMYFUNCTION("""COMPUTED_VALUE"""),0.16) -> 0.16 | T40: =IFERROR(__xludf.DUMMYFUNCTION("""COMPUTED_VALUE"""),214.85714285714286) -> 214.85714 | U40: =IFERROR(__xludf.DUMMYFUNCTION("""COMPUTED_VALUE"""),0.2857142857142857) -> 0.28571429 | V40: =IFERROR(__xludf.DUMMYFUNCTION("""COMPUTED_VALUE"""),0.35714285714285715) -> 0.35714286 | W40: =IFERROR(__xludf.DUMMYFUNCTION("""COMPUTED_VALUE"""),0.7857142857142857) -> 0.78571429 | X40: =IFERROR(__xludf.DUMMYFUNCTION("""COMPUTED_VALUE"""),1.7857142857142858) -> 1.7857143 | Y40: =IFERROR(__xludf.DUMMYFUNCTION("""COMPUTED_VALUE"""),1.0) -> 1 | Z40: =IFERROR(__xludf.DUMMYFUNCTION("""COMPUTED_VALUE"""),0.0) -> 0 | AA40: =IFERROR(__xludf.DUMMYFUNCTION("""COMPUTED_VALUE"""),1.0) -> 1 | AB40: =IFERROR(__xludf.DUMMYFUNCTION("""COMPUTED_VALUE"""),0.0) -> 0 | AC40: =IFERROR(__xludf.DUMMYFUNCTION("""COMPUTED_VALUE"""),11.0) -> 11 | AD40: =IFERROR(__xludf.DUMMYFUNCTION("""COMPUTED_VALUE"""),7.0) -> 7
A41: =IFERROR(__xludf.DUMMYFUNCTION("""COMPUTED_VALUE"""),"Amateur") -> Amateur | B41: =IFERROR(__xludf.DUMMYFUNCTION("""COMPUTED_VALUE"""),"RSC008151") -> RSC008151 | C41: =IFERROR(__xludf.DUMMYFUNCTION("""COMPUTED_VALUE"""),"Extrakrispybecky") -> Extrakrispybecky | D41: =IFERROR(__xludf.DUMMYFUNCTION("""COMPUTED_VALUE"""),"Kappa") -> Kappa | E41: =IFERROR(__xludf.DUMMYFUNCTION("""COMPUTED_VALUE"""),"N/A") -> N/A | F41: =IFERROR(__xludf.DUMMYFUNCTION("""COMPUTED_VALUE"""),15.265513534116828) -> 15.265514 | G41: =IFERROR(__xludf.DUMMYFUNCTION("""COMPUTED_VALUE"""),25.547063768002943) -> 25.547064 | H41: =IFERROR(__xludf.DUMMYFUNCTION("""COMPUTED_VALUE"""),20.406288651059885) -> 20.406289 | I41: =IFERROR(__xludf.DUMMYFUNCTION("""COMPUTED_VALUE"""),16.0) -> 16 | J41: =IFERROR(__xludf.DUMMYFUNCTION("IFERROR(FILTER(Stats!$F:$Z,(Stats!$A:$A=$A41)*(Stats!$B:$B=$B41)))"),5.0) -> 5 | K41: =IFERROR(__xludf.DUMMYFUNCTION("""COMPUTED_VALUE"""),11.0) -> 11 | L41: =IFERROR(__xludf.DUMMYFUNCTION("""COMPUTED_VALUE"""),0.3125) -> 0.3125 | M41: =IFERROR(__xludf.DUMMYFUNCTION("""COMPUTED_VALUE"""),0.0) -> 0 | N41: =IFERROR(__xludf.DUMMYFUNCTION("""COMPUTED_VALUE"""),3739.0) -> 3739 | O41: =IFERROR(__xludf.DUMMYFUNCTION("""COMPUTED_VALUE"""),8.0) -> 8 | P41: =IFERROR(__xludf.DUMMYFUNCTION("""COMPUTED_VALUE"""),5.0) -> 5 | Q41: =IFERROR(__xludf.DUMMYFUNCTION("""COMPUTED_VALUE"""),20.0) -> 20 | R41: =IFERROR(__xludf.DUMMYFUNCTION("""COMPUTED_VALUE"""),19.0) -> 19 | S41: =IFERROR(__xludf.DUMMYFUNCTION("""COMPUTED_VALUE"""),0.42105263157894735) -> 0.42105263 | T41: =IFERROR(__xludf.DUMMYFUNCTION("""COMPUTED_VALUE"""),233.6875) -> 233.6875 | U41: =IFERROR(__xludf.DUMMYFUNCTION("""COMPUTED_VALUE"""),0.5) -> 0.5 | V41: =IFERROR(__xludf.DUMMYFUNCTION("""COMPUTED_VALUE"""),0.3125) -> 0.3125 | W41: =IFERROR(__xludf.DUMMYFUNCTION("""COMPUTED_VALUE"""),1.25) -> 1.25 | X41: =IFERROR(__xludf.DUMMYFUNCTION("""COMPUTED_VALUE"""),1.1875) -> 1.1875 | Y41: =IFERROR(__xludf.DUMMYFUNCTION("""COMPUTED_VALUE"""),1.0) -> 1 | Z41: =IFERROR(__xludf.DUMMYFUNCTION("""COMPUTED_VALUE"""),0.0) -> 0 | AA41: =IFERROR(__xludf.DUMMYFUNCTION("""COMPUTED_VALUE"""),0.0) -> 0 | AB41: =IFERROR(__xludf.DUMMYFUNCTION("""COMPUTED_VALUE"""),1.0) -> 1 | AC41: =IFERROR(__xludf.DUMMYFUNCTION("""COMPUTED_VALUE"""),21.0) -> 21 | AD41: =IFERROR(__xludf.DUMMYFUNCTION("""COMPUTED_VALUE"""),14.0) -> 14
A42: =IFERROR(__xludf.DUMMYFUNCTION("""COMPUTED_VALUE"""),"Amateur") -> Amateur | B42: =IFERROR(__xludf.DUMMYFUNCTION("""COMPUTED_VALUE"""),"RSC007678") -> RSC007678 | C42: =IFERROR(__xludf.DUMMYFUNCTION("""COMPUTED_VALUE"""),"SavedHawk") -> SavedHawk | D42: =IFERROR(__xludf.DUMMYFUNCTION("""COMPUTED_VALUE"""),"Winter Fresh") -> Winter Fresh | E42: =IFERROR(__xludf.DUMMYFUNCTION("""COMPUTED_VALUE"""),"N/A") -> N/A | F42: =IFERROR(__xludf.DUMMYFUNCTION("""COMPUTED_VALUE"""),-17.678656323291804) -> -17.678656 | G42: =IFERROR(__xludf.DUMMYFUNCTION("""COMPUTED_VALUE"""),-0.5509846670849612) -> -0.55098467 | H42: =IFERROR(__xludf.DUMMYFUNCTION("""COMPUTED_VALUE"""),-9.114820495188383) -> -9.1148205 | I42: =IFERROR(__xludf.DUMMYFUNCTION("""COMPUTED_VALUE"""),4.0) -> 4 | J42: =IFERROR(__xludf.DUMMYFUNCTION("IFERROR(FILTER(Stats!$F:$Z,(Stats!$A:$A=$A42)*(Stats!$B:$B=$B42)))"),0.0) -> 0 | K42: =IFERROR(__xludf.DUMMYFUNCTION("""COMPUTED_VALUE"""),4.0) -> 4 | L42: =IFERROR(__xludf.DUMMYFUNCTION("""COMPUTED_VALUE"""),0.0) -> 0 | M42: =IFERROR(__xludf.DUMMYFUNCTION("""COMPUTED_VALUE"""),0.0) -> 0 | N42: =IFERROR(__xludf.DUMMYFUNCTION("""COMPUTED_VALUE"""),704.0) -> 704 | O42: =IFERROR(__xludf.DUMMYFUNCTION("""COMPUTED_VALUE"""),1.0) -> 1 | P42: =IFERROR(__xludf.DUMMYFUNCTION("""COMPUTED_VALUE"""),0.0) -> 0 | Q42: =IFERROR(__xludf.DUMMYFUNCTION("""COMPUTED_VALUE"""),3.0) -> 3 | R42: =IFERROR(__xludf.DUMMYFUNCTION("""COMPUTED_VALUE"""),2.0) -> 2 | S42: =IFERROR(__xludf.DUMMYFUNCTION("""COMPUTED_VALUE"""),0.5) -> 0.5 | T42: =IFERROR(__xludf.DUMMYFUNCTION("""COMPUTED_VALUE"""),176.0) -> 176 | U42: =IFERROR(__xludf.DUMMYFUNCTION("""COMPUTED_VALUE"""),0.25) -> 0.25 | V42: =IFERROR(__xludf.DUMMYFUNCTION("""COMPUTED_VALUE"""),0.0) -> 0 | W42: =IFERROR(__xludf.DUMMYFUNCTION("""COMPUTED_VALUE"""),0.75) -> 0.75 | X42: =IFERROR(__xludf.DUMMYFUNCTION("""COMPUTED_VALUE"""),0.5) -> 0.5 | Y42: =IFERROR(__xludf.DUMMYFUNCTION("""COMPUTED_VALUE"""),0.0) -> 0 | Z42: =IFERROR(__xludf.DUMMYFUNCTION("""COMPUTED_VALUE"""),0.0) -> 0 | AA42: =IFERROR(__xludf.DUMMYFUNCTION("""COMPUTED_VALUE"""),0.0) -> 0 | AB42: =IFERROR(__xludf.DUMMYFUNCTION("""COMPUTED_VALUE"""),0.0) -> 0 | AC42: =IFERROR(__xludf.DUMMYFUNCTION("""COMPUTED_VALUE"""),3.0) -> 3 | AD42: =IFERROR(__xludf.DUMMYFUNCTION("""COMPUTED_VALUE"""),6.0) -> 6
A43: =IFERROR(__xludf.DUMMYFUNCTION("""COMPUTED_VALUE"""),"Amateur") -> Amateur | B43: =IFERROR(__xludf.DUMMYFUNCTION("""COMPUTED_VALUE"""),"RSC006364") -> RSC006364 | C43: =IFERROR(__xludf.DUMMYFUNCTION("""COMPUTED_VALUE"""),"YT_rocketbrah") -> YT_rocketbrah | D43: =IFERROR(__xludf.DUMMYFUNCTION("""COMPUTED_VALUE"""),"Legionaries") -> Legionaries | E43: =IFERROR(__xludf.DUMMYFUNCTION("""COMPUTED_VALUE"""),"N/A") -> N/A | F43: =IFERROR(__xludf.DUMMYFUNCTION("""COMPUTED_VALUE"""),-31.188058387739204) -> -31.188058 | G43: =IFERROR(__xludf.DUMMYFUNCTION("""COMPUTED_VALUE"""),-5.299303725534173) -> -5.2993037 | H43: =IFERROR(__xludf.DUMMYFUNCTION("""COMPUTED_VALUE"""),-18.24368105663669) -> -18.243681 | I43: =IFERROR(__xludf.DUMMYFUNCTION("""COMPUTED_VALUE"""),3.0) -> 3 | J43: =IFERROR(__xludf.DUMMYFUNCTION("IFERROR(FILTER(Stats!$F:$Z,(Stats!$A:$A=$A43)*(Stats!$B:$B=$B43)))"),0.0) -> 0 | K43: =IFERROR(__xludf.DUMMYFUNCTION("""COMPUTED_VALUE"""),3.0) -> 3 | L43: =IFERROR(__xludf.DUMMYFUNCTION("""COMPUTED_VALUE"""),0.0) -> 0 | M43: =IFERROR(__xludf.DUMMYFUNCTION("""COMPUTED_VALUE"""),0.0) -> 0 | N43: =IFERROR(__xludf.DUMMYFUNCTION("""COMPUTED_VALUE"""),467.0) -> 467 | O43: =IFERROR(__xludf.DUMMYFUNCTION("""COMPUTED_VALUE"""),0.0) -> 0 | P43: =IFERROR(__xludf.DUMMYFUNCTION("""COMPUTED_VALUE"""),0.0) -> 0 | Q43: =IFERROR(__xludf.DUMMYFUNCTION("""COMPUTED_VALUE"""),4.0) -> 4 | R43: =IFERROR(__xludf.DUMMYFUNCTION("""COMPUTED_VALUE"""),3.0) -> 3 | S43: =IFERROR(__xludf.DUMMYFUNCTION("""COMPUTED_VALUE"""),0.0) -> 0 | T43: =IFERROR(__xludf.DUMMYFUNCTION("""COMPUTED_VALUE"""),155.66666666666666) -> 155.66667 | U43: =IFERROR(__xludf.DUMMYFUNCTION("""COMPUTED_VALUE"""),0.0) -> 0 | V43: =IFERROR(__xludf.DUMMYFUNCTION("""COMPUTED_VALUE"""),0.0) -> 0 | W43: =IFERROR(__xludf.DUMMYFUNCTION("""COMPUTED_VALUE"""),1.3333333333333333) -> 1.3333333 | X43: =IFERROR(__xludf.DUMMYFUNCTION("""COMPUTED_VALUE"""),1.0) -> 1 | Y43: =IFERROR(__xludf.DUMMYFUNCTION("""COMPUTED_VALUE"""),0.0) -> 0 | Z43: =IFERROR(__xludf.DUMMYFUNCTION("""COMPUTED_VALUE"""),0.0) -> 0 | AA43: =IFERROR(__xludf.DUMMYFUNCTION("""COMPUTED_VALUE"""),0.0) -> 0 | AB43: =IFERROR(__xludf.DUMMYFUNCTION("""COMPUTED_VALUE"""),0.0) -> 0 | AC43: =IFERROR(__xludf.DUMMYFUNCTION("""COMPUTED_VALUE"""),1.0) -> 1 | AD43: =IFERROR(__xludf.DUMMYFUNCTION("""COMPUTED_VALUE"""),2.0) -> 2
A44: =IFERROR(__xludf.DUMMYFUNCTION("""COMPUTED_VALUE"""),"Amateur") -> Amateur | B44: =IFERROR(__xludf.DUMMYFUNCTION("""COMPUTED_VALUE"""),"RSC008489") -> RSC008489 | C44: =IFERROR(__xludf.DUMMYFUNCTION("""COMPUTED_VALUE"""),"nacho_nachos2") -> nacho_nachos2 | D44: =IFERROR(__xludf.DUMMYFUNCTION("""COMPUTED_VALUE"""),"Bombers") -> Bombers | E44: =IFERROR(__xludf.DUMMYFUNCTION("""COMPUTED_VALUE"""),"N/A") -> N/A | F44: =IFERROR(__xludf.DUMMYFUNCTION("""COMPUTED_VALUE"""),-45.10097464478005) -> -45.100975 | G44: =IFERROR(__xludf.DUMMYFUNCTION("""COMPUTED_VALUE"""),-6.663296389554475) -> -6.6632964 | H44: =IFERROR(__xludf.DUMMYFUNCTION("""COMPUTED_VALUE"""),-25.882135517167264) -> -25.882136 | I44: =IFERROR(__xludf.DUMMYFUNCTION("""COMPUTED_VALUE"""),4.0) -> 4 | J44: =IFERROR(__xludf.DUMMYFUNCTION("IFERROR(FILTER(Stats!$F:$Z,(Stats!$A:$A=$A44)*(Stats!$B:$B=$B44)))"),1.0) -> 1 | K44: =IFERROR(__xludf.DUMMYFUNCTION("""COMPUTED_VALUE"""),3.0) -> 3 | L44: =IFERROR(__xludf.DUMMYFUNCTION("""COMPUTED_VALUE"""),0.25) -> 0.25 | M44: =IFERROR(__xludf.DUMMYFUNCTION("""COMPUTED_VALUE"""),0.0) -> 0 | N44: =IFERROR(__xludf.DUMMYFUNCTION("""COMPUTED_VALUE"""),361.0) -> 361 | O44: =IFERROR(__xludf.DUMMYFUNCTION("""COMPUTED_VALUE"""),0.0) -> 0 | P44: =IFERROR(__xludf.DUMMYFUNCTION("""COMPUTED_VALUE"""),0.0) -> 0 | Q44: =IFERROR(__xludf.DUMMYFUNCTION("""COMPUTED_VALUE"""),2.0) -> 2 | R44: =IFERROR(__xludf.DUMMYFUNCTION("""COMPUTED_VALUE"""),2.0) -> 2 | S44: =IFERROR(__xludf.DUMMYFUNCTION("""COMPUTED_VALUE"""),0.0) -> 0 | T44: =IFERROR(__xludf.DUMMYFUNCTION("""COMPUTED_VALUE"""),90.25) -> 90.25 | U44: =IFERROR(__xludf.DUMMYFUNCTION("""COMPUTED_VALUE"""),0.0) -> 0 | V44: =IFERROR(__xludf.DUMMYFUNCTION("""COMPUTED_VALUE"""),0.0) -> 0 | W44: =IFERROR(__xludf.DUMMYFUNCTION("""COMPUTED_VALUE"""),0.5) -> 0.5 | X44: =IFERROR(__xludf.DUMMYFUNCTION("""COMPUTED_VALUE"""),0.5) -> 0.5 | Y44: =IFERROR(__xludf.DUMMYFUNCTION("""COMPUTED_VALUE"""),0.0) -> 0 | Z44: =IFERROR(__xludf.DUMMYFUNCTION("""COMPUTED_VALUE"""),0.0) -> 0 | AA44: =IFERROR(__xludf.DUMMYFUNCTION("""COMPUTED_VALUE"""),0.0) -> 0 | AB44: =IFERROR(__xludf.DUMMYFUNCTION("""COMPUTED_VALUE"""),0.0) -> 0 | AC44: =IFERROR(__xludf.DUMMYFUNCTION("""COMPUTED_VALUE"""),0.0) -> 0 | AD44: =IFERROR(__xludf.DUMMYFUNCTION("""COMPUTED_VALUE"""),2.0) -> 2
A45: =IFERROR(__xludf.DUMMYFUNCTION("""COMPUTED_VALUE"""),"Challenger") -> Challenger | B45: =IFERROR(__xludf.DUMMYFUNCTION("""COMPUTED_VALUE"""),"RSC002412") -> RSC002412 | C45: =IFERROR(__xludf.DUMMYFUNCTION("""COMPUTED_VALUE"""),"Rosefanatic3615") -> Rosefanatic3615 | D45: =IFERROR(__xludf.DUMMYFUNCTION("""COMPUTED_VALUE"""),"Manticore") -> Manticore | E45: =IFERROR(__xludf.DUMMYFUNCTION("""COMPUTED_VALUE"""),"Solar") -> Solar | F45: =IFERROR(__xludf.DUMMYFUNCTION("""COMPUTED_VALUE"""),88.10121453576465) -> 88.101215 | G45: =IFERROR(__xludf.DUMMYFUNCTION("""COMPUTED_VALUE"""),121.25973872794016) -> 121.25974 | H45: =IFERROR(__xludf.DUMMYFUNCTION("""COMPUTED_VALUE"""),104.6804766318524) -> 104.68048 | I45: =IFERROR(__xludf.DUMMYFUNCTION("""COMPUTED_VALUE"""),56.0) -> 56 | J45: =IFERROR(__xludf.DUMMYFUNCTION("IFERROR(FILTER(Stats!$F:$Z,(Stats!$A:$A=$A45)*(Stats!$B:$B=$B45)))"),40.0) -> 40 | K45: =IFERROR(__xludf.DUMMYFUNCTION("""COMPUTED_VALUE"""),16.0) -> 16 | L45: =IFERROR(__xludf.DUMMYFUNCTION("""COMPUTED_VALUE"""),0.7142857142857143) -> 0.71428571 | M45: =IFERROR(__xludf.DUMMYFUNCTION("""COMPUTED_VALUE"""),14.0) -> 14 | N45: =IFERROR(__xludf.DUMMYFUNCTION("""COMPUTED_VALUE"""),22611.0) -> 22611 | O45: =IFERROR(__xludf.DUMMYFUNCTION("""COMPUTED_VALUE"""),73.0) -> 73 | P45: =IFERROR(__xludf.DUMMYFUNCTION("""COMPUTED_VALUE"""),48.0) -> 48 | Q45: =IFERROR(__xludf.DUMMYFUNCTION("""COMPUTED_VALUE"""),47.0) -> 47 | R45: =IFERROR(__xludf.DUMMYFUNCTION("""COMPUTED_VALUE"""),208.0) -> 208 | S45: =IFERROR(__xludf.DUMMYFUNCTION("""COMPUTED_VALUE"""),0.35096153846153844) -> 0.35096154 | T45: =IFERROR(__xludf.DUMMYFUNCTION("""COMPUTED_VALUE"""),403.76785714285717) -> 403.76786 | U45: =IFERROR(__xludf.DUMMYFUNCTION("""COMPUTED_VALUE"""),1.3035714285714286) -> 1.3035714 | V45: =IFERROR(__xludf.DUMMYFUNCTION("""COMPUTED_VALUE"""),0.8571428571428571) -> 0.85714286 | W45: =IFERROR(__xludf.DUMMYFUNCTION("""COMPUTED_VALUE"""),0.8392857142857143) -> 0.83928571 | X45: =IFERROR(__xludf.DUMMYFUNCTION("""COMPUTED_VALUE"""),3.7142857142857144) -> 3.7142857 | Y45: =IFERROR(__xludf.DUMMYFUNCTION("""COMPUTED_VALUE"""),18.0) -> 18 | Z45: =IFERROR(__xludf.DUMMYFUNCTION("""COMPUTED_VALUE"""),6.0) -> 6 | AA45: =IFERROR(__xludf.DUMMYFUNCTION("""COMPUTED_VALUE"""),1.0) -> 1 | AB45: =IFERROR(__xludf.DUMMYFUNCTION("""COMPUTED_VALUE"""),2.0) -> 2 | AC45: =IFERROR(__xludf.DUMMYFUNCTION("""COMPUTED_VALUE"""),35.0) -> 35 | AD45: =IFERROR(__xludf.DUMMYFUNCTION("""COMPUTED_VALUE"""),58.0) -> 58
A46: =IFERROR(__xludf.DUMMYFUNCTION("""COMPUTED_VALUE"""),"Challenger") -> Challenger | B46: =IFERROR(__xludf.DUMMYFUNCTION("""COMPUTED_VALUE"""),"RSC008288") -> RSC008288 | C46: =IFERROR(__xludf.DUMMYFUNCTION("""COMPUTED_VALUE"""),"WifiWFB") -> WifiWFB | D46: =IFERROR(__xludf.DUMMYFUNCTION("""COMPUTED_VALUE"""),"Thunder Pups Blitzars") -> Thunder Pups Blitzars | E46: =IFERROR(__xludf.DUMMYFUNCTION("""COMPUTED_VALUE"""),"Solar Lunar") -> Solar Lunar | F46: =IFERROR(__xludf.DUMMYFUNCTION("""COMPUTED_VALUE"""),93.24830031633488) -> 93.2483 | G46: =IFERROR(__xludf.DUMMYFUNCTION("""COMPUTED_VALUE"""),102.63537436929053) -> 102.63537 | H46: =IFERROR(__xludf.DUMMYFUNCTION("""COMPUTED_VALUE"""),97.9418373428127) -> 97.941837 | I46: =IFERROR(__xludf.DUMMYFUNCTION("""COMPUTED_VALUE"""),36.0) -> 36 | J46: =IFERROR(__xludf.DUMMYFUNCTION("IFERROR(FILTER(Stats!$F:$Z,(Stats!$A:$A=$A46)*(Stats!$B:$B=$B46)))"),27.0) -> 27 | K46: =IFERROR(__xludf.DUMMYFUNCTION("""COMPUTED_VALUE"""),9.0) -> 9 | L46: =IFERROR(__xludf.DUMMYFUNCTION("""COMPUTED_VALUE"""),0.75) -> 0.75 | M46: =IFERROR(__xludf.DUMMYFUNCTION("""COMPUTED_VALUE"""),13.0) -> 13 | N46: =IFERROR(__xludf.DUMMYFUNCTION("""COMPUTED_VALUE"""),14832.0) -> 14832 | O46: =IFERROR(__xludf.DUMMYFUNCTION("""COMPUTED_VALUE"""),44.0) -> 44 | P46: =IFERROR(__xludf.DUMMYFUNCTION("""COMPUTED_VALUE"""),25.0) -> 25 | Q46: =IFERROR(__xludf.DUMMYFUNCTION("""COMPUTED_VALUE"""),48.0) -> 48 | R46: =IFERROR(__xludf.DUMMYFUNCTION("""COMPUTED_VALUE"""),115.0) -> 115 | S46: =IFERROR(__xludf.DUMMYFUNCTION("""COMPUTED_VALUE"""),0.3826086956521739) -> 0.3826087 | T46: =IFERROR(__xludf.DUMMYFUNCTION("""COMPUTED_VALUE"""),412.0) -> 412 | U46: =IFERROR(__xludf.DUMMYFUNCTION("""COMPUTED_VALUE"""),1.2222222222222223) -> 1.2222222 | V46: =IFERROR(__xludf.DUMMYFUNCTION("""COMPUTED_VALUE"""),0.6944444444444444) -> 0.69444444 | W46: =IFERROR(__xludf.DUMMYFUNCTION("""COMPUTED_VALUE"""),1.3333333333333333) -> 1.3333333 | X46: =IFERROR(__xludf.DUMMYFUNCTION("""COMPUTED_VALUE"""),3.1944444444444446) -> 3.1944444 | Y46: =IFERROR(__xludf.DUMMYFUNCTION("""COMPUTED_VALUE"""),9.0) -> 9 | Z46: =IFERROR(__xludf.DUMMYFUNCTION("""COMPUTED_VALUE"""),3.0) -> 3 | AA46: =IFERROR(__xludf.DUMMYFUNCTION("""COMPUTED_VALUE"""),1.0) -> 1 | AB46: =IFERROR(__xludf.DUMMYFUNCTION("""COMPUTED_VALUE"""),7.0) -> 7 | AC46: =IFERROR(__xludf.DUMMYFUNCTION("""COMPUTED_VALUE"""),89.0) -> 89 | AD46: =IFERROR(__xludf.DUMMYFUNCTION("""COMPUTED_VALUE"""),22.0) -> 22
A47: =IFERROR(__xludf.DUMMYFUNCTION("""COMPUTED_VALUE"""),"Challenger") -> Challenger | B47: =IFERROR(__xludf.DUMMYFUNCTION("""COMPUTED_VALUE"""),"RSC006477") -> RSC006477 | C47: =IFERROR(__xludf.DUMMYFUNCTION("""COMPUTED_VALUE"""),"XtraCrispyRL") -> XtraCrispyRL | D47: =IFERROR(__xludf.DUMMYFUNCTION("""COMPUTED_VALUE"""),"Void") -> Void | E47: =IFERROR(__xludf.DUMMYFUNCTION("""COMPUTED_VALUE"""),"Solar") -> Solar | F47: =IFERROR(__xludf.DUMMYFUNCTION("""COMPUTED_VALUE"""),93.6553865551164) -> 93.655387 | G47: =IFERROR(__xludf.DUMMYFUNCTION("""COMPUTED_VALUE"""),99.00857746509288) -> 99.008577 | H47: =IFERROR(__xludf.DUMMYFUNCTION("""COMPUTED_VALUE"""),96.33198201010464) -> 96.331982 | I47: =IFERROR(__xludf.DUMMYFUNCTION("""COMPUTED_VALUE"""),46.0) -> 46 | J47: =IFERROR(__xludf.DUMMYFUNCTION("IFERROR(FILTER(Stats!$F:$Z,(Stats!$A:$A=$A47)*(Stats!$B:$B=$B47)))"),21.0) -> 21 | K47: =IFERROR(__xludf.DUMMYFUNCTION("""COMPUTED_VALUE"""),25.0) -> 25 | L47: =IFERROR(__xludf.DUMMYFUNCTION("""COMPUTED_VALUE"""),0.45652173913043476) -> 0.45652174 | M47: =IFERROR(__xludf.DUMMYFUNCTION("""COMPUTED_VALUE"""),12.0) -> 12 | N47: =IFERROR(__xludf.DUMMYFUNCTION("""COMPUTED_VALUE"""),20379.0) -> 20379 | O47: =IFERROR(__xludf.DUMMYFUNCTION("""COMPUTED_VALUE"""),57.0) -> 57 | P47: =IFERROR(__xludf.DUMMYFUNCTION("""COMPUTED_VALUE"""),29.0) -> 29 | Q47: =IFERROR(__xludf.DUMMYFUNCTION("""COMPUTED_VALUE"""),70.0) -> 70 | R47: =IFERROR(__xludf.DUMMYFUNCTION("""COMPUTED_VALUE"""),171.0) -> 171 | S47: =IFERROR(__xludf.DUMMYFUNCTION("""COMPUTED_VALUE"""),0.3333333333333333) -> 0.33333333 | T47: =IFERROR(__xludf.DUMMYFUNCTION("""COMPUTED_VALUE"""),443.0217391304348) -> 443.02174 | U47: =IFERROR(__xludf.DUMMYFUNCTION("""COMPUTED_VALUE"""),1.2391304347826086) -> 1.2391304 | V47: =IFERROR(__xludf.DUMMYFUNCTION("""COMPUTED_VALUE"""),0.6304347826086957) -> 0.63043478 | W47: =IFERROR(__xludf.DUMMYFUNCTION("""COMPUTED_VALUE"""),1.5217391304347827) -> 1.5217391 | X47: =IFERROR(__xludf.DUMMYFUNCTION("""COMPUTED_VALUE"""),3.717391304347826) -> 3.7173913 | Y47: =IFERROR(__xludf.DUMMYFUNCTION("""COMPUTED_VALUE"""),14.0) -> 14 | Z47: =IFERROR(__xludf.DUMMYFUNCTION("""COMPUTED_VALUE"""),8.0) -> 8 | AA47: =IFERROR(__xludf.DUMMYFUNCTION("""COMPUTED_VALUE"""),3.0) -> 3 | AB47: =IFERROR(__xludf.DUMMYFUNCTION("""COMPUTED_VALUE"""),10.0) -> 10 | AC47: =IFERROR(__xludf.DUMMYFUNCTION("""COMPUTED_VALUE"""),28.0) -> 28 | AD47: =IFERROR(__xludf.DUMMYFUNCTION("""COMPUTED_VALUE"""),44.0) -> 44
A48: =IFERROR(__xludf.DUMMYFUNCTION("""COMPUTED_VALUE"""),"Challenger") -> Challenger | B48: =IFERROR(__xludf.DUMMYFUNCTION("""COMPUTED_VALUE"""),"RSC008454") -> RSC008454 | C48: =IFERROR(__xludf.DUMMYFUNCTION("""COMPUTED_VALUE"""),"Worma") -> Worma | D48: =IFERROR(__xludf.DUMMYFUNCTION("""COMPUTED_VALUE"""),"Blitzars") -> Blitzars | E48: =IFERROR(__xludf.DUMMYFUNCTION("""COMPUTED_VALUE"""),"Lunar") -> Lunar | F48: =IFERROR(__xludf.DUMMYFUNCTION("""COMPUTED_VALUE"""),88.74814519888562) -> 88.748145 | G48: =IFERROR(__xludf.DUMMYFUNCTION("""COMPUTED_VALUE"""),90.26671848285659) -> 90.266718 | H48: =IFERROR(__xludf.DUMMYFUNCTION("""COMPUTED_VALUE"""),89.5074318408711) -> 89.507432 | I48: =IFERROR(__xludf.DUMMYFUNCTION("""COMPUTED_VALUE"""),49.0) -> 49 | J48: =IFERROR(__xludf.DUMMYFUNCTION("IFERROR(FILTER(Stats!$F:$Z,(Stats!$A:$A=$A48)*(Stats!$B:$B=$B48)))"),28.0) -> 28 | K48: =IFERROR(__xludf.DUMMYFUNCTION("""COMPUTED_VALUE"""),21.0) -> 21 | L48: =IFERROR(__xludf.DUMMYFUNCTION("""COMPUTED_VALUE"""),0.5714285714285714) -> 0.57142857 | M48: =IFERROR(__xludf.DUMMYFUNCTION("""COMPUTED_VALUE"""),16.0) -> 16 | N48: =IFERROR(__xludf.DUMMYFUNCTION("""COMPUTED_VALUE"""),20088.0) -> 20088 | O48: =IFERROR(__xludf.DUMMYFUNCTION("""COMPUTED_VALUE"""),54.0) -> 54 | P48: =IFERROR(__xludf.DUMMYFUNCTION("""COMPUTED_VALUE"""),29.0) -> 29 | Q48: =IFERROR(__xludf.DUMMYFUNCTION("""COMPUTED_VALUE"""),65.0) -> 65 | R48: =IFERROR(__xludf.DUMMYFUNCTION("""COMPUTED_VALUE"""),158.0) -> 158 | S48: =IFERROR(__xludf.DUMMYFUNCTION("""COMPUTED_VALUE"""),0.34177215189873417) -> 0.34177215 | T48: =IFERROR(__xludf.DUMMYFUNCTION("""COMPUTED_VALUE"""),409.9591836734694) -> 409.95918 | U48: =IFERROR(__xludf.DUMMYFUNCTION("""COMPUTED_VALUE"""),1.1020408163265305) -> 1.1020408 | V48: =IFERROR(__xludf.DUMMYFUNCTION("""COMPUTED_VALUE"""),0.5918367346938775) -> 0.59183673 | W48: =IFERROR(__xludf.DUMMYFUNCTION("""COMPUTED_VALUE"""),1.3265306122448979) -> 1.3265306 | X48: =IFERROR(__xludf.DUMMYFUNCTION("""COMPUTED_VALUE"""),3.2244897959183674) -> 3.2244898 | Y48: =IFERROR(__xludf.DUMMYFUNCTION("""COMPUTED_VALUE"""),12.0) -> 12 | Z48: =IFERROR(__xludf.DUMMYFUNCTION("""COMPUTED_VALUE"""),6.0) -> 6 | AA48: =IFERROR(__xludf.DUMMYFUNCTION("""COMPUTED_VALUE"""),2.0) -> 2 | AB48: =IFERROR(__xludf.DUMMYFUNCTION("""COMPUTED_VALUE"""),9.0) -> 9 | AC48: =IFERROR(__xludf.DUMMYFUNCTION("""COMPUTED_VALUE"""),25.0) -> 25 | AD48: =IFERROR(__xludf.DUMMYFUNCTION("""COMPUTED_VALUE"""),38.0) -> 38
A49: =IFERROR(__xludf.DUMMYFUNCTION("""COMPUTED_VALUE"""),"Challenger") -> Challenger | B49: =IFERROR(__xludf.DUMMYFUNCTION("""COMPUTED_VALUE"""),"RSC006240") -> RSC006240 | C49: =IFERROR(__xludf.DUMMYFUNCTION("""COMPUTED_VALUE"""),"Canadian Gamer") -> Canadian Gamer | D49: =IFERROR(__xludf.DUMMYFUNCTION("""COMPUTED_VALUE"""),"Manticore") -> Manticore | E49: =IFERROR(__xludf.DUMMYFUNCTION("""COMPUTED_VALUE"""),"Solar") -> Solar | F49: =IFERROR(__xludf.DUMMYFUNCTION("""COMPUTED_VALUE"""),73.70759829650235) -> 73.707598 | G49: =IFERROR(__xludf.DUMMYFUNCTION("""COMPUTED_VALUE"""),103.16323194465882) -> 103.16323 | H49: =IFERROR(__xludf.DUMMYFUNCTION("""COMPUTED_VALUE"""),88.43541512058059) -> 88.435415 | I49: =IFERROR(__xludf.DUMMYFUNCTION("""COMPUTED_VALUE"""),52.0) -> 52 | J49: =IFERROR(__xludf.DUMMYFUNCTION("IFERROR(FILTER(Stats!$F:$Z,(Stats!$A:$A=$A49)*(Stats!$B:$B=$B49)))"),39.0) -> 39 | K49: =IFERROR(__xludf.DUMMYFUNCTION("""COMPUTED_VALUE"""),13.0) -> 13 | L49: =IFERROR(__xludf.DUMMYFUNCTION("""COMPUTED_VALUE"""),0.75) -> 0.75 | M49: =IFERROR(__xludf.DUMMYFUNCTION("""COMPUTED_VALUE"""),14.0) -> 14 | N49: =IFERROR(__xludf.DUMMYFUNCTION("""COMPUTED_VALUE"""),20440.0) -> 20440 | O49: =IFERROR(__xludf.DUMMYFUNCTION("""COMPUTED_VALUE"""),65.0) -> 65 | P49: =IFERROR(__xludf.DUMMYFUNCTION("""COMPUTED_VALUE"""),38.0) -> 38 | Q49: =IFERROR(__xludf.DUMMYFUNCTION("""COMPUTED_VALUE"""),60.0) -> 60 | R49: =IFERROR(__xludf.DUMMYFUNCTION("""COMPUTED_VALUE"""),157.0) -> 157 | S49: =IFERROR(__xludf.DUMMYFUNCTION("""COMPUTED_VALUE"""),0.4140127388535032) -> 0.41401274 | T49: =IFERROR(__xludf.DUMMYFUNCTION("""COMPUTED_VALUE"""),393.0769230769231) -> 393.07692 | U49: =IFERROR(__xludf.DUMMYFUNCTION("""COMPUTED_VALUE"""),1.25) -> 1.25 | V49: =IFERROR(__xludf.DUMMYFUNCTION("""COMPUTED_VALUE"""),0.7307692307692307) -> 0.73076923 | W49: =IFERROR(__xludf.DUMMYFUNCTION("""COMPUTED_VALUE"""),1.1538461538461537) -> 1.1538462 | X49: =IFERROR(__xludf.DUMMYFUNCTION("""COMPUTED_VALUE"""),3.019230769230769) -> 3.0192308 | Y49: =IFERROR(__xludf.DUMMYFUNCTION("""COMPUTED_VALUE"""),13.0) -> 13 | Z49: =IFERROR(__xludf.DUMMYFUNCTION("""COMPUTED_VALUE"""),6.0) -> 6 | AA49: =IFERROR(__xludf.DUMMYFUNCTION("""COMPUTED_VALUE"""),3.0) -> 3 | AB49: =IFERROR(__xludf.DUMMYFUNCTION("""COMPUTED_VALUE"""),8.0) -> 8 | AC49: =IFERROR(__xludf.DUMMYFUNCTION("""COMPUTED_VALUE"""),46.0) -> 46 | AD49: =IFERROR(__xludf.DUMMYFUNCTION("""COMPUTED_VALUE"""),42.0) -> 42
A50: =IFERROR(__xludf.DUMMYFUNCTION("""COMPUTED_VALUE"""),"Challenger") -> Challenger | B50: =IFERROR(__xludf.DUMMYFUNCTION("""COMPUTED_VALUE"""),"RSC000014") -> RSC000014 | C50: =IFERROR(__xludf.DUMMYFUNCTION("""COMPUTED_VALUE"""),"Queue") -> Queue | D50: =IFERROR(__xludf.DUMMYFUNCTION("""COMPUTED_VALUE"""),"Manticore") -> Manticore | E50: =IFERROR(__xludf.DUMMYFUNCTION("""COMPUTED_VALUE"""),"Solar") -> Solar | F50: =IFERROR(__xludf.DUMMYFUNCTION("""COMPUTED_VALUE"""),76.35887811433051) -> 76.358878 | G50: =IFERROR(__xludf.DUMMYFUNCTION("""COMPUTED_VALUE"""),99.3637756685939) -> 99.363776 | H50: =IFERROR(__xludf.DUMMYFUNCTION("""COMPUTED_VALUE"""),87.8613268914622) -> 87.861327 | I50: =IFERROR(__xludf.DUMMYFUNCTION("""COMPUTED_VALUE"""),56.0) -> 56 | J50: =IFERROR(__xludf.DUMMYFUNCTION("IFERROR(FILTER(Stats!$F:$Z,(Stats!$A:$A=$A50)*(Stats!$B:$B=$B50)))"),40.0) -> 40 | K50: =IFERROR(__xludf.DUMMYFUNCTION("""COMPUTED_VALUE"""),16.0) -> 16 | L50: =IFERROR(__xludf.DUMMYFUNCTION("""COMPUTED_VALUE"""),0.7142857142857143) -> 0.71428571 | M50: =IFERROR(__xludf.DUMMYFUNCTION("""COMPUTED_VALUE"""),11.0) -> 11 | N50: =IFERROR(__xludf.DUMMYFUNCTION("""COMPUTED_VALUE"""),20958.0) -> 20958 | O50: =IFERROR(__xludf.DUMMYFUNCTION("""COMPUTED_VALUE"""),47.0) -> 47 | P50: =IFERROR(__xludf.DUMMYFUNCTION("""COMPUTED_VALUE"""),50.0) -> 50 | Q50: =IFERROR(__xludf.DUMMYFUNCTION("""COMPUTED_VALUE"""),55.0) -> 55 | R50: =IFERROR(__xludf.DUMMYFUNCTION("""COMPUTED_VALUE"""),179.0) -> 179 | S50: =IFERROR(__xludf.DUMMYFUNCTION("""COMPUTED_VALUE"""),0.26256983240223464) -> 0.26256983 | T50: =IFERROR(__xludf.DUMMYFUNCTION("""COMPUTED_VALUE"""),374.25) -> 374.25 | U50: =IFERROR(__xludf.DUMMYFUNCTION("""COMPUTED_VALUE"""),0.8392857142857143) -> 0.83928571 | V50: =IFERROR(__xludf.DUMMYFUNCTION("""COMPUTED_VALUE"""),0.8928571428571429) -> 0.89285714 | W50: =IFERROR(__xludf.DUMMYFUNCTION("""COMPUTED_VALUE"""),0.9821428571428571) -> 0.98214286 | X50: =IFERROR(__xludf.DUMMYFUNCTION("""COMPUTED_VALUE"""),3.1964285714285716) -> 3.1964286 | Y50: =IFERROR(__xludf.DUMMYFUNCTION("""COMPUTED_VALUE"""),10.0) -> 10 | Z50: =IFERROR(__xludf.DUMMYFUNCTION("""COMPUTED_VALUE"""),3.0) -> 3 | AA50: =IFERROR(__xludf.DUMMYFUNCTION("""COMPUTED_VALUE"""),4.0) -> 4 | AB50: =IFERROR(__xludf.DUMMYFUNCTION("""COMPUTED_VALUE"""),4.0) -> 4 | AC50: =IFERROR(__xludf.DUMMYFUNCTION("""COMPUTED_VALUE"""),62.0) -> 62 | AD50: =IFERROR(__xludf.DUMMYFUNCTION("""COMPUTED_VALUE"""),58.0) -> 58
A51: =IFERROR(__xludf.DUMMYFUNCTION("""COMPUTED_VALUE"""),"Challenger") -> Challenger | B51: =IFERROR(__xludf.DUMMYFUNCTION("""COMPUTED_VALUE"""),"RSC008426") -> RSC008426 | C51: =IFERROR(__xludf.DUMMYFUNCTION("""COMPUTED_VALUE"""),"Midnight") -> Midnight | D51: =IFERROR(__xludf.DUMMYFUNCTION("""COMPUTED_VALUE"""),"Warbirds") -> Warbirds | E51: =IFERROR(__xludf.DUMMYFUNCTION("""COMPUTED_VALUE"""),"Lunar") -> Lunar | F51: =IFERROR(__xludf.DUMMYFUNCTION("""COMPUTED_VALUE"""),81.92090532566553) -> 81.920905 | G51: =IFERROR(__xludf.DUMMYFUNCTION("""COMPUTED_VALUE"""),90.77928271363535) -> 90.779283 | H51: =IFERROR(__xludf.DUMMYFUNCTION("""COMPUTED_VALUE"""),86.35009401965044) -> 86.350094 | I51: =IFERROR(__xludf.DUMMYFUNCTION("""COMPUTED_VALUE"""),52.0) -> 52 | J51: =IFERROR(__xludf.DUMMYFUNCTION("IFERROR(FILTER(Stats!$F:$Z,(Stats!$A:$A=$A51)*(Stats!$B:$B=$B51)))"),32.0) -> 32 | K51: =IFERROR(__xludf.DUMMYFUNCTION("""COMPUTED_VALUE"""),20.0) -> 20 | L51: =IFERROR(__xludf.DUMMYFUNCTION("""COMPUTED_VALUE"""),0.6153846153846154) -> 0.61538462 | M51: =IFERROR(__xludf.DUMMYFUNCTION("""COMPUTED_VALUE"""),18.0) -> 18 | N51: =IFERROR(__xludf.DUMMYFUNCTION("""COMPUTED_VALUE"""),22495.0) -> 22495 | O51: =IFERROR(__xludf.DUMMYFUNCTION("""COMPUTED_VALUE"""),66.0) -> 66 | P51: =IFERROR(__xludf.DUMMYFUNCTION("""COMPUTED_VALUE"""),27.0) -> 27 | Q51: =IFERROR(__xludf.DUMMYFUNCTION("""COMPUTED_VALUE"""),68.0) -> 68 | R51: =IFERROR(__xludf.DUMMYFUNCTION("""COMPUTED_VALUE"""),162.0) -> 162 | S51: =IFERROR(__xludf.DUMMYFUNCTION("""COMPUTED_VALUE"""),0.4074074074074074) -> 0.40740741 | T51: =IFERROR(__xludf.DUMMYFUNCTION("""COMPUTED_VALUE"""),432.59615384615387) -> 432.59615 | U51: =IFERROR(__xludf.DUMMYFUNCTION("""COMPUTED_VALUE"""),1.2692307692307692) -> 1.2692308 | V51: =IFERROR(__xludf.DUMMYFUNCTION("""COMPUTED_VALUE"""),0.5192307692307693) -> 0.51923077 | W51: =IFERROR(__xludf.DUMMYFUNCTION("""COMPUTED_VALUE"""),1.3076923076923077) -> 1.3076923 | X51: =IFERROR(__xludf.DUMMYFUNCTION("""COMPUTED_VALUE"""),3.1153846153846154) -> 3.1153846 | Y51: =IFERROR(__xludf.DUMMYFUNCTION("""COMPUTED_VALUE"""),13.0) -> 13 | Z51: =IFERROR(__xludf.DUMMYFUNCTION("""COMPUTED_VALUE"""),5.0) -> 5 | AA51: =IFERROR(__xludf.DUMMYFUNCTION("""COMPUTED_VALUE"""),0.0) -> 0 | AB51: =IFERROR(__xludf.DUMMYFUNCTION("""COMPUTED_VALUE"""),10.0) -> 10 | AC51: =IFERROR(__xludf.DUMMYFUNCTION("""COMPUTED_VALUE"""),49.0) -> 49 | AD51: =IFERROR(__xludf.DUMMYFUNCTION("""COMPUTED_VALUE"""),41.0) -> 41
A52: =IFERROR(__xludf.DUMMYFUNCTION("""COMPUTED_VALUE"""),"Challenger") -> Challenger | B52: =IFERROR(__xludf.DUMMYFUNCTION("""COMPUTED_VALUE"""),"RSC006067") -> RSC006067 | C52: =IFERROR(__xludf.DUMMYFUNCTION("""COMPUTED_VALUE"""),"ShinxX403") -> ShinxX403 | D52: =IFERROR(__xludf.DUMMYFUNCTION("""COMPUTED_VALUE"""),"Panda Bears") -> Panda Bears | E52: =IFERROR(__xludf.DUMMYFUNCTION("""COMPUTED_VALUE"""),"Solar") -> Solar | F52: =IFERROR(__xludf.DUMMYFUNCTION("""COMPUTED_VALUE"""),80.29185194136352) -> 80.291852 | G52: =IFERROR(__xludf.DUMMYFUNCTION("""COMPUTED_VALUE"""),92.23189699110125) -> 92.231897 | H52: =IFERROR(__xludf.DUMMYFUNCTION("""COMPUTED_VALUE"""),86.26187446623238) -> 86.261874 | I52: =IFERROR(__xludf.DUMMYFUNCTION("""COMPUTED_VALUE"""),56.0) -> 56 | J52: =IFERROR(__xludf.DUMMYFUNCTION("IFERROR(FILTER(Stats!$F:$Z,(Stats!$A:$A=$A52)*(Stats!$B:$B=$B52)))"),32.0) -> 32 | K52: =IFERROR(__xludf.DUMMYFUNCTION("""COMPUTED_VALUE"""),24.0) -> 24 | L52: =IFERROR(__xludf.DUMMYFUNCTION("""COMPUTED_VALUE"""),0.5714285714285714) -> 0.57142857 | M52: =IFERROR(__xludf.DUMMYFUNCTION("""COMPUTED_VALUE"""),14.0) -> 14 | N52: =IFERROR(__xludf.DUMMYFUNCTION("""COMPUTED_VALUE"""),22246.0) -> 22246 | O52: =IFERROR(__xludf.DUMMYFUNCTION("""COMPUTED_VALUE"""),52.0) -> 52 | P52: =IFERROR(__xludf.DUMMYFUNCTION("""COMPUTED_VALUE"""),48.0) -> 48 | Q52: =IFERROR(__xludf.DUMMYFUNCTION("""COMPUTED_VALUE"""),78.0) -> 78 | R52: =IFERROR(__xludf.DUMMYFUNCTION("""COMPUTED_VALUE"""),153.0) -> 153 | S52: =IFERROR(__xludf.DUMMYFUNCTION("""COMPUTED_VALUE"""),0.33986928104575165) -> 0.33986928 | T52: =IFERROR(__xludf.DUMMYFUNCTION("""COMPUTED_VALUE"""),397.25) -> 397.25 | U52: =IFERROR(__xludf.DUMMYFUNCTION("""COMPUTED_VALUE"""),0.9285714285714286) -> 0.92857143 | V52: =IFERROR(__xludf.DUMMYFUNCTION("""COMPUTED_VALUE"""),0.8571428571428571) -> 0.85714286 | W52: =IFERROR(__xludf.DUMMYFUNCTION("""COMPUTED_VALUE"""),1.3928571428571428) -> 1.3928571 | X52: =IFERROR(__xludf.DUMMYFUNCTION("""COMPUTED_VALUE"""),2.732142857142857) -> 2.7321429 | Y52: =IFERROR(__xludf.DUMMYFUNCTION("""COMPUTED_VALUE"""),18.0) -> 18 | Z52: =IFERROR(__xludf.DUMMYFUNCTION("""COMPUTED_VALUE"""),4.0) -> 4 | AA52: =IFERROR(__xludf.DUMMYFUNCTION("""COMPUTED_VALUE"""),1.0) -> 1 | AB52: =IFERROR(__xludf.DUMMYFUNCTION("""COMPUTED_VALUE"""),8.0) -> 8 | AC52: =IFERROR(__xludf.DUMMYFUNCTION("""COMPUTED_VALUE"""),47.0) -> 47 | AD52: =IFERROR(__xludf.DUMMYFUNCTION("""COMPUTED_VALUE"""),60.0) -> 60
A53: =IFERROR(__xludf.DUMMYFUNCTION("""COMPUTED_VALUE"""),"Challenger") -> Challenger | B53: =IFERROR(__xludf.DUMMYFUNCTION("""COMPUTED_VALUE"""),"RSC007153") -> RSC007153 | C53: =IFERROR(__xludf.DUMMYFUNCTION("""COMPUTED_VALUE"""),"Washyymann") -> Washyymann | D53: =IFERROR(__xludf.DUMMYFUNCTION("""COMPUTED_VALUE"""),"Apple Associates") -> Apple Associates | E53: =IFERROR(__xludf.DUMMYFUNCTION("""COMPUTED_VALUE"""),"Lunar") -> Lunar | F53: =IFERROR(__xludf.DUMMYFUNCTION("""COMPUTED_VALUE"""),79.21995281086133) -> 79.219953 | G53: =IFERROR(__xludf.DUMMYFUNCTION("""COMPUTED_VALUE"""),93.10883914764779) -> 93.108839 | H53: =IFERROR(__xludf.DUMMYFUNCTION("""COMPUTED_VALUE"""),86.16439597925455) -> 86.164396 | I53: =IFERROR(__xludf.DUMMYFUNCTION("""COMPUTED_VALUE"""),23.0) -> 23 | J53: =IFERROR(__xludf.DUMMYFUNCTION("IFERROR(FILTER(Stats!$F:$Z,(Stats!$A:$A=$A53)*(Stats!$B:$B=$B53)))"),13.0) -> 13 | K53: =IFERROR(__xludf.DUMMYFUNCTION("""COMPUTED_VALUE"""),10.0) -> 10 | L53: =IFERROR(__xludf.DUMMYFUNCTION("""COMPUTED_VALUE"""),0.5652173913043478) -> 0.56521739 | M53: =IFERROR(__xludf.DUMMYFUNCTION("""COMPUTED_VALUE"""),6.0) -> 6 | N53: =IFERROR(__xludf.DUMMYFUNCTION("""COMPUTED_VALUE"""),8438.0) -> 8438 | O53: =IFERROR(__xludf.DUMMYFUNCTION("""COMPUTED_VALUE"""),23.0) -> 23 | P53: =IFERROR(__xludf.DUMMYFUNCTION("""COMPUTED_VALUE"""),21.0) -> 21 | Q53: =IFERROR(__xludf.DUMMYFUNCTION("""COMPUTED_VALUE"""),21.0) -> 21 | R53: =IFERROR(__xludf.DUMMYFUNCTION("""COMPUTED_VALUE"""),64.0) -> 64 | S53: =IFERROR(__xludf.DUMMYFUNCTION("""COMPUTED_VALUE"""),0.359375) -> 0.359375 | T53: =IFERROR(__xludf.DUMMYFUNCTION("""COMPUTED_VALUE"""),366.8695652173913) -> 366.86957 | U53: =IFERROR(__xludf.DUMMYFUNCTION("""COMPUTED_VALUE"""),1.0) -> 1 | V53: =IFERROR(__xludf.DUMMYFUNCTION("""COMPUTED_VALUE"""),0.9130434782608695) -> 0.91304348 | W53: =IFERROR(__xludf.DUMMYFUNCTION("""COMPUTED_VALUE"""),0.9130434782608695) -> 0.91304348 | X53: =IFERROR(__xludf.DUMMYFUNCTION("""COMPUTED_VALUE"""),2.782608695652174) -> 2.7826087 | Y53: =IFERROR(__xludf.DUMMYFUNCTION("""COMPUTED_VALUE"""),7.0) -> 7 | Z53: =IFERROR(__xludf.DUMMYFUNCTION("""COMPUTED_VALUE"""),2.0) -> 2 | AA53: =IFERROR(__xludf.DUMMYFUNCTION("""COMPUTED_VALUE"""),1.0) -> 1 | AB53: =IFERROR(__xludf.DUMMYFUNCTION("""COMPUTED_VALUE"""),2.0) -> 2 | AC53: =IFERROR(__xludf.DUMMYFUNCTION("""COMPUTED_VALUE"""),32.0) -> 32 | AD53: =IFERROR(__xludf.DUMMYFUNCTION("""COMPUTED_VALUE"""),18.0) -> 18
A54: =IFERROR(__xludf.DUMMYFUNCTION("""COMPUTED_VALUE"""),"Challenger") -> Challenger | B54: =IFERROR(__xludf.DUMMYFUNCTION("""COMPUTED_VALUE"""),"RSC005570") -> RSC005570 | C54: =IFERROR(__xludf.DUMMYFUNCTION("""COMPUTED_VALUE"""),"Lupo") -> Lupo | D54: =IFERROR(__xludf.DUMMYFUNCTION("""COMPUTED_VALUE"""),"Cooks") -> Cooks | E54: =IFERROR(__xludf.DUMMYFUNCTION("""COMPUTED_VALUE"""),"Solar") -> Solar | F54: =IFERROR(__xludf.DUMMYFUNCTION("""COMPUTED_VALUE"""),71.94851499555823) -> 71.948515 | G54: =IFERROR(__xludf.DUMMYFUNCTION("""COMPUTED_VALUE"""),99.17743400179151) -> 99.177434 | H54: =IFERROR(__xludf.DUMMYFUNCTION("""COMPUTED_VALUE"""),85.56297449867486) -> 85.562974 | I54: =IFERROR(__xludf.DUMMYFUNCTION("""COMPUTED_VALUE"""),2.0) -> 2 | J54: =IFERROR(__xludf.DUMMYFUNCTION("IFERROR(FILTER(Stats!$F:$Z,(Stats!$A:$A=$A54)*(Stats!$B:$B=$B54)))"),1.0) -> 1 | K54: =IFERROR(__xludf.DUMMYFUNCTION("""COMPUTED_VALUE"""),1.0) -> 1 | L54: =IFERROR(__xludf.DUMMYFUNCTION("""COMPUTED_VALUE"""),0.5) -> 0.5 | M54: =IFERROR(__xludf.DUMMYFUNCTION("""COMPUTED_VALUE"""),0.0) -> 0 | N54: =IFERROR(__xludf.DUMMYFUNCTION("""COMPUTED_VALUE"""),709.0) -> 709 | O54: =IFERROR(__xludf.DUMMYFUNCTION("""COMPUTED_VALUE"""),3.0) -> 3 | P54: =IFERROR(__xludf.DUMMYFUNCTION("""COMPUTED_VALUE"""),1.0) -> 1 | Q54: =IFERROR(__xludf.DUMMYFUNCTION("""COMPUTED_VALUE"""),1.0) -> 1 | R54: =IFERROR(__xludf.DUMMYFUNCTION("""COMPUTED_VALUE"""),6.0) -> 6 | S54: =IFERROR(__xludf.DUMMYFUNCTION("""COMPUTED_VALUE"""),0.5) -> 0.5 | T54: =IFERROR(__xludf.DUMMYFUNCTION("""COMPUTED_VALUE"""),354.5) -> 354.5 | U54: =IFERROR(__xludf.DUMMYFUNCTION("""COMPUTED_VALUE"""),1.5) -> 1.5 | V54: =IFERROR(__xludf.DUMMYFUNCTION("""COMPUTED_VALUE"""),0.5) -> 0.5 | W54: =IFERROR(__xludf.DUMMYFUNCTION("""COMPUTED_VALUE"""),0.5) -> 0.5 | X54: =IFERROR(__xludf.DUMMYFUNCTION("""COMPUTED_VALUE"""),3.0) -> 3 | Y54: =IFERROR(__xludf.DUMMYFUNCTION("""COMPUTED_VALUE"""),0.0) -> 0 | Z54: =IFERROR(__xludf.DUMMYFUNCTION("""COMPUTED_VALUE"""),0.0) -> 0 | AA54: =IFERROR(__xludf.DUMMYFUNCTION("""COMPUTED_VALUE"""),0.0) -> 0 | AB54: =IFERROR(__xludf.DUMMYFUNCTION("""COMPUTED_VALUE"""),0.0) -> 0 | AC54: =IFERROR(__xludf.DUMMYFUNCTION("""COMPUTED_VALUE"""),1.0) -> 1 | AD54: =IFERROR(__xludf.DUMMYFUNCTION("""COMPUTED_VALUE"""),3.0) -> 3
A55: =IFERROR(__xludf.DUMMYFUNCTION("""COMPUTED_VALUE"""),"Challenger") -> Challenger | B55: =IFERROR(__xludf.DUMMYFUNCTION("""COMPUTED_VALUE"""),"RSC007370") -> RSC007370 | C55: =IFERROR(__xludf.DUMMYFUNCTION("""COMPUTED_VALUE"""),"Jarrod81535") -> Jarrod81535 | D55: =IFERROR(__xludf.DUMMYFUNCTION("""COMPUTED_VALUE"""),"Happy B-day Jess") -> Happy B-day Jess | E55: =IFERROR(__xludf.DUMMYFUNCTION("""COMPUTED_VALUE"""),"Lunar") -> Lunar | F55: =IFERROR(__xludf.DUMMYFUNCTION("""COMPUTED_VALUE"""),81.74498240728855) -> 81.744982 | G55: =IFERROR(__xludf.DUMMYFUNCTION("""COMPUTED_VALUE"""),88.54498075690128) -> 88.544981 | H55: =IFERROR(__xludf.DUMMYFUNCTION("""COMPUTED_VALUE"""),85.14498158209491) -> 85.144982 | I55: =IFERROR(__xludf.DUMMYFUNCTION("""COMPUTED_VALUE"""),54.0) -> 54 | J55: =IFERROR(__xludf.DUMMYFUNCTION("IFERROR(FILTER(Stats!$F:$Z,(Stats!$A:$A=$A55)*(Stats!$B:$B=$B55)))"),33.0) -> 33 | K55: =IFERROR(__xludf.DUMMYFUNCTION("""COMPUTED_VALUE"""),21.0) -> 21 | L55: =IFERROR(__xludf.DUMMYFUNCTION("""COMPUTED_VALUE"""),0.6111111111111112) -> 0.61111111 | M55: =IFERROR(__xludf.DUMMYFUNCTION("""COMPUTED_VALUE"""),20.0) -> 20 | N55: =IFERROR(__xludf.DUMMYFUNCTION("""COMPUTED_VALUE"""),21156.0) -> 21156 | O55: =IFERROR(__xludf.DUMMYFUNCTION("""COMPUTED_VALUE"""),57.0) -> 57 | P55: =IFERROR(__xludf.DUMMYFUNCTION("""COMPUTED_VALUE"""),35.0) -> 35 | Q55: =IFERROR(__xludf.DUMMYFUNCTION("""COMPUTED_VALUE"""),71.0) -> 71 | R55: =IFERROR(__xludf.DUMMYFUNCTION("""COMPUTED_VALUE"""),182.0) -> 182 | S55: =IFERROR(__xludf.DUMMYFUNCTION("""COMPUTED_VALUE"""),0.3131868131868132) -> 0.31318681 | T55: =IFERROR(__xludf.DUMMYFUNCTION("""COMPUTED_VALUE"""),391.77777777777777) -> 391.77778 | U55: =IFERROR(__xludf.DUMMYFUNCTION("""COMPUTED_VALUE"""),1.0555555555555556) -> 1.0555556 | V55: =IFERROR(__xludf.DUMMYFUNCTION("""COMPUTED_VALUE"""),0.6481481481481481) -> 0.64814815 | W55: =IFERROR(__xludf.DUMMYFUNCTION("""COMPUTED_VALUE"""),1.3148148148148149) -> 1.3148148 | X55: =IFERROR(__xludf.DUMMYFUNCTION("""COMPUTED_VALUE"""),3.3703703703703702) -> 3.3703704 | Y55: =IFERROR(__xludf.DUMMYFUNCTION("""COMPUTED_VALUE"""),14.0) -> 14 | Z55: =IFERROR(__xludf.DUMMYFUNCTION("""COMPUTED_VALUE"""),5.0) -> 5 | AA55: =IFERROR(__xludf.DUMMYFUNCTION("""COMPUTED_VALUE"""),4.0) -> 4 | AB55: =IFERROR(__xludf.DUMMYFUNCTION("""COMPUTED_VALUE"""),8.0) -> 8 | AC55: =IFERROR(__xludf.DUMMYFUNCTION("""COMPUTED_VALUE"""),59.0) -> 59 | AD55: =IFERROR(__xludf.DUMMYFUNCTION("""COMPUTED_VALUE"""),44.0) -> 44
A56: =IFERROR(__xludf.DUMMYFUNCTION("""COMPUTED_VALUE"""),"Challenger") -> Challenger | B56: =IFERROR(__xludf.DUMMYFUNCTION("""COMPUTED_VALUE"""),"RSC006177") -> RSC006177 | C56: =IFERROR(__xludf.DUMMYFUNCTION("""COMPUTED_VALUE"""),"Flyerrr85") -> Flyerrr85 | D56: =IFERROR(__xludf.DUMMYFUNCTION("""COMPUTED_VALUE"""),"Corals Warbirds") -> Corals Warbirds | E56: =IFERROR(__xludf.DUMMYFUNCTION("""COMPUTED_VALUE"""),"Lunar Lunar") -> Lunar Lunar | F56: =IFERROR(__xludf.DUMMYFUNCTION("""COMPUTED_VALUE"""),78.36765099638839) -> 78.367651 | G56: =IFERROR(__xludf.DUMMYFUNCTION("""COMPUTED_VALUE"""),90.70248655901648) -> 90.702487 | H56: =IFERROR(__xludf.DUMMYFUNCTION("""COMPUTED_VALUE"""),84.53506877770243) -> 84.535069 | I56: =IFERROR(__xludf.DUMMYFUNCTION("""COMPUTED_VALUE"""),56.0) -> 56 | J56: =IFERROR(__xludf.DUMMYFUNCTION("IFERROR(FILTER(Stats!$F:$Z,(Stats!$A:$A=$A56)*(Stats!$B:$B=$B56)))"),29.0) -> 29 | K56: =IFERROR(__xludf.DUMMYFUNCTION("""COMPUTED_VALUE"""),27.0) -> 27 | L56: =IFERROR(__xludf.DUMMYFUNCTION("""COMPUTED_VALUE"""),0.5178571428571429) -> 0.51785714 | M56: =IFERROR(__xludf.DUMMYFUNCTION("""COMPUTED_VALUE"""),16.0) -> 16 | N56: =IFERROR(__xludf.DUMMYFUNCTION("""COMPUTED_VALUE"""),22575.0) -> 22575 | O56: =IFERROR(__xludf.DUMMYFUNCTION("""COMPUTED_VALUE"""),52.0) -> 52 | P56: =IFERROR(__xludf.DUMMYFUNCTION("""COMPUTED_VALUE"""),41.0) -> 41 | Q56: =IFERROR(__xludf.DUMMYFUNCTION("""COMPUTED_VALUE"""),72.0) -> 72 | R56: =IFERROR(__xludf.DUMMYFUNCTION("""COMPUTED_VALUE"""),194.0) -> 194 | S56: =IFERROR(__xludf.DUMMYFUNCTION("""COMPUTED_VALUE"""),0.26804123711340205) -> 0.26804124 | T56: =IFERROR(__xludf.DUMMYFUNCTION("""COMPUTED_VALUE"""),403.125) -> 403.125 | U56: =IFERROR(__xludf.DUMMYFUNCTION("""COMPUTED_VALUE"""),0.9285714285714286) -> 0.92857143 | V56: =IFERROR(__xludf.DUMMYFUNCTION("""COMPUTED_VALUE"""),0.7321428571428571) -> 0.73214286 | W56: =IFERROR(__xludf.DUMMYFUNCTION("""COMPUTED_VALUE"""),1.2857142857142858) -> 1.2857143 | X56: =IFERROR(__xludf.DUMMYFUNCTION("""COMPUTED_VALUE"""),3.4642857142857144) -> 3.4642857 | Y56: =IFERROR(__xludf.DUMMYFUNCTION("""COMPUTED_VALUE"""),16.0) -> 16 | Z56: =IFERROR(__xludf.DUMMYFUNCTION("""COMPUTED_VALUE"""),6.0) -> 6 | AA56: =IFERROR(__xludf.DUMMYFUNCTION("""COMPUTED_VALUE"""),0.0) -> 0 | AB56: =IFERROR(__xludf.DUMMYFUNCTION("""COMPUTED_VALUE"""),8.0) -> 8 | AC56: =IFERROR(__xludf.DUMMYFUNCTION("""COMPUTED_VALUE"""),38.0) -> 38 | AD56: =IFERROR(__xludf.DUMMYFUNCTION("""COMPUTED_VALUE"""),64.0) -> 64
A57: =IFERROR(__xludf.DUMMYFUNCTION("""COMPUTED_VALUE"""),"Challenger") -> Challenger | B57: =IFERROR(__xludf.DUMMYFUNCTION("""COMPUTED_VALUE"""),"RSC008260") -> RSC008260 | C57: =IFERROR(__xludf.DUMMYFUNCTION("""COMPUTED_VALUE"""),"Crucified6856") -> Crucified6856 | D57: =IFERROR(__xludf.DUMMYFUNCTION("""COMPUTED_VALUE"""),"Glaciers") -> Glaciers | E57: =IFERROR(__xludf.DUMMYFUNCTION("""COMPUTED_VALUE"""),"Solar") -> Solar | F57: =IFERROR(__xludf.DUMMYFUNCTION("""COMPUTED_VALUE"""),85.79605027519656) -> 85.79605 | G57: =IFERROR(__xludf.DUMMYFUNCTION("""COMPUTED_VALUE"""),79.26065397857461) -> 79.260654 | H57: =IFERROR(__xludf.DUMMYFUNCTION("""COMPUTED_VALUE"""),82.52835212688558) -> 82.528352 | I57: =IFERROR(__xludf.DUMMYFUNCTION("""COMPUTED_VALUE"""),49.0) -> 49 | J57: =IFERROR(__xludf.DUMMYFUNCTION("IFERROR(FILTER(Stats!$F:$Z,(Stats!$A:$A=$A57)*(Stats!$B:$B=$B57)))"),27.0) -> 27 | K57: =IFERROR(__xludf.DUMMYFUNCTION("""COMPUTED_VALUE"""),22.0) -> 22 | L57: =IFERROR(__xludf.DUMMYFUNCTION("""COMPUTED_VALUE"""),0.5510204081632653) -> 0.55102041 | M57: =IFERROR(__xludf.DUMMYFUNCTION("""COMPUTED_VALUE"""),15.0) -> 15 | N57: =IFERROR(__xludf.DUMMYFUNCTION("""COMPUTED_VALUE"""),19944.0) -> 19944 | O57: =IFERROR(__xludf.DUMMYFUNCTION("""COMPUTED_VALUE"""),50.0) -> 50 | P57: =IFERROR(__xludf.DUMMYFUNCTION("""COMPUTED_VALUE"""),27.0) -> 27 | Q57: =IFERROR(__xludf.DUMMYFUNCTION("""COMPUTED_VALUE"""),65.0) -> 65 | R57: =IFERROR(__xludf.DUMMYFUNCTION("""COMPUTED_VALUE"""),162.0) -> 162 | S57: =IFERROR(__xludf.DUMMYFUNCTION("""COMPUTED_VALUE"""),0.30864197530864196) -> 0.30864198 | T57: =IFERROR(__xludf.DUMMYFUNCTION("""COMPUTED_VALUE"""),407.0204081632653) -> 407.02041 | U57: =IFERROR(__xludf.DUMMYFUNCTION("""COMPUTED_VALUE"""),1.0204081632653061) -> 1.0204082 | V57: =IFERROR(__xludf.DUMMYFUNCTION("""COMPUTED_VALUE"""),0.5510204081632653) -> 0.55102041 | W57: =IFERROR(__xludf.DUMMYFUNCTION("""COMPUTED_VALUE"""),1.3265306122448979) -> 1.3265306 | X57: =IFERROR(__xludf.DUMMYFUNCTION("""COMPUTED_VALUE"""),3.306122448979592) -> 3.3061224 | Y57: =IFERROR(__xludf.DUMMYFUNCTION("""COMPUTED_VALUE"""),8.0) -> 8 | Z57: =IFERROR(__xludf.DUMMYFUNCTION("""COMPUTED_VALUE"""),6.0) -> 6 | AA57: =IFERROR(__xludf.DUMMYFUNCTION("""COMPUTED_VALUE"""),0.0) -> 0 | AB57: =IFERROR(__xludf.DUMMYFUNCTION("""COMPUTED_VALUE"""),4.0) -> 4 | AC57: =IFERROR(__xludf.DUMMYFUNCTION("""COMPUTED_VALUE"""),36.0) -> 36 | AD57: =IFERROR(__xludf.DUMMYFUNCTION("""COMPUTED_VALUE"""),65.0) -> 65
A58: =IFERROR(__xludf.DUMMYFUNCTION("""COMPUTED_VALUE"""),"Challenger") -> Challenger | B58: =IFERROR(__xludf.DUMMYFUNCTION("""COMPUTED_VALUE"""),"RSC008078") -> RSC008078 | C58: =IFERROR(__xludf.DUMMYFUNCTION("""COMPUTED_VALUE"""),"ADV3RSE.") -> ADV3RSE. | D58: =IFERROR(__xludf.DUMMYFUNCTION("""COMPUTED_VALUE"""),"Cooks") -> Cooks | E58: =IFERROR(__xludf.DUMMYFUNCTION("""COMPUTED_VALUE"""),"Solar") -> Solar | F58: =IFERROR(__xludf.DUMMYFUNCTION("""COMPUTED_VALUE"""),77.70065524177859) -> 77.700655 | G58: =IFERROR(__xludf.DUMMYFUNCTION("""COMPUTED_VALUE"""),82.29311794363326) -> 82.293118 | H58: =IFERROR(__xludf.DUMMYFUNCTION("""COMPUTED_VALUE"""),79.99688659270592) -> 79.996887 | I58: =IFERROR(__xludf.DUMMYFUNCTION("""COMPUTED_VALUE"""),54.0) -> 54 | J58: =IFERROR(__xludf.DUMMYFUNCTION("IFERROR(FILTER(Stats!$F:$Z,(Stats!$A:$A=$A58)*(Stats!$B:$B=$B58)))"),35.0) -> 35 | K58: =IFERROR(__xludf.DUMMYFUNCTION("""COMPUTED_VALUE"""),19.0) -> 19 | L58: =IFERROR(__xludf.DUMMYFUNCTION("""COMPUTED_VALUE"""),0.6481481481481481) -> 0.64814815 | M58: =IFERROR(__xludf.DUMMYFUNCTION("""COMPUTED_VALUE"""),14.0) -> 14 | N58: =IFERROR(__xludf.DUMMYFUNCTION("""COMPUTED_VALUE"""),20118.0) -> 20118 | O58: =IFERROR(__xludf.DUMMYFUNCTION("""COMPUTED_VALUE"""),52.0) -> 52 | P58: =IFERROR(__xludf.DUMMYFUNCTION("""COMPUTED_VALUE"""),33.0) -> 33 | Q58: =IFERROR(__xludf.DUMMYFUNCTION("""COMPUTED_VALUE"""),65.0) -> 65 | R58: =IFERROR(__xludf.DUMMYFUNCTION("""COMPUTED_VALUE"""),175.0) -> 175 | S58: =IFERROR(__xludf.DUMMYFUNCTION("""COMPUTED_VALUE"""),0.29714285714285715) -> 0.29714286 | T58: =IFERROR(__xludf.DUMMYFUNCTION("""COMPUTED_VALUE"""),372.55555555555554) -> 372.55556 | U58: =IFERROR(__xludf.DUMMYFUNCTION("""COMPUTED_VALUE"""),0.9629629629629629) -> 0.96296296 | V58: =IFERROR(__xludf.DUMMYFUNCTION("""COMPUTED_VALUE"""),0.6111111111111112) -> 0.61111111 | W58: =IFERROR(__xludf.DUMMYFUNCTION("""COMPUTED_VALUE"""),1.2037037037037037) -> 1.2037037 | X58: =IFERROR(__xludf.DUMMYFUNCTION("""COMPUTED_VALUE"""),3.240740740740741) -> 3.2407407 | Y58: =IFERROR(__xludf.DUMMYFUNCTION("""COMPUTED_VALUE"""),8.0) -> 8 | Z58: =IFERROR(__xludf.DUMMYFUNCTION("""COMPUTED_VALUE"""),5.0) -> 5 | AA58: =IFERROR(__xludf.DUMMYFUNCTION("""COMPUTED_VALUE"""),1.0) -> 1 | AB58: =IFERROR(__xludf.DUMMYFUNCTION("""COMPUTED_VALUE"""),5.0) -> 5 | AC58: =IFERROR(__xludf.DUMMYFUNCTION("""COMPUTED_VALUE"""),44.0) -> 44 | AD58: =IFERROR(__xludf.DUMMYFUNCTION("""COMPUTED_VALUE"""),28.0) -> 28
A59: =IFERROR(__xludf.DUMMYFUNCTION("""COMPUTED_VALUE"""),"Challenger") -> Challenger | B59: =IFERROR(__xludf.DUMMYFUNCTION("""COMPUTED_VALUE"""),"RSC008393") -> RSC008393 | C59: =IFERROR(__xludf.DUMMYFUNCTION("""COMPUTED_VALUE"""),"zerajule") -> zerajule | D59: =IFERROR(__xludf.DUMMYFUNCTION("""COMPUTED_VALUE"""),"Olympic Knights") -> Olympic Knights | E59: =IFERROR(__xludf.DUMMYFUNCTION("""COMPUTED_VALUE"""),"Solar") -> Solar | F59: =IFERROR(__xludf.DUMMYFUNCTION("""COMPUTED_VALUE"""),75.79785460495914) -> 75.797855 | G59: =IFERROR(__xludf.DUMMYFUNCTION("""COMPUTED_VALUE"""),83.09658587889813) -> 83.096586 | H59: =IFERROR(__xludf.DUMMYFUNCTION("""COMPUTED_VALUE"""),79.44722024192863) -> 79.44722 | I59: =IFERROR(__xludf.DUMMYFUNCTION("""COMPUTED_VALUE"""),51.0) -> 51 | J59: =IFERROR(__xludf.DUMMYFUNCTION("IFERROR(FILTER(Stats!$F:$Z,(Stats!$A:$A=$A59)*(Stats!$B:$B=$B59)))"),36.0) -> 36 | K59: =IFERROR(__xludf.DUMMYFUNCTION("""COMPUTED_VALUE"""),15.0) -> 15 | L59: =IFERROR(__xludf.DUMMYFUNCTION("""COMPUTED_VALUE"""),0.7058823529411765) -> 0.70588235 | M59: =IFERROR(__xludf.DUMMYFUNCTION("""COMPUTED_VALUE"""),17.0) -> 17 | N59: =IFERROR(__xludf.DUMMYFUNCTION("""COMPUTED_VALUE"""),18820.0) -> 18820 | O59: =IFERROR(__xludf.DUMMYFUNCTION("""COMPUTED_VALUE"""),55.0) -> 55 | P59: =IFERROR(__xludf.DUMMYFUNCTION("""COMPUTED_VALUE"""),22.0) -> 22 | Q59: =IFERROR(__xludf.DUMMYFUNCTION("""COMPUTED_VALUE"""),48.0) -> 48 | R59: =IFERROR(__xludf.DUMMYFUNCTION("""COMPUTED_VALUE"""),160.0) -> 160 | S59: =IFERROR(__xludf.DUMMYFUNCTION("""COMPUTED_VALUE"""),0.34375) -> 0.34375 | T59: =IFERROR(__xludf.DUMMYFUNCTION("""COMPUTED_VALUE"""),369.01960784313724) -> 369.01961 | U59: =IFERROR(__xludf.DUMMYFUNCTION("""COMPUTED_VALUE"""),1.0784313725490196) -> 1.0784314 | V59: =IFERROR(__xludf.DUMMYFUNCTION("""COMPUTED_VALUE"""),0.43137254901960786) -> 0.43137255 | W59: =IFERROR(__xludf.DUMMYFUNCTION("""COMPUTED_VALUE"""),0.9411764705882353) -> 0.94117647 | X59: =IFERROR(__xludf.DUMMYFUNCTION("""COMPUTED_VALUE"""),3.1372549019607843) -> 3.1372549 | Y59: =IFERROR(__xludf.DUMMYFUNCTION("""COMPUTED_VALUE"""),7.0) -> 7 | Z59: =IFERROR(__xludf.DUMMYFUNCTION("""COMPUTED_VALUE"""),3.0) -> 3 | AA59: =IFERROR(__xludf.DUMMYFUNCTION("""COMPUTED_VALUE"""),0.0) -> 0 | AB59: =IFERROR(__xludf.DUMMYFUNCTION("""COMPUTED_VALUE"""),3.0) -> 3 | AC59: =IFERROR(__xludf.DUMMYFUNCTION("""COMPUTED_VALUE"""),40.0) -> 40 | AD59: =IFERROR(__xludf.DUMMYFUNCTION("""COMPUTED_VALUE"""),44.0) -> 44
A60: =IFERROR(__xludf.DUMMYFUNCTION("""COMPUTED_VALUE"""),"Challenger") -> Challenger | B60: =IFERROR(__xludf.DUMMYFUNCTION("""COMPUTED_VALUE"""),"RSC007190") -> RSC007190 | C60: =IFERROR(__xludf.DUMMYFUNCTION("""COMPUTED_VALUE"""),"Cagiestsafe6") -> Cagiestsafe6 | D60: =IFERROR(__xludf.DUMMYFUNCTION("""COMPUTED_VALUE"""),"Thunder Pups") -> Thunder Pups | E60: =IFERROR(__xludf.DUMMYFUNCTION("""COMPUTED_VALUE"""),"Solar") -> Solar | F60: =IFERROR(__xludf.DUMMYFUNCTION("""COMPUTED_VALUE"""),74.28403222595922) -> 74.284032 | G60: =IFERROR(__xludf.DUMMYFUNCTION("""COMPUTED_VALUE"""),78.35616460051017) -> 78.356165 | H60: =IFERROR(__xludf.DUMMYFUNCTION("""COMPUTED_VALUE"""),76.32009841323469) -> 76.320098 | I60: =IFERROR(__xludf.DUMMYFUNCTION("""COMPUTED_VALUE"""),51.0) -> 51 | J60: =IFERROR(__xludf.DUMMYFUNCTION("IFERROR(FILTER(Stats!$F:$Z,(Stats!$A:$A=$A60)*(Stats!$B:$B=$B60)))"),28.0) -> 28 | K60: =IFERROR(__xludf.DUMMYFUNCTION("""COMPUTED_VALUE"""),23.0) -> 23 | L60: =IFERROR(__xludf.DUMMYFUNCTION("""COMPUTED_VALUE"""),0.5490196078431373) -> 0.54901961 | M60: =IFERROR(__xludf.DUMMYFUNCTION("""COMPUTED_VALUE"""),12.0) -> 12 | N60: =IFERROR(__xludf.DUMMYFUNCTION("""COMPUTED_VALUE"""),21159.0) -> 21159 | O60: =IFERROR(__xludf.DUMMYFUNCTION("""COMPUTED_VALUE"""),58.0) -> 58 | P60: =IFERROR(__xludf.DUMMYFUNCTION("""COMPUTED_VALUE"""),28.0) -> 28 | Q60: =IFERROR(__xludf.DUMMYFUNCTION("""COMPUTED_VALUE"""),76.0) -> 76 | R60: =IFERROR(__xludf.DUMMYFUNCTION("""COMPUTED_VALUE"""),146.0) -> 146 | S60: =IFERROR(__xludf.DUMMYFUNCTION("""COMPUTED_VALUE"""),0.3972602739726027) -> 0.39726027 | T60: =IFERROR(__xludf.DUMMYFUNCTION("""COMPUTED_VALUE"""),414.88235294117646) -> 414.88235 | U60: =IFERROR(__xludf.DUMMYFUNCTION("""COMPUTED_VALUE"""),1.1372549019607843) -> 1.1372549 | V60: =IFERROR(__xludf.DUMMYFUNCTION("""COMPUTED_VALUE"""),0.5490196078431373) -> 0.54901961 | W60: =IFERROR(__xludf.DUMMYFUNCTION("""COMPUTED_VALUE"""),1.4901960784313726) -> 1.4901961 | X60: =IFERROR(__xludf.DUMMYFUNCTION("""COMPUTED_VALUE"""),2.8627450980392157) -> 2.8627451 | Y60: =IFERROR(__xludf.DUMMYFUNCTION("""COMPUTED_VALUE"""),10.0) -> 10 | Z60: =IFERROR(__xludf.DUMMYFUNCTION("""COMPUTED_VALUE"""),3.0) -> 3 | AA60: =IFERROR(__xludf.DUMMYFUNCTION("""COMPUTED_VALUE"""),0.0) -> 0 | AB60: =IFERROR(__xludf.DUMMYFUNCTION("""COMPUTED_VALUE"""),12.0) -> 12 | AC60: =IFERROR(__xludf.DUMMYFUNCTION("""COMPUTED_VALUE"""),34.0) -> 34 | AD60: =IFERROR(__xludf.DUMMYFUNCTION("""COMPUTED_VALUE"""),58.0) -> 58
A61: =IFERROR(__xludf.DUMMYFUNCTION("""COMPUTED_VALUE"""),"Challenger") -> Challenger | B61: =IFERROR(__xludf.DUMMYFUNCTION("""COMPUTED_VALUE"""),"RSC005603") -> RSC005603 | C61: =IFERROR(__xludf.DUMMYFUNCTION("""COMPUTED_VALUE"""),"Meta.Rl-") -> Meta.Rl- | D61: =IFERROR(__xludf.DUMMYFUNCTION("""COMPUTED_VALUE"""),"Insider Traders") -> Insider Traders | E61: =IFERROR(__xludf.DUMMYFUNCTION("""COMPUTED_VALUE"""),"Lunar") -> Lunar | F61: =IFERROR(__xludf.DUMMYFUNCTION("""COMPUTED_VALUE"""),74.9795526971508) -> 74.979553 | G61: =IFERROR(__xludf.DUMMYFUNCTION("""COMPUTED_VALUE"""),75.63058155835999) -> 75.630582 | H61: =IFERROR(__xludf.DUMMYFUNCTION("""COMPUTED_VALUE"""),75.3050671277554) -> 75.305067 | I61: =IFERROR(__xludf.DUMMYFUNCTION("""COMPUTED_VALUE"""),49.0) -> 49 | J61: =IFERROR(__xludf.DUMMYFUNCTION("IFERROR(FILTER(Stats!$F:$Z,(Stats!$A:$A=$A61)*(Stats!$B:$B=$B61)))"),27.0) -> 27 | K61: =IFERROR(__xludf.DUMMYFUNCTION("""COMPUTED_VALUE"""),22.0) -> 22 | L61: =IFERROR(__xludf.DUMMYFUNCTION("""COMPUTED_VALUE"""),0.5510204081632653) -> 0.55102041 | M61: =IFERROR(__xludf.DUMMYFUNCTION("""COMPUTED_VALUE"""),14.0) -> 14 | N61: =IFERROR(__xludf.DUMMYFUNCTION("""COMPUTED_VALUE"""),18183.0) -> 18183 | O61: =IFERROR(__xludf.DUMMYFUNCTION("""COMPUTED_VALUE"""),53.0) -> 53 | P61: =IFERROR(__xludf.DUMMYFUNCTION("""COMPUTED_VALUE"""),26.0) -> 26 | Q61: =IFERROR(__xludf.DUMMYFUNCTION("""COMPUTED_VALUE"""),54.0) -> 54 | R61: =IFERROR(__xludf.DUMMYFUNCTION("""COMPUTED_VALUE"""),134.0) -> 134 | S61: =IFERROR(__xludf.DUMMYFUNCTION("""COMPUTED_VALUE"""),0.39552238805970147) -> 0.39552239 | T61: =IFERROR(__xludf.DUMMYFUNCTION("""COMPUTED_VALUE"""),371.0816326530612) -> 371.08163 | U61: =IFERROR(__xludf.DUMMYFUNCTION("""COMPUTED_VALUE"""),1.0816326530612246) -> 1.0816327 | V61: =IFERROR(__xludf.DUMMYFUNCTION("""COMPUTED_VALUE"""),0.5306122448979592) -> 0.53061224 | W61: =IFERROR(__xludf.DUMMYFUNCTION("""COMPUTED_VALUE"""),1.1020408163265305) -> 1.1020408 | X61: =IFERROR(__xludf.DUMMYFUNCTION("""COMPUTED_VALUE"""),2.7346938775510203) -> 2.7346939 | Y61: =IFERROR(__xludf.DUMMYFUNCTION("""COMPUTED_VALUE"""),7.0) -> 7 | Z61: =IFERROR(__xludf.DUMMYFUNCTION("""COMPUTED_VALUE"""),6.0) -> 6 | AA61: =IFERROR(__xludf.DUMMYFUNCTION("""COMPUTED_VALUE"""),0.0) -> 0 | AB61: =IFERROR(__xludf.DUMMYFUNCTION("""COMPUTED_VALUE"""),5.0) -> 5 | AC61: =IFERROR(__xludf.DUMMYFUNCTION("""COMPUTED_VALUE"""),54.0) -> 54 | AD61: =IFERROR(__xludf.DUMMYFUNCTION("""COMPUTED_VALUE"""),36.0) -> 36
A62: =IFERROR(__xludf.DUMMYFUNCTION("""COMPUTED_VALUE"""),"Challenger") -> Challenger | B62: =IFERROR(__xludf.DUMMYFUNCTION("""COMPUTED_VALUE"""),"RSC006923") -> RSC006923 | C62: =IFERROR(__xludf.DUMMYFUNCTION("""COMPUTED_VALUE"""),"LostZealous") -> LostZealous | D62: =IFERROR(__xludf.DUMMYFUNCTION("""COMPUTED_VALUE"""),"Zombies") -> Zombies | E62: =IFERROR(__xludf.DUMMYFUNCTION("""COMPUTED_VALUE"""),"Lunar") -> Lunar | F62: =IFERROR(__xludf.DUMMYFUNCTION("""COMPUTED_VALUE"""),77.79969488157144) -> 77.799695 | G62: =IFERROR(__xludf.DUMMYFUNCTION("""COMPUTED_VALUE"""),71.3942844460365) -> 71.394284 | H62: =IFERROR(__xludf.DUMMYFUNCTION("""COMPUTED_VALUE"""),74.59698966380397) -> 74.59699 | I62: =IFERROR(__xludf.DUMMYFUNCTION("""COMPUTED_VALUE"""),52.0) -> 52 | J62: =IFERROR(__xludf.DUMMYFUNCTION("IFERROR(FILTER(Stats!$F:$Z,(Stats!$A:$A=$A62)*(Stats!$B:$B=$B62)))"),29.0) -> 29 | K62: =IFERROR(__xludf.DUMMYFUNCTION("""COMPUTED_VALUE"""),23.0) -> 23 | L62: =IFERROR(__xludf.DUMMYFUNCTION("""COMPUTED_VALUE"""),0.5576923076923077) -> 0.55769231 | M62: =IFERROR(__xludf.DUMMYFUNCTION("""COMPUTED_VALUE"""),15.0) -> 15 | N62: =IFERROR(__xludf.DUMMYFUNCTION("""COMPUTED_VALUE"""),20145.0) -> 20145 | O62: =IFERROR(__xludf.DUMMYFUNCTION("""COMPUTED_VALUE"""),48.0) -> 48 | P62: =IFERROR(__xludf.DUMMYFUNCTION("""COMPUTED_VALUE"""),28.0) -> 28 | Q62: =IFERROR(__xludf.DUMMYFUNCTION("""COMPUTED_VALUE"""),63.0) -> 63 | R62: =IFERROR(__xludf.DUMMYFUNCTION("""COMPUTED_VALUE"""),154.0) -> 154 | S62: =IFERROR(__xludf.DUMMYFUNCTION("""COMPUTED_VALUE"""),0.3116883116883117) -> 0.31168831 | T62: =IFERROR(__xludf.DUMMYFUNCTION("""COMPUTED_VALUE"""),387.40384615384613) -> 387.40385 | U62: =IFERROR(__xludf.DUMMYFUNCTION("""COMPUTED_VALUE"""),0.9230769230769231) -> 0.92307692 | V62: =IFERROR(__xludf.DUMMYFUNCTION("""COMPUTED_VALUE"""),0.5384615384615384) -> 0.53846154 | W62: =IFERROR(__xludf.DUMMYFUNCTION("""COMPUTED_VALUE"""),1.2115384615384615) -> 1.2115385 | X62: =IFERROR(__xludf.DUMMYFUNCTION("""COMPUTED_VALUE"""),2.9615384615384617) -> 2.9615385 | Y62: =IFERROR(__xludf.DUMMYFUNCTION("""COMPUTED_VALUE"""),9.0) -> 9 | Z62: =IFERROR(__xludf.DUMMYFUNCTION("""COMPUTED_VALUE"""),3.0) -> 3 | AA62: =IFERROR(__xludf.DUMMYFUNCTION("""COMPUTED_VALUE"""),1.0) -> 1 | AB62: =IFERROR(__xludf.DUMMYFUNCTION("""COMPUTED_VALUE"""),8.0) -> 8 | AC62: =IFERROR(__xludf.DUMMYFUNCTION("""COMPUTED_VALUE"""),80.0) -> 80 | AD62: =IFERROR(__xludf.DUMMYFUNCTION("""COMPUTED_VALUE"""),55.0) -> 55
A63: =IFERROR(__xludf.DUMMYFUNCTION("""COMPUTED_VALUE"""),"Challenger") -> Challenger | B63: =IFERROR(__xludf.DUMMYFUNCTION("""COMPUTED_VALUE"""),"RSC004618") -> RSC004618 | C63: =IFERROR(__xludf.DUMMYFUNCTION("""COMPUTED_VALUE"""),"Squirrel") -> Squirrel | D63: =IFERROR(__xludf.DUMMYFUNCTION("""COMPUTED_VALUE"""),"Spearmint") -> Spearmint | E63: =IFERROR(__xludf.DUMMYFUNCTION("""COMPUTED_VALUE"""),"Solar") -> Solar | F63: =IFERROR(__xludf.DUMMYFUNCTION("""COMPUTED_VALUE"""),74.73891703429949) -> 74.738917 | G63: =IFERROR(__xludf.DUMMYFUNCTION("""COMPUTED_VALUE"""),74.42172204519919) -> 74.421722 | H63: =IFERROR(__xludf.DUMMYFUNCTION("""COMPUTED_VALUE"""),74.58031953974934) -> 74.58032 | I63: =IFERROR(__xludf.DUMMYFUNCTION("""COMPUTED_VALUE"""),38.0) -> 38 | J63: =IFERROR(__xludf.DUMMYFUNCTION("IFERROR(FILTER(Stats!$F:$Z,(Stats!$A:$A=$A63)*(Stats!$B:$B=$B63)))"),22.0) -> 22 | K63: =IFERROR(__xludf.DUMMYFUNCTION("""COMPUTED_VALUE"""),16.0) -> 16 | L63: =IFERROR(__xludf.DUMMYFUNCTION("""COMPUTED_VALUE"""),0.5789473684210527) -> 0.57894737 | M63: =IFERROR(__xludf.DUMMYFUNCTION("""COMPUTED_VALUE"""),9.0) -> 9 | N63: =IFERROR(__xludf.DUMMYFUNCTION("""COMPUTED_VALUE"""),14377.0) -> 14377 | O63: =IFERROR(__xludf.DUMMYFUNCTION("""COMPUTED_VALUE"""),31.0) -> 31 | P63: =IFERROR(__xludf.DUMMYFUNCTION("""COMPUTED_VALUE"""),27.0) -> 27 | Q63: =IFERROR(__xludf.DUMMYFUNCTION("""COMPUTED_VALUE"""),51.0) -> 51 | R63: =IFERROR(__xludf.DUMMYFUNCTION("""COMPUTED_VALUE"""),103.0) -> 103 | S63: =IFERROR(__xludf.DUMMYFUNCTION("""COMPUTED_VALUE"""),0.30097087378640774) -> 0.30097087 | T63: =IFERROR(__xludf.DUMMYFUNCTION("""COMPUTED_VALUE"""),378.3421052631579) -> 378.34211 | U63: =IFERROR(__xludf.DUMMYFUNCTION("""COMPUTED_VALUE"""),0.8157894736842105) -> 0.81578947 | V63: =IFERROR(__xludf.DUMMYFUNCTION("""COMPUTED_VALUE"""),0.7105263157894737) -> 0.71052632 | W63: =IFERROR(__xludf.DUMMYFUNCTION("""COMPUTED_VALUE"""),1.3421052631578947) -> 1.3421053 | X63: =IFERROR(__xludf.DUMMYFUNCTION("""COMPUTED_VALUE"""),2.710526315789474) -> 2.7105263 | Y63: =IFERROR(__xludf.DUMMYFUNCTION("""COMPUTED_VALUE"""),13.0) -> 13 | Z63: =IFERROR(__xludf.DUMMYFUNCTION("""COMPUTED_VALUE"""),2.0) -> 2 | AA63: =IFERROR(__xludf.DUMMYFUNCTION("""COMPUTED_VALUE"""),1.0) -> 1 | AB63: =IFERROR(__xludf.DUMMYFUNCTION("""COMPUTED_VALUE"""),4.0) -> 4 | AC63: =IFERROR(__xludf.DUMMYFUNCTION("""COMPUTED_VALUE"""),62.0) -> 62 | AD63: =IFERROR(__xludf.DUMMYFUNCTION("""COMPUTED_VALUE"""),28.0) -> 28
A64: =IFERROR(__xludf.DUMMYFUNCTION("""COMPUTED_VALUE"""),"Challenger") -> Challenger | B64: =IFERROR(__xludf.DUMMYFUNCTION("""COMPUTED_VALUE"""),"RSC008251") -> RSC008251 | C64: =IFERROR(__xludf.DUMMYFUNCTION("""COMPUTED_VALUE"""),"Honey x Badger3") -> Honey x Badger3 | D64: =IFERROR(__xludf.DUMMYFUNCTION("""COMPUTED_VALUE"""),"Happy B-day Jess Corals") -> Happy B-day Jess Corals | E64: =IFERROR(__xludf.DUMMYFUNCTION("""COMPUTED_VALUE"""),"Lunar Lunar") -> Lunar Lunar | F64: =IFERROR(__xludf.DUMMYFUNCTION("""COMPUTED_VALUE"""),69.69736582525388) -> 69.697366 | G64: =IFERROR(__xludf.DUMMYFUNCTION("""COMPUTED_VALUE"""),75.94619083331041) -> 75.946191 | H64: =IFERROR(__xludf.DUMMYFUNCTION("""COMPUTED_VALUE"""),72.82177832928215) -> 72.821778 | I64: =IFERROR(__xludf.DUMMYFUNCTION("""COMPUTED_VALUE"""),40.0) -> 40 | J64: =IFERROR(__xludf.DUMMYFUNCTION("IFERROR(FILTER(Stats!$F:$Z,(Stats!$A:$A=$A64)*(Stats!$B:$B=$B64)))"),23.0) -> 23 | K64: =IFERROR(__xludf.DUMMYFUNCTION("""COMPUTED_VALUE"""),17.0) -> 17 | L64: =IFERROR(__xludf.DUMMYFUNCTION("""COMPUTED_VALUE"""),0.575) -> 0.575 | M64: =IFERROR(__xludf.DUMMYFUNCTION("""COMPUTED_VALUE"""),7.0) -> 7 | N64: =IFERROR(__xludf.DUMMYFUNCTION("""COMPUTED_VALUE"""),14191.0) -> 14191 | O64: =IFERROR(__xludf.DUMMYFUNCTION("""COMPUTED_VALUE"""),34.0) -> 34 | P64: =IFERROR(__xludf.DUMMYFUNCTION("""COMPUTED_VALUE"""),29.0) -> 29 | Q64: =IFERROR(__xludf.DUMMYFUNCTION("""COMPUTED_VALUE"""),41.0) -> 41 | R64: =IFERROR(__xludf.DUMMYFUNCTION("""COMPUTED_VALUE"""),124.0) -> 124 | S64: =IFERROR(__xludf.DUMMYFUNCTION("""COMPUTED_VALUE"""),0.27419354838709675) -> 0.27419355 | T64: =IFERROR(__xludf.DUMMYFUNCTION("""COMPUTED_VALUE"""),354.775) -> 354.775 | U64: =IFERROR(__xludf.DUMMYFUNCTION("""COMPUTED_VALUE"""),0.85) -> 0.85 | V64: =IFERROR(__xludf.DUMMYFUNCTION("""COMPUTED_VALUE"""),0.725) -> 0.725 | W64: =IFERROR(__xludf.DUMMYFUNCTION("""COMPUTED_VALUE"""),1.025) -> 1.025 | X64: =IFERROR(__xludf.DUMMYFUNCTION("""COMPUTED_VALUE"""),3.1) -> 3.1 | Y64: =IFERROR(__xludf.DUMMYFUNCTION("""COMPUTED_VALUE"""),10.0) -> 10 | Z64: =IFERROR(__xludf.DUMMYFUNCTION("""COMPUTED_VALUE"""),2.0) -> 2 | AA64: =IFERROR(__xludf.DUMMYFUNCTION("""COMPUTED_VALUE"""),1.0) -> 1 | AB64: =IFERROR(__xludf.DUMMYFUNCTION("""COMPUTED_VALUE"""),2.0) -> 2 | AC64: =IFERROR(__xludf.DUMMYFUNCTION("""COMPUTED_VALUE"""),54.0) -> 54 | AD64: =IFERROR(__xludf.DUMMYFUNCTION("""COMPUTED_VALUE"""),30.0) -> 30
A65: =IFERROR(__xludf.DUMMYFUNCTION("""COMPUTED_VALUE"""),"Challenger") -> Challenger | B65: =IFERROR(__xludf.DUMMYFUNCTION("""COMPUTED_VALUE"""),"RSC007911") -> RSC007911 | C65: =IFERROR(__xludf.DUMMYFUNCTION("""COMPUTED_VALUE"""),"Redhood913011") -> Redhood913011 | D65: =IFERROR(__xludf.DUMMYFUNCTION("""COMPUTED_VALUE"""),"Gold Hoarders Sirens") -> Gold Hoarders Sirens | E65: =IFERROR(__xludf.DUMMYFUNCTION("""COMPUTED_VALUE"""),"Lunar Solar") -> Lunar Solar | F65: =IFERROR(__xludf.DUMMYFUNCTION("""COMPUTED_VALUE"""),77.44378719091824) -> 77.443787 | G65: =IFERROR(__xludf.DUMMYFUNCTION("""COMPUTED_VALUE"""),68.18594118558426) -> 68.185941 | H65: =IFERROR(__xludf.DUMMYFUNCTION("""COMPUTED_VALUE"""),72.81486418825125) -> 72.814864 | I65: =IFERROR(__xludf.DUMMYFUNCTION("""COMPUTED_VALUE"""),51.0) -> 51 | J65: =IFERROR(__xludf.DUMMYFUNCTION("IFERROR(FILTER(Stats!$F:$Z,(Stats!$A:$A=$A65)*(Stats!$B:$B=$B65)))"),25.0) -> 25 | K65: =IFERROR(__xludf.DUMMYFUNCTION("""COMPUTED_VALUE"""),26.0) -> 26 | L65: =IFERROR(__xludf.DUMMYFUNCTION("""COMPUTED_VALUE"""),0.49019607843137253) -> 0.49019608 | M65: =IFERROR(__xludf.DUMMYFUNCTION("""COMPUTED_VALUE"""),11.0) -> 11 | N65: =IFERROR(__xludf.DUMMYFUNCTION("""COMPUTED_VALUE"""),21626.0) -> 21626 | O65: =IFERROR(__xludf.DUMMYFUNCTION("""COMPUTED_VALUE"""),53.0) -> 53 | P65: =IFERROR(__xludf.DUMMYFUNCTION("""COMPUTED_VALUE"""),21.0) -> 21 | Q65: =IFERROR(__xludf.DUMMYFUNCTION("""COMPUTED_VALUE"""),80.0) -> 80 | R65: =IFERROR(__xludf.DUMMYFUNCTION("""COMPUTED_VALUE"""),171.0) -> 171 | S65: =IFERROR(__xludf.DUMMYFUNCTION("""COMPUTED_VALUE"""),0.30994152046783624) -> 0.30994152 | T65: =IFERROR(__xludf.DUMMYFUNCTION("""COMPUTED_VALUE"""),424.03921568627453) -> 424.03922 | U65: =IFERROR(__xludf.DUMMYFUNCTION("""COMPUTED_VALUE"""),1.0392156862745099) -> 1.0392157 | V65: =IFERROR(__xludf.DUMMYFUNCTION("""COMPUTED_VALUE"""),0.4117647058823529) -> 0.41176471 | W65: =IFERROR(__xludf.DUMMYFUNCTION("""COMPUTED_VALUE"""),1.5686274509803921) -> 1.5686275 | X65: =IFERROR(__xludf.DUMMYFUNCTION("""COMPUTED_VALUE"""),3.3529411764705883) -> 3.3529412 | Y65: =IFERROR(__xludf.DUMMYFUNCTION("""COMPUTED_VALUE"""),8.0) -> 8 | Z65: =IFERROR(__xludf.DUMMYFUNCTION("""COMPUTED_VALUE"""),5.0) -> 5 | AA65: =IFERROR(__xludf.DUMMYFUNCTION("""COMPUTED_VALUE"""),1.0) -> 1 | AB65: =IFERROR(__xludf.DUMMYFUNCTION("""COMPUTED_VALUE"""),10.0) -> 10 | AC65: =IFERROR(__xludf.DUMMYFUNCTION("""COMPUTED_VALUE"""),32.0) -> 32 | AD65: =IFERROR(__xludf.DUMMYFUNCTION("""COMPUTED_VALUE"""),35.0) -> 35
A66: =IFERROR(__xludf.DUMMYFUNCTION("""COMPUTED_VALUE"""),"Challenger") -> Challenger | B66: =IFERROR(__xludf.DUMMYFUNCTION("""COMPUTED_VALUE"""),"RSC008026") -> RSC008026 | C66: =IFERROR(__xludf.DUMMYFUNCTION("""COMPUTED_VALUE"""),"Kanashìmi") -> Kanashìmi | D66: =IFERROR(__xludf.DUMMYFUNCTION("""COMPUTED_VALUE"""),"Havarti Hustlers") -> Havarti Hustlers | E66: =IFERROR(__xludf.DUMMYFUNCTION("""COMPUTED_VALUE"""),"Lunar") -> Lunar | F66: =IFERROR(__xludf.DUMMYFUNCTION("""COMPUTED_VALUE"""),85.35127583604574) -> 85.351276 | G66: =IFERROR(__xludf.DUMMYFUNCTION("""COMPUTED_VALUE"""),58.811696482268076) -> 58.811696 | H66: =IFERROR(__xludf.DUMMYFUNCTION("""COMPUTED_VALUE"""),72.08148615915691) -> 72.081486 | I66: =IFERROR(__xludf.DUMMYFUNCTION("""COMPUTED_VALUE"""),4.0) -> 4 | J66: =IFERROR(__xludf.DUMMYFUNCTION("IFERROR(FILTER(Stats!$F:$Z,(Stats!$A:$A=$A66)*(Stats!$B:$B=$B66)))"),1.0) -> 1 | K66: =IFERROR(__xludf.DUMMYFUNCTION("""COMPUTED_VALUE"""),3.0) -> 3 | L66: =IFERROR(__xludf.DUMMYFUNCTION("""COMPUTED_VALUE"""),0.25) -> 0.25 | M66: =IFERROR(__xludf.DUMMYFUNCTION("""COMPUTED_VALUE"""),0.0) -> 0 | N66: =IFERROR(__xludf.DUMMYFUNCTION("""COMPUTED_VALUE"""),1577.0) -> 1577 | O66: =IFERROR(__xludf.DUMMYFUNCTION("""COMPUTED_VALUE"""),4.0) -> 4 | P66: =IFERROR(__xludf.DUMMYFUNCTION("""COMPUTED_VALUE"""),2.0) -> 2 | Q66: =IFERROR(__xludf.DUMMYFUNCTION("""COMPUTED_VALUE"""),4.0) -> 4 | R66: =IFERROR(__xludf.DUMMYFUNCTION("""COMPUTED_VALUE"""),10.0) -> 10 | S66: =IFERROR(__xludf.DUMMYFUNCTION("""COMPUTED_VALUE"""),0.4) -> 0.4 | T66: =IFERROR(__xludf.DUMMYFUNCTION("""COMPUTED_VALUE"""),394.25) -> 394.25 | U66: =IFERROR(__xludf.DUMMYFUNCTION("""COMPUTED_VALUE"""),1.0) -> 1 | V66: =IFERROR(__xludf.DUMMYFUNCTION("""COMPUTED_VALUE"""),0.5) -> 0.5 | W66: =IFERROR(__xludf.DUMMYFUNCTION("""COMPUTED_VALUE"""),1.0) -> 1 | X66: =IFERROR(__xludf.DUMMYFUNCTION("""COMPUTED_VALUE"""),2.5) -> 2.5 | Y66: =IFERROR(__xludf.DUMMYFUNCTION("""COMPUTED_VALUE"""),0.0) -> 0 | Z66: =IFERROR(__xludf.DUMMYFUNCTION("""COMPUTED_VALUE"""),0.0) -> 0 | AA66: =IFERROR(__xludf.DUMMYFUNCTION("""COMPUTED_VALUE"""),0.0) -> 0 | AB66: =IFERROR(__xludf.DUMMYFUNCTION("""COMPUTED_VALUE"""),1.0) -> 1 | AC66: =IFERROR(__xludf.DUMMYFUNCTION("""COMPUTED_VALUE"""),5.0) -> 5 | AD66: =IFERROR(__xludf.DUMMYFUNCTION("""COMPUTED_VALUE"""),4.0) -> 4
A67: =IFERROR(__xludf.DUMMYFUNCTION("""COMPUTED_VALUE"""),"Challenger") -> Challenger | B67: =IFERROR(__xludf.DUMMYFUNCTION("""COMPUTED_VALUE"""),"RSC008415") -> RSC008415 | C67: =IFERROR(__xludf.DUMMYFUNCTION("""COMPUTED_VALUE"""),"StorchBurn") -> StorchBurn | D67: =IFERROR(__xludf.DUMMYFUNCTION("""COMPUTED_VALUE"""),"Threshers") -> Threshers | E67: =IFERROR(__xludf.DUMMYFUNCTION("""COMPUTED_VALUE"""),"Solar") -> Solar | F67: =IFERROR(__xludf.DUMMYFUNCTION("""COMPUTED_VALUE"""),75.1123004508204) -> 75.1123 | G67: =IFERROR(__xludf.DUMMYFUNCTION("""COMPUTED_VALUE"""),67.38582437982232) -> 67.385824 | H67: =IFERROR(__xludf.DUMMYFUNCTION("""COMPUTED_VALUE"""),71.24906241532136) -> 71.249062 | I67: =IFERROR(__xludf.DUMMYFUNCTION("""COMPUTED_VALUE"""),56.0) -> 56 | J67: =IFERROR(__xludf.DUMMYFUNCTION("IFERROR(FILTER(Stats!$F:$Z,(Stats!$A:$A=$A67)*(Stats!$B:$B=$B67)))"),32.0) -> 32 | K67: =IFERROR(__xludf.DUMMYFUNCTION("""COMPUTED_VALUE"""),24.0) -> 24 | L67: =IFERROR(__xludf.DUMMYFUNCTION("""COMPUTED_VALUE"""),0.5714285714285714) -> 0.57142857 | M67: =IFERROR(__xludf.DUMMYFUNCTION("""COMPUTED_VALUE"""),15.0) -> 15 | N67: =IFERROR(__xludf.DUMMYFUNCTION("""COMPUTED_VALUE"""),21110.0) -> 21110 | O67: =IFERROR(__xludf.DUMMYFUNCTION("""COMPUTED_VALUE"""),45.0) -> 45 | P67: =IFERROR(__xludf.DUMMYFUNCTION("""COMPUTED_VALUE"""),33.0) -> 33 | Q67: =IFERROR(__xludf.DUMMYFUNCTION("""COMPUTED_VALUE"""),90.0) -> 90 | R67: =IFERROR(__xludf.DUMMYFUNCTION("""COMPUTED_VALUE"""),138.0) -> 138 | S67: =IFERROR(__xludf.DUMMYFUNCTION("""COMPUTED_VALUE"""),0.32608695652173914) -> 0.32608696 | T67: =IFERROR(__xludf.DUMMYFUNCTION("""COMPUTED_VALUE"""),376.9642857142857) -> 376.96429 | U67: =IFERROR(__xludf.DUMMYFUNCTION("""COMPUTED_VALUE"""),0.8035714285714286) -> 0.80357143 | V67: =IFERROR(__xludf.DUMMYFUNCTION("""COMPUTED_VALUE"""),0.5892857142857143) -> 0.58928571 | W67: =IFERROR(__xludf.DUMMYFUNCTION("""COMPUTED_VALUE"""),1.6071428571428572) -> 1.6071429 | X67: =IFERROR(__xludf.DUMMYFUNCTION("""COMPUTED_VALUE"""),2.4642857142857144) -> 2.4642857 | Y67: =IFERROR(__xludf.DUMMYFUNCTION("""COMPUTED_VALUE"""),9.0) -> 9 | Z67: =IFERROR(__xludf.DUMMYFUNCTION("""COMPUTED_VALUE"""),3.0) -> 3 | AA67: =IFERROR(__xludf.DUMMYFUNCTION("""COMPUTED_VALUE"""),0.0) -> 0 | AB67: =IFERROR(__xludf.DUMMYFUNCTION("""COMPUTED_VALUE"""),9.0) -> 9 | AC67: =IFERROR(__xludf.DUMMYFUNCTION("""COMPUTED_VALUE"""),79.0) -> 79 | AD67: =IFERROR(__xludf.DUMMYFUNCTION("""COMPUTED_VALUE"""),53.0) -> 53
A68: =IFERROR(__xludf.DUMMYFUNCTION("""COMPUTED_VALUE"""),"Challenger") -> Challenger | B68: =IFERROR(__xludf.DUMMYFUNCTION("""COMPUTED_VALUE"""),"RSC006642") -> RSC006642 | C68: =IFERROR(__xludf.DUMMYFUNCTION("""COMPUTED_VALUE"""),"Zone Killa") -> Zone Killa | D68: =IFERROR(__xludf.DUMMYFUNCTION("""COMPUTED_VALUE"""),"Apple Associates") -> Apple Associates | E68: =IFERROR(__xludf.DUMMYFUNCTION("""COMPUTED_VALUE"""),"Lunar") -> Lunar | F68: =IFERROR(__xludf.DUMMYFUNCTION("""COMPUTED_VALUE"""),72.18604082037102) -> 72.186041 | G68: =IFERROR(__xludf.DUMMYFUNCTION("""COMPUTED_VALUE"""),66.8266253842831) -> 66.826625 | H68: =IFERROR(__xludf.DUMMYFUNCTION("""COMPUTED_VALUE"""),69.50633310232706) -> 69.506333 | I68: =IFERROR(__xludf.DUMMYFUNCTION("""COMPUTED_VALUE"""),43.0) -> 43 | J68: =IFERROR(__xludf.DUMMYFUNCTION("IFERROR(FILTER(Stats!$F:$Z,(Stats!$A:$A=$A68)*(Stats!$B:$B=$B68)))"),28.0) -> 28 | K68: =IFERROR(__xludf.DUMMYFUNCTION("""COMPUTED_VALUE"""),15.0) -> 15 | L68: =IFERROR(__xludf.DUMMYFUNCTION("""COMPUTED_VALUE"""),0.6511627906976745) -> 0.65116279 | M68: =IFERROR(__xludf.DUMMYFUNCTION("""COMPUTED_VALUE"""),14.0) -> 14 | N68: =IFERROR(__xludf.DUMMYFUNCTION("""COMPUTED_VALUE"""),16647.0) -> 16647 | O68: =IFERROR(__xludf.DUMMYFUNCTION("""COMPUTED_VALUE"""),42.0) -> 42 | P68: =IFERROR(__xludf.DUMMYFUNCTION("""COMPUTED_VALUE"""),24.0) -> 24 | Q68: =IFERROR(__xludf.DUMMYFUNCTION("""COMPUTED_VALUE"""),66.0) -> 66 | R68: =IFERROR(__xludf.DUMMYFUNCTION("""COMPUTED_VALUE"""),94.0) -> 94 | S68: =IFERROR(__xludf.DUMMYFUNCTION("""COMPUTED_VALUE"""),0.44680851063829785) -> 0.44680851 | T68: =IFERROR(__xludf.DUMMYFUNCTION("""COMPUTED_VALUE"""),387.13953488372096) -> 387.13953 | U68: =IFERROR(__xludf.DUMMYFUNCTION("""COMPUTED_VALUE"""),0.9767441860465116) -> 0.97674419 | V68: =IFERROR(__xludf.DUMMYFUNCTION("""COMPUTED_VALUE"""),0.5581395348837209) -> 0.55813953 | W68: =IFERROR(__xludf.DUMMYFUNCTION("""COMPUTED_VALUE"""),1.5348837209302326) -> 1.5348837 | X68: =IFERROR(__xludf.DUMMYFUNCTION("""COMPUTED_VALUE"""),2.186046511627907) -> 2.1860465 | Y68: =IFERROR(__xludf.DUMMYFUNCTION("""COMPUTED_VALUE"""),11.0) -> 11 | Z68: =IFERROR(__xludf.DUMMYFUNCTION("""COMPUTED_VALUE"""),3.0) -> 3 | AA68: =IFERROR(__xludf.DUMMYFUNCTION("""COMPUTED_VALUE"""),1.0) -> 1 | AB68: =IFERROR(__xludf.DUMMYFUNCTION("""COMPUTED_VALUE"""),11.0) -> 11 | AC68: =IFERROR(__xludf.DUMMYFUNCTION("""COMPUTED_VALUE"""),38.0) -> 38 | AD68: =IFERROR(__xludf.DUMMYFUNCTION("""COMPUTED_VALUE"""),38.0) -> 38
A69: =IFERROR(__xludf.DUMMYFUNCTION("""COMPUTED_VALUE"""),"Challenger") -> Challenger | B69: =IFERROR(__xludf.DUMMYFUNCTION("""COMPUTED_VALUE"""),"RSC006187") -> RSC006187 | C69: =IFERROR(__xludf.DUMMYFUNCTION("""COMPUTED_VALUE"""),"1999 Toyota Camry") -> 1999 Toyota Camry | D69: =IFERROR(__xludf.DUMMYFUNCTION("""COMPUTED_VALUE"""),"Corals") -> Corals | E69: =IFERROR(__xludf.DUMMYFUNCTION("""COMPUTED_VALUE"""),"Lunar") -> Lunar | F69: =IFERROR(__xludf.DUMMYFUNCTION("""COMPUTED_VALUE"""),55.41350556425243) -> 55.413506 | G69: =IFERROR(__xludf.DUMMYFUNCTION("""COMPUTED_VALUE"""),83.12324117907116) -> 83.123241 | H69: =IFERROR(__xludf.DUMMYFUNCTION("""COMPUTED_VALUE"""),69.2683733716618) -> 69.268373 | I69: =IFERROR(__xludf.DUMMYFUNCTION("""COMPUTED_VALUE"""),11.0) -> 11 | J69: =IFERROR(__xludf.DUMMYFUNCTION("IFERROR(FILTER(Stats!$F:$Z,(Stats!$A:$A=$A69)*(Stats!$B:$B=$B69)))"),4.0) -> 4 | K69: =IFERROR(__xludf.DUMMYFUNCTION("""COMPUTED_VALUE"""),7.0) -> 7 | L69: =IFERROR(__xludf.DUMMYFUNCTION("""COMPUTED_VALUE"""),0.36363636363636365) -> 0.36363636 | M69: =IFERROR(__xludf.DUMMYFUNCTION("""COMPUTED_VALUE"""),0.0) -> 0 | N69: =IFERROR(__xludf.DUMMYFUNCTION("""COMPUTED_VALUE"""),4058.0) -> 4058 | O69: =IFERROR(__xludf.DUMMYFUNCTION("""COMPUTED_VALUE"""),13.0) -> 13 | P69: =IFERROR(__xludf.DUMMYFUNCTION("""COMPUTED_VALUE"""),6.0) -> 6 | Q69: =IFERROR(__xludf.DUMMYFUNCTION("""COMPUTED_VALUE"""),11.0) -> 11 | R69: =IFERROR(__xludf.DUMMYFUNCTION("""COMPUTED_VALUE"""),32.0) -> 32 | S69: =IFERROR(__xludf.DUMMYFUNCTION("""COMPUTED_VALUE"""),0.40625) -> 0.40625 | T69: =IFERROR(__xludf.DUMMYFUNCTION("""COMPUTED_VALUE"""),368.90909090909093) -> 368.90909 | U69: =IFERROR(__xludf.DUMMYFUNCTION("""COMPUTED_VALUE"""),1.1818181818181819) -> 1.1818182 | V69: =IFERROR(__xludf.DUMMYFUNCTION("""COMPUTED_VALUE"""),0.5454545454545454) -> 0.54545455 | W69: =IFERROR(__xludf.DUMMYFUNCTION("""COMPUTED_VALUE"""),1.0) -> 1 | X69: =IFERROR(__xludf.DUMMYFUNCTION("""COMPUTED_VALUE"""),2.909090909090909) -> 2.9090909 | Y69: =IFERROR(__xludf.DUMMYFUNCTION("""COMPUTED_VALUE"""),5.0) -> 5 | Z69: =IFERROR(__xludf.DUMMYFUNCTION("""COMPUTED_VALUE"""),1.0) -> 1 | AA69: =IFERROR(__xludf.DUMMYFUNCTION("""COMPUTED_VALUE"""),0.0) -> 0 | AB69: =IFERROR(__xludf.DUMMYFUNCTION("""COMPUTED_VALUE"""),1.0) -> 1 | AC69: =IFERROR(__xludf.DUMMYFUNCTION("""COMPUTED_VALUE"""),11.0) -> 11 | AD69: =IFERROR(__xludf.DUMMYFUNCTION("""COMPUTED_VALUE"""),4.0) -> 4
A70: =IFERROR(__xludf.DUMMYFUNCTION("""COMPUTED_VALUE"""),"Challenger") -> Challenger | B70: =IFERROR(__xludf.DUMMYFUNCTION("""COMPUTED_VALUE"""),"RSC007885") -> RSC007885 | C70: =IFERROR(__xludf.DUMMYFUNCTION("""COMPUTED_VALUE"""),"Larkspur") -> Larkspur | D70: =IFERROR(__xludf.DUMMYFUNCTION("""COMPUTED_VALUE"""),"Stingrays") -> Stingrays | E70: =IFERROR(__xludf.DUMMYFUNCTION("""COMPUTED_VALUE"""),"Lunar") -> Lunar | F70: =IFERROR(__xludf.DUMMYFUNCTION("""COMPUTED_VALUE"""),60.46931745814024) -> 60.469317 | G70: =IFERROR(__xludf.DUMMYFUNCTION("""COMPUTED_VALUE"""),76.98777531613933) -> 76.987775 | H70: =IFERROR(__xludf.DUMMYFUNCTION("""COMPUTED_VALUE"""),68.72854638713979) -> 68.728546 | I70: =IFERROR(__xludf.DUMMYFUNCTION("""COMPUTED_VALUE"""),54.0) -> 54 | J70: =IFERROR(__xludf.DUMMYFUNCTION("IFERROR(FILTER(Stats!$F:$Z,(Stats!$A:$A=$A70)*(Stats!$B:$B=$B70)))"),28.0) -> 28 | K70: =IFERROR(__xludf.DUMMYFUNCTION("""COMPUTED_VALUE"""),26.0) -> 26 | L70: =IFERROR(__xludf.DUMMYFUNCTION("""COMPUTED_VALUE"""),0.5185185185185185) -> 0.51851852 | M70: =IFERROR(__xludf.DUMMYFUNCTION("""COMPUTED_VALUE"""),8.0) -> 8 | N70: =IFERROR(__xludf.DUMMYFUNCTION("""COMPUTED_VALUE"""),19386.0) -> 19386 | O70: =IFERROR(__xludf.DUMMYFUNCTION("""COMPUTED_VALUE"""),52.0) -> 52 | P70: =IFERROR(__xludf.DUMMYFUNCTION("""COMPUTED_VALUE"""),39.0) -> 39 | Q70: =IFERROR(__xludf.DUMMYFUNCTION("""COMPUTED_VALUE"""),61.0) -> 61 | R70: =IFERROR(__xludf.DUMMYFUNCTION("""COMPUTED_VALUE"""),146.0) -> 146 | S70: =IFERROR(__xludf.DUMMYFUNCTION("""COMPUTED_VALUE"""),0.3561643835616438) -> 0.35616438 | T70: =IFERROR(__xludf.DUMMYFUNCTION("""COMPUTED_VALUE"""),359.0) -> 359 | U70: =IFERROR(__xludf.DUMMYFUNCTION("""COMPUTED_VALUE"""),0.9629629629629629) -> 0.96296296 | V70: =IFERROR(__xludf.DUMMYFUNCTION("""COMPUTED_VALUE"""),0.7222222222222222) -> 0.72222222 | W70: =IFERROR(__xludf.DUMMYFUNCTION("""COMPUTED_VALUE"""),1.1296296296296295) -> 1.1296296 | X70: =IFERROR(__xludf.DUMMYFUNCTION("""COMPUTED_VALUE"""),2.7037037037037037) -> 2.7037037 | Y70: =IFERROR(__xludf.DUMMYFUNCTION("""COMPUTED_VALUE"""),9.0) -> 9 | Z70: =IFERROR(__xludf.DUMMYFUNCTION("""COMPUTED_VALUE"""),2.0) -> 2 | AA70: =IFERROR(__xludf.DUMMYFUNCTION("""COMPUTED_VALUE"""),3.0) -> 3 | AB70: =IFERROR(__xludf.DUMMYFUNCTION("""COMPUTED_VALUE"""),6.0) -> 6 | AC70: =IFERROR(__xludf.DUMMYFUNCTION("""COMPUTED_VALUE"""),54.0) -> 54 | AD70: =IFERROR(__xludf.DUMMYFUNCTION("""COMPUTED_VALUE"""),63.0) -> 63
A71: =IFERROR(__xludf.DUMMYFUNCTION("""COMPUTED_VALUE"""),"Challenger") -> Challenger | B71: =IFERROR(__xludf.DUMMYFUNCTION("""COMPUTED_VALUE"""),"RSC000233") -> RSC000233 | C71: =IFERROR(__xludf.DUMMYFUNCTION("""COMPUTED_VALUE"""),"LilPrsnWithAnger") -> LilPrsnWithAnger | D71: =IFERROR(__xludf.DUMMYFUNCTION("""COMPUTED_VALUE"""),"Corals") -> Corals | E71: =IFERROR(__xludf.DUMMYFUNCTION("""COMPUTED_VALUE"""),"Lunar") -> Lunar | F71: =IFERROR(__xludf.DUMMYFUNCTION("""COMPUTED_VALUE"""),61.840317208197796) -> 61.840317 | G71: =IFERROR(__xludf.DUMMYFUNCTION("""COMPUTED_VALUE"""),75.05653990117439) -> 75.05654 | H71: =IFERROR(__xludf.DUMMYFUNCTION("""COMPUTED_VALUE"""),68.44842855468609) -> 68.448429 | I71: =IFERROR(__xludf.DUMMYFUNCTION("""COMPUTED_VALUE"""),20.0) -> 20 | J71: =IFERROR(__xludf.DUMMYFUNCTION("IFERROR(FILTER(Stats!$F:$Z,(Stats!$A:$A=$A71)*(Stats!$B:$B=$B71)))"),16.0) -> 16 | K71: =IFERROR(__xludf.DUMMYFUNCTION("""COMPUTED_VALUE"""),4.0) -> 4 | L71: =IFERROR(__xludf.DUMMYFUNCTION("""COMPUTED_VALUE"""),0.8) -> 0.8 | M71: =IFERROR(__xludf.DUMMYFUNCTION("""COMPUTED_VALUE"""),3.0) -> 3 | N71: =IFERROR(__xludf.DUMMYFUNCTION("""COMPUTED_VALUE"""),6833.0) -> 6833 | O71: =IFERROR(__xludf.DUMMYFUNCTION("""COMPUTED_VALUE"""),16.0) -> 16 | P71: =IFERROR(__xludf.DUMMYFUNCTION("""COMPUTED_VALUE"""),16.0) -> 16 | Q71: =IFERROR(__xludf.DUMMYFUNCTION("""COMPUTED_VALUE"""),21.0) -> 21 | R71: =IFERROR(__xludf.DUMMYFUNCTION("""COMPUTED_VALUE"""),49.0) -> 49 | S71: =IFERROR(__xludf.DUMMYFUNCTION("""COMPUTED_VALUE"""),0.32653061224489793) -> 0.32653061 | T71: =IFERROR(__xludf.DUMMYFUNCTION("""COMPUTED_VALUE"""),341.65) -> 341.65 | U71: =IFERROR(__xludf.DUMMYFUNCTION("""COMPUTED_VALUE"""),0.8) -> 0.8 | V71: =IFERROR(__xludf.DUMMYFUNCTION("""COMPUTED_VALUE"""),0.8) -> 0.8 | W71: =IFERROR(__xludf.DUMMYFUNCTION("""COMPUTED_VALUE"""),1.05) -> 1.05 | X71: =IFERROR(__xludf.DUMMYFUNCTION("""COMPUTED_VALUE"""),2.45) -> 2.45 | Y71: =IFERROR(__xludf.DUMMYFUNCTION("""COMPUTED_VALUE"""),2.0) -> 2 | Z71: =IFERROR(__xludf.DUMMYFUNCTION("""COMPUTED_VALUE"""),2.0) -> 2 | AA71: =IFERROR(__xludf.DUMMYFUNCTION("""COMPUTED_VALUE"""),0.0) -> 0 | AB71: =IFERROR(__xludf.DUMMYFUNCTION("""COMPUTED_VALUE"""),1.0) -> 1 | AC71: =IFERROR(__xludf.DUMMYFUNCTION("""COMPUTED_VALUE"""),29.0) -> 29 | AD71: =IFERROR(__xludf.DUMMYFUNCTION("""COMPUTED_VALUE"""),29.0) -> 29
A72: =IFERROR(__xludf.DUMMYFUNCTION("""COMPUTED_VALUE"""),"Challenger") -> Challenger | B72: =IFERROR(__xludf.DUMMYFUNCTION("""COMPUTED_VALUE"""),"RSC007865") -> RSC007865 | C72: =IFERROR(__xludf.DUMMYFUNCTION("""COMPUTED_VALUE"""),"StoveMessiah") -> StoveMessiah | D72: =IFERROR(__xludf.DUMMYFUNCTION("""COMPUTED_VALUE"""),"Stingrays") -> Stingrays | E72: =IFERROR(__xludf.DUMMYFUNCTION("""COMPUTED_VALUE"""),"Lunar") -> Lunar | F72: =IFERROR(__xludf.DUMMYFUNCTION("""COMPUTED_VALUE"""),60.77497387125234) -> 60.774974 | G72: =IFERROR(__xludf.DUMMYFUNCTION("""COMPUTED_VALUE"""),75.31937367127131) -> 75.319374 | H72: =IFERROR(__xludf.DUMMYFUNCTION("""COMPUTED_VALUE"""),68.04717377126182) -> 68.047174 | I72: =IFERROR(__xludf.DUMMYFUNCTION("""COMPUTED_VALUE"""),54.0) -> 54 | J72: =IFERROR(__xludf.DUMMYFUNCTION("IFERROR(FILTER(Stats!$F:$Z,(Stats!$A:$A=$A72)*(Stats!$B:$B=$B72)))"),29.0) -> 29 | K72: =IFERROR(__xludf.DUMMYFUNCTION("""COMPUTED_VALUE"""),25.0) -> 25 | L72: =IFERROR(__xludf.DUMMYFUNCTION("""COMPUTED_VALUE"""),0.5370370370370371) -> 0.53703704 | M72: =IFERROR(__xludf.DUMMYFUNCTION("""COMPUTED_VALUE"""),9.0) -> 9 | N72: =IFERROR(__xludf.DUMMYFUNCTION("""COMPUTED_VALUE"""),19976.0) -> 19976 | O72: =IFERROR(__xludf.DUMMYFUNCTION("""COMPUTED_VALUE"""),54.0) -> 54 | P72: =IFERROR(__xludf.DUMMYFUNCTION("""COMPUTED_VALUE"""),37.0) -> 37 | Q72: =IFERROR(__xludf.DUMMYFUNCTION("""COMPUTED_VALUE"""),65.0) -> 65 | R72: =IFERROR(__xludf.DUMMYFUNCTION("""COMPUTED_VALUE"""),142.0) -> 142 | S72: =IFERROR(__xludf.DUMMYFUNCTION("""COMPUTED_VALUE"""),0.38028169014084506) -> 0.38028169 | T72: =IFERROR(__xludf.DUMMYFUNCTION("""COMPUTED_VALUE"""),369.9259259259259) -> 369.92593 | U72: =IFERROR(__xludf.DUMMYFUNCTION("""COMPUTED_VALUE"""),1.0) -> 1 | V72: =IFERROR(__xludf.DUMMYFUNCTION("""COMPUTED_VALUE"""),0.6851851851851852) -> 0.68518519 | W72: =IFERROR(__xludf.DUMMYFUNCTION("""COMPUTED_VALUE"""),1.2037037037037037) -> 1.2037037 | X72: =IFERROR(__xludf.DUMMYFUNCTION("""COMPUTED_VALUE"""),2.6296296296296298) -> 2.6296296 | Y72: =IFERROR(__xludf.DUMMYFUNCTION("""COMPUTED_VALUE"""),11.0) -> 11 | Z72: =IFERROR(__xludf.DUMMYFUNCTION("""COMPUTED_VALUE"""),5.0) -> 5 | AA72: =IFERROR(__xludf.DUMMYFUNCTION("""COMPUTED_VALUE"""),0.0) -> 0 | AB72: =IFERROR(__xludf.DUMMYFUNCTION("""COMPUTED_VALUE"""),6.0) -> 6 | AC72: =IFERROR(__xludf.DUMMYFUNCTION("""COMPUTED_VALUE"""),35.0) -> 35 | AD72: =IFERROR(__xludf.DUMMYFUNCTION("""COMPUTED_VALUE"""),43.0) -> 43
A73: =IFERROR(__xludf.DUMMYFUNCTION("""COMPUTED_VALUE"""),"Challenger") -> Challenger | B73: =IFERROR(__xludf.DUMMYFUNCTION("""COMPUTED_VALUE"""),"RSC008466") -> RSC008466 | C73: =IFERROR(__xludf.DUMMYFUNCTION("""COMPUTED_VALUE"""),"Cwuzzy") -> Cwuzzy | D73: =IFERROR(__xludf.DUMMYFUNCTION("""COMPUTED_VALUE"""),"Warbirds") -> Warbirds | E73: =IFERROR(__xludf.DUMMYFUNCTION("""COMPUTED_VALUE"""),"Lunar") -> Lunar | F73: =IFERROR(__xludf.DUMMYFUNCTION("""COMPUTED_VALUE"""),66.8132506883471) -> 66.813251 | G73: =IFERROR(__xludf.DUMMYFUNCTION("""COMPUTED_VALUE"""),68.5131881293581) -> 68.513188 | H73: =IFERROR(__xludf.DUMMYFUNCTION("""COMPUTED_VALUE"""),67.6632194088526) -> 67.663219 | I73: =IFERROR(__xludf.DUMMYFUNCTION("""COMPUTED_VALUE"""),8.0) -> 8 | J73: =IFERROR(__xludf.DUMMYFUNCTION("IFERROR(FILTER(Stats!$F:$Z,(Stats!$A:$A=$A73)*(Stats!$B:$B=$B73)))"),6.0) -> 6 | K73: =IFERROR(__xludf.DUMMYFUNCTION("""COMPUTED_VALUE"""),2.0) -> 2 | L73: =IFERROR(__xludf.DUMMYFUNCTION("""COMPUTED_VALUE"""),0.75) -> 0.75 | M73: =IFERROR(__xludf.DUMMYFUNCTION("""COMPUTED_VALUE"""),1.0) -> 1 | N73: =IFERROR(__xludf.DUMMYFUNCTION("""COMPUTED_VALUE"""),3081.0) -> 3081 | O73: =IFERROR(__xludf.DUMMYFUNCTION("""COMPUTED_VALUE"""),7.0) -> 7 | P73: =IFERROR(__xludf.DUMMYFUNCTION("""COMPUTED_VALUE"""),4.0) -> 4 | Q73: =IFERROR(__xludf.DUMMYFUNCTION("""COMPUTED_VALUE"""),12.0) -> 12 | R73: =IFERROR(__xludf.DUMMYFUNCTION("""COMPUTED_VALUE"""),20.0) -> 20 | S73: =IFERROR(__xludf.DUMMYFUNCTION("""COMPUTED_VALUE"""),0.35) -> 0.35 | T73: =IFERROR(__xludf.DUMMYFUNCTION("""COMPUTED_VALUE"""),385.125) -> 385.125 | U73: =IFERROR(__xludf.DUMMYFUNCTION("""COMPUTED_VALUE"""),0.875) -> 0.875 | V73: =IFERROR(__xludf.DUMMYFUNCTION("""COMPUTED_VALUE"""),0.5) -> 0.5 | W73: =IFERROR(__xludf.DUMMYFUNCTION("""COMPUTED_VALUE"""),1.5) -> 1.5 | X73: =IFERROR(__xludf.DUMMYFUNCTION("""COMPUTED_VALUE"""),2.5) -> 2.5 | Y73: =IFERROR(__xludf.DUMMYFUNCTION("""COMPUTED_VALUE"""),1.0) -> 1 | Z73: =IFERROR(__xludf.DUMMYFUNCTION("""COMPUTED_VALUE"""),0.0) -> 0 | AA73: =IFERROR(__xludf.DUMMYFUNCTION("""COMPUTED_VALUE"""),0.0) -> 0 | AB73: =IFERROR(__xludf.DUMMYFUNCTION("""COMPUTED_VALUE"""),1.0) -> 1 | AC73: =IFERROR(__xludf.DUMMYFUNCTION("""COMPUTED_VALUE"""),10.0) -> 10 | AD73: =IFERROR(__xludf.DUMMYFUNCTION("""COMPUTED_VALUE"""),6.0) -> 6
A74: =IFERROR(__xludf.DUMMYFUNCTION("""COMPUTED_VALUE"""),"Challenger") -> Challenger | B74: =IFERROR(__xludf.DUMMYFUNCTION("""COMPUTED_VALUE"""),"RSC000922") -> RSC000922 | C74: =IFERROR(__xludf.DUMMYFUNCTION("""COMPUTED_VALUE"""),"D_e_r_k") -> D_e_r_k | D74: =IFERROR(__xludf.DUMMYFUNCTION("""COMPUTED_VALUE"""),"Shade") -> Shade | E74: =IFERROR(__xludf.DUMMYFUNCTION("""COMPUTED_VALUE"""),"Lunar") -> Lunar | F74: =IFERROR(__xludf.DUMMYFUNCTION("""COMPUTED_VALUE"""),70.40614967116852) -> 70.40615 | G74: =IFERROR(__xludf.DUMMYFUNCTION("""COMPUTED_VALUE"""),64.90913868954459) -> 64.909139 | H74: =IFERROR(__xludf.DUMMYFUNCTION("""COMPUTED_VALUE"""),67.65764418035656) -> 67.657644 | I74: =IFERROR(__xludf.DUMMYFUNCTION("""COMPUTED_VALUE"""),53.0) -> 53 | J74: =IFERROR(__xludf.DUMMYFUNCTION("IFERROR(FILTER(Stats!$F:$Z,(Stats!$A:$A=$A74)*(Stats!$B:$B=$B74)))"),34.0) -> 34 | K74: =IFERROR(__xludf.DUMMYFUNCTION("""COMPUTED_VALUE"""),19.0) -> 19 | L74: =IFERROR(__xludf.DUMMYFUNCTION("""COMPUTED_VALUE"""),0.6415094339622641) -> 0.64150943 | M74: =IFERROR(__xludf.DUMMYFUNCTION("""COMPUTED_VALUE"""),19.0) -> 19 | N74: =IFERROR(__xludf.DUMMYFUNCTION("""COMPUTED_VALUE"""),18527.0) -> 18527 | O74: =IFERROR(__xludf.DUMMYFUNCTION("""COMPUTED_VALUE"""),45.0) -> 45 | P74: =IFERROR(__xludf.DUMMYFUNCTION("""COMPUTED_VALUE"""),26.0) -> 26 | Q74: =IFERROR(__xludf.DUMMYFUNCTION("""COMPUTED_VALUE"""),60.0) -> 60 | R74: =IFERROR(__xludf.DUMMYFUNCTION("""COMPUTED_VALUE"""),144.0) -> 144 | S74: =IFERROR(__xludf.DUMMYFUNCTION("""COMPUTED_VALUE"""),0.3125) -> 0.3125 | T74: =IFERROR(__xludf.DUMMYFUNCTION("""COMPUTED_VALUE"""),349.5660377358491) -> 349.56604 | U74: =IFERROR(__xludf.DUMMYFUNCTION("""COMPUTED_VALUE"""),0.8490566037735849) -> 0.8490566 | V74: =IFERROR(__xludf.DUMMYFUNCTION("""COMPUTED_VALUE"""),0.49056603773584906) -> 0.49056604 | W74: =IFERROR(__xludf.DUMMYFUNCTION("""COMPUTED_VALUE"""),1.1320754716981132) -> 1.1320755 | X74: =IFERROR(__xludf.DUMMYFUNCTION("""COMPUTED_VALUE"""),2.7169811320754715) -> 2.7169811 | Y74: =IFERROR(__xludf.DUMMYFUNCTION("""COMPUTED_VALUE"""),14.0) -> 14 | Z74: =IFERROR(__xludf.DUMMYFUNCTION("""COMPUTED_VALUE"""),3.0) -> 3 | AA74: =IFERROR(__xludf.DUMMYFUNCTION("""COMPUTED_VALUE"""),1.0) -> 1 | AB74: =IFERROR(__xludf.DUMMYFUNCTION("""COMPUTED_VALUE"""),6.0) -> 6 | AC74: =IFERROR(__xludf.DUMMYFUNCTION("""COMPUTED_VALUE"""),39.0) -> 39 | AD74: =IFERROR(__xludf.DUMMYFUNCTION("""COMPUTED_VALUE"""),45.0) -> 45
A75: =IFERROR(__xludf.DUMMYFUNCTION("""COMPUTED_VALUE"""),"Challenger") -> Challenger | B75: =IFERROR(__xludf.DUMMYFUNCTION("""COMPUTED_VALUE"""),"RSC003331") -> RSC003331 | C75: =IFERROR(__xludf.DUMMYFUNCTION("""COMPUTED_VALUE"""),"Frostii") -> Frostii | D75: =IFERROR(__xludf.DUMMYFUNCTION("""COMPUTED_VALUE"""),"Chromatic Chaos") -> Chromatic Chaos | E75: =IFERROR(__xludf.DUMMYFUNCTION("""COMPUTED_VALUE"""),"Solar") -> Solar | F75: =IFERROR(__xludf.DUMMYFUNCTION("""COMPUTED_VALUE"""),69.86929546364675) -> 69.869295 | G75: =IFERROR(__xludf.DUMMYFUNCTION("""COMPUTED_VALUE"""),64.66857904700012) -> 64.668579 | H75: =IFERROR(__xludf.DUMMYFUNCTION("""COMPUTED_VALUE"""),67.26893725532344) -> 67.268937 | I75: =IFERROR(__xludf.DUMMYFUNCTION("""COMPUTED_VALUE"""),52.0) -> 52 | J75: =IFERROR(__xludf.DUMMYFUNCTION("IFERROR(FILTER(Stats!$F:$Z,(Stats!$A:$A=$A75)*(Stats!$B:$B=$B75)))"),26.0) -> 26 | K75: =IFERROR(__xludf.DUMMYFUNCTION("""COMPUTED_VALUE"""),26.0) -> 26 | L75: =IFERROR(__xludf.DUMMYFUNCTION("""COMPUTED_VALUE"""),0.5) -> 0.5 | M75: =IFERROR(__xludf.DUMMYFUNCTION("""COMPUTED_VALUE"""),20.0) -> 20 | N75: =IFERROR(__xludf.DUMMYFUNCTION("""COMPUTED_VALUE"""),19986.0) -> 19986 | O75: =IFERROR(__xludf.DUMMYFUNCTION("""COMPUTED_VALUE"""),51.0) -> 51 | P75: =IFERROR(__xludf.DUMMYFUNCTION("""COMPUTED_VALUE"""),25.0) -> 25 | Q75: =IFERROR(__xludf.DUMMYFUNCTION("""COMPUTED_VALUE"""),67.0) -> 67 | R75: =IFERROR(__xludf.DUMMYFUNCTION("""COMPUTED_VALUE"""),139.0) -> 139 | S75: =IFERROR(__xludf.DUMMYFUNCTION("""COMPUTED_VALUE"""),0.3669064748201439) -> 0.36690647 | T75: =IFERROR(__xludf.DUMMYFUNCTION("""COMPUTED_VALUE"""),384.34615384615387) -> 384.34615 | U75: =IFERROR(__xludf.DUMMYFUNCTION("""COMPUTED_VALUE"""),0.9807692307692307) -> 0.98076923 | V75: =IFERROR(__xludf.DUMMYFUNCTION("""COMPUTED_VALUE"""),0.4807692307692308) -> 0.48076923 | W75: =IFERROR(__xludf.DUMMYFUNCTION("""COMPUTED_VALUE"""),1.2884615384615385) -> 1.2884615 | X75: =IFERROR(__xludf.DUMMYFUNCTION("""COMPUTED_VALUE"""),2.673076923076923) -> 2.6730769 | Y75: =IFERROR(__xludf.DUMMYFUNCTION("""COMPUTED_VALUE"""),9.0) -> 9 | Z75: =IFERROR(__xludf.DUMMYFUNCTION("""COMPUTED_VALUE"""),5.0) -> 5 | AA75: =IFERROR(__xludf.DUMMYFUNCTION("""COMPUTED_VALUE"""),0.0) -> 0 | AB75: =IFERROR(__xludf.DUMMYFUNCTION("""COMPUTED_VALUE"""),7.0) -> 7 | AC75: =IFERROR(__xludf.DUMMYFUNCTION("""COMPUTED_VALUE"""),63.0) -> 63 | AD75: =IFERROR(__xludf.DUMMYFUNCTION("""COMPUTED_VALUE"""),48.0) -> 48
A76: =IFERROR(__xludf.DUMMYFUNCTION("""COMPUTED_VALUE"""),"Challenger") -> Challenger | B76: =IFERROR(__xludf.DUMMYFUNCTION("""COMPUTED_VALUE"""),"RSC003897") -> RSC003897 | C76: =IFERROR(__xludf.DUMMYFUNCTION("""COMPUTED_VALUE"""),"HalfieHour") -> HalfieHour | D76: =IFERROR(__xludf.DUMMYFUNCTION("""COMPUTED_VALUE"""),"Jinyiwei Insider Traders") -> Jinyiwei Insider Traders | E76: =IFERROR(__xludf.DUMMYFUNCTION("""COMPUTED_VALUE"""),"Lunar Lunar") -> Lunar Lunar | F76: =IFERROR(__xludf.DUMMYFUNCTION("""COMPUTED_VALUE"""),68.28146996903791) -> 68.28147 | G76: =IFERROR(__xludf.DUMMYFUNCTION("""COMPUTED_VALUE"""),64.42110741878615) -> 64.421107 | H76: =IFERROR(__xludf.DUMMYFUNCTION("""COMPUTED_VALUE"""),66.35128869391204) -> 66.351289 | I76: =IFERROR(__xludf.DUMMYFUNCTION("""COMPUTED_VALUE"""),48.0) -> 48 | J76: =IFERROR(__xludf.DUMMYFUNCTION("IFERROR(FILTER(Stats!$F:$Z,(Stats!$A:$A=$A76)*(Stats!$B:$B=$B76)))"),21.0) -> 21 | K76: =IFERROR(__xludf.DUMMYFUNCTION("""COMPUTED_VALUE"""),27.0) -> 27 | L76: =IFERROR(__xludf.DUMMYFUNCTION("""COMPUTED_VALUE"""),0.4375) -> 0.4375 | M76: =IFERROR(__xludf.DUMMYFUNCTION("""COMPUTED_VALUE"""),8.0) -> 8 | N76: =IFERROR(__xludf.DUMMYFUNCTION("""COMPUTED_VALUE"""),19036.0) -> 19036 | O76: =IFERROR(__xludf.DUMMYFUNCTION("""COMPUTED_VALUE"""),49.0) -> 49 | P76: =IFERROR(__xludf.DUMMYFUNCTION("""COMPUTED_VALUE"""),23.0) -> 23 | Q76: =IFERROR(__xludf.DUMMYFUNCTION("""COMPUTED_VALUE"""),74.0) -> 74 | R76: =IFERROR(__xludf.DUMMYFUNCTION("""COMPUTED_VALUE"""),135.0) -> 135 | S76: =IFERROR(__xludf.DUMMYFUNCTION("""COMPUTED_VALUE"""),0.362962962962963) -> 0.36296296 | T76: =IFERROR(__xludf.DUMMYFUNCTION("""COMPUTED_VALUE"""),396.5833333333333) -> 396.58333 | U76: =IFERROR(__xludf.DUMMYFUNCTION("""COMPUTED_VALUE"""),1.0208333333333333) -> 1.0208333 | V76: =IFERROR(__xludf.DUMMYFUNCTION("""COMPUTED_VALUE"""),0.4791666666666667) -> 0.47916667 | W76: =IFERROR(__xludf.DUMMYFUNCTION("""COMPUTED_VALUE"""),1.5416666666666667) -> 1.5416667 | X76: =IFERROR(__xludf.DUMMYFUNCTION("""COMPUTED_VALUE"""),2.8125) -> 2.8125 | Y76: =IFERROR(__xludf.DUMMYFUNCTION("""COMPUTED_VALUE"""),7.0) -> 7 | Z76: =IFERROR(__xludf.DUMMYFUNCTION("""COMPUTED_VALUE"""),3.0) -> 3 | AA76: =IFERROR(__xludf.DUMMYFUNCTION("""COMPUTED_VALUE"""),2.0) -> 2 | AB76: =IFERROR(__xludf.DUMMYFUNCTION("""COMPUTED_VALUE"""),10.0) -> 10 | AC76: =IFERROR(__xludf.DUMMYFUNCTION("""COMPUTED_VALUE"""),37.0) -> 37 | AD76: =IFERROR(__xludf.DUMMYFUNCTION("""COMPUTED_VALUE"""),51.0) -> 51
A77: =IFERROR(__xludf.DUMMYFUNCTION("""COMPUTED_VALUE"""),"Challenger") -> Challenger | B77: =IFERROR(__xludf.DUMMYFUNCTION("""COMPUTED_VALUE"""),"RSC002040") -> RSC002040 | C77: =IFERROR(__xludf.DUMMYFUNCTION("""COMPUTED_VALUE"""),"Scomps") -> Scomps | D77: =IFERROR(__xludf.DUMMYFUNCTION("""COMPUTED_VALUE"""),"Warbirds Decuriones") -> Warbirds Decuriones | E77: =IFERROR(__xludf.DUMMYFUNCTION("""COMPUTED_VALUE"""),"Lunar Solar") -> Lunar Solar | F77: =IFERROR(__xludf.DUMMYFUNCTION("""COMPUTED_VALUE"""),65.69472706726299) -> 65.694727 | G77: =IFERROR(__xludf.DUMMYFUNCTION("""COMPUTED_VALUE"""),65.26307773193) -> 65.263078 | H77: =IFERROR(__xludf.DUMMYFUNCTION("""COMPUTED_VALUE"""),65.47890239959649) -> 65.478902 | I77: =IFERROR(__xludf.DUMMYFUNCTION("""COMPUTED_VALUE"""),36.0) -> 36 | J77: =IFERROR(__xludf.DUMMYFUNCTION("IFERROR(FILTER(Stats!$F:$Z,(Stats!$A:$A=$A77)*(Stats!$B:$B=$B77)))"),18.0) -> 18 | K77: =IFERROR(__xludf.DUMMYFUNCTION("""COMPUTED_VALUE"""),18.0) -> 18 | L77: =IFERROR(__xludf.DUMMYFUNCTION("""COMPUTED_VALUE"""),0.5) -> 0.5 | M77: =IFERROR(__xludf.DUMMYFUNCTION("""COMPUTED_VALUE"""),10.0) -> 10 | N77: =IFERROR(__xludf.DUMMYFUNCTION("""COMPUTED_VALUE"""),13661.0) -> 13661 | O77: =IFERROR(__xludf.DUMMYFUNCTION("""COMPUTED_VALUE"""),30.0) -> 30 | P77: =IFERROR(__xludf.DUMMYFUNCTION("""COMPUTED_VALUE"""),18.0) -> 18 | Q77: =IFERROR(__xludf.DUMMYFUNCTION("""COMPUTED_VALUE"""),54.0) -> 54 | R77: =IFERROR(__xludf.DUMMYFUNCTION("""COMPUTED_VALUE"""),102.0) -> 102 | S77: =IFERROR(__xludf.DUMMYFUNCTION("""COMPUTED_VALUE"""),0.29411764705882354) -> 0.29411765 | T77: =IFERROR(__xludf.DUMMYFUNCTION("""COMPUTED_VALUE"""),379.47222222222223) -> 379.47222 | U77: =IFERROR(__xludf.DUMMYFUNCTION("""COMPUTED_VALUE"""),0.8333333333333334) -> 0.83333333 | V77: =IFERROR(__xludf.DUMMYFUNCTION("""COMPUTED_VALUE"""),0.5) -> 0.5 | W77: =IFERROR(__xludf.DUMMYFUNCTION("""COMPUTED_VALUE"""),1.5) -> 1.5 | X77: =IFERROR(__xludf.DUMMYFUNCTION("""COMPUTED_VALUE"""),2.8333333333333335) -> 2.8333333 | Y77: =IFERROR(__xludf.DUMMYFUNCTION("""COMPUTED_VALUE"""),4.0) -> 4 | Z77: =IFERROR(__xludf.DUMMYFUNCTION("""COMPUTED_VALUE"""),1.0) -> 1 | AA77: =IFERROR(__xludf.DUMMYFUNCTION("""COMPUTED_VALUE"""),1.0) -> 1 | AB77: =IFERROR(__xludf.DUMMYFUNCTION("""COMPUTED_VALUE"""),8.0) -> 8 | AC77: =IFERROR(__xludf.DUMMYFUNCTION("""COMPUTED_VALUE"""),9.0) -> 9 | AD77: =IFERROR(__xludf.DUMMYFUNCTION("""COMPUTED_VALUE"""),51.0) -> 51
A78: =IFERROR(__xludf.DUMMYFUNCTION("""COMPUTED_VALUE"""),"Challenger") -> Challenger | B78: =IFERROR(__xludf.DUMMYFUNCTION("""COMPUTED_VALUE"""),"RSC006416") -> RSC006416 | C78: =IFERROR(__xludf.DUMMYFUNCTION("""COMPUTED_VALUE"""),"StaRazor") -> StaRazor | D78: =IFERROR(__xludf.DUMMYFUNCTION("""COMPUTED_VALUE"""),"Thunder Pups Warthogs") -> Thunder Pups Warthogs | E78: =IFERROR(__xludf.DUMMYFUNCTION("""COMPUTED_VALUE"""),"Solar Lunar") -> Solar Lunar | F78: =IFERROR(__xludf.DUMMYFUNCTION("""COMPUTED_VALUE"""),61.26450736500315) -> 61.264507 | G78: =IFERROR(__xludf.DUMMYFUNCTION("""COMPUTED_VALUE"""),69.15093525953216) -> 69.150935 | H78: =IFERROR(__xludf.DUMMYFUNCTION("""COMPUTED_VALUE"""),65.20772131226765) -> 65.207721 | I78: =IFERROR(__xludf.DUMMYFUNCTION("""COMPUTED_VALUE"""),32.0) -> 32 | J78: =IFERROR(__xludf.DUMMYFUNCTION("IFERROR(FILTER(Stats!$F:$Z,(Stats!$A:$A=$A78)*(Stats!$B:$B=$B78)))"),17.0) -> 17 | K78: =IFERROR(__xludf.DUMMYFUNCTION("""COMPUTED_VALUE"""),15.0) -> 15 | L78: =IFERROR(__xludf.DUMMYFUNCTION("""COMPUTED_VALUE"""),0.53125) -> 0.53125 | M78: =IFERROR(__xludf.DUMMYFUNCTION("""COMPUTED_VALUE"""),4.0) -> 4 | N78: =IFERROR(__xludf.DUMMYFUNCTION("""COMPUTED_VALUE"""),12035.0) -> 12035 | O78: =IFERROR(__xludf.DUMMYFUNCTION("""COMPUTED_VALUE"""),23.0) -> 23 | P78: =IFERROR(__xludf.DUMMYFUNCTION("""COMPUTED_VALUE"""),26.0) -> 26 | Q78: =IFERROR(__xludf.DUMMYFUNCTION("""COMPUTED_VALUE"""),55.0) -> 55 | R78: =IFERROR(__xludf.DUMMYFUNCTION("""COMPUTED_VALUE"""),78.0) -> 78 | S78: =IFERROR(__xludf.DUMMYFUNCTION("""COMPUTED_VALUE"""),0.2948717948717949) -> 0.29487179 | T78: =IFERROR(__xludf.DUMMYFUNCTION("""COMPUTED_VALUE"""),376.09375) -> 376.09375 | U78: =IFERROR(__xludf.DUMMYFUNCTION("""COMPUTED_VALUE"""),0.71875) -> 0.71875 | V78: =IFERROR(__xludf.DUMMYFUNCTION("""COMPUTED_VALUE"""),0.8125) -> 0.8125 | W78: =IFERROR(__xludf.DUMMYFUNCTION("""COMPUTED_VALUE"""),1.71875) -> 1.71875 | X78: =IFERROR(__xludf.DUMMYFUNCTION("""COMPUTED_VALUE"""),2.4375) -> 2.4375 | Y78: =IFERROR(__xludf.DUMMYFUNCTION("""COMPUTED_VALUE"""),6.0) -> 6 | Z78: =IFERROR(__xludf.DUMMYFUNCTION("""COMPUTED_VALUE"""),1.0) -> 1 | AA78: =IFERROR(__xludf.DUMMYFUNCTION("""COMPUTED_VALUE"""),1.0) -> 1 | AB78: =IFERROR(__xludf.DUMMYFUNCTION("""COMPUTED_VALUE"""),9.0) -> 9 | AC78: =IFERROR(__xludf.DUMMYFUNCTION("""COMPUTED_VALUE"""),22.0) -> 22 | AD78: =IFERROR(__xludf.DUMMYFUNCTION("""COMPUTED_VALUE"""),39.0) -> 39
A79: =IFERROR(__xludf.DUMMYFUNCTION("""COMPUTED_VALUE"""),"Challenger") -> Challenger | B79: =IFERROR(__xludf.DUMMYFUNCTION("""COMPUTED_VALUE"""),"RSC000967") -> RSC000967 | C79: =IFERROR(__xludf.DUMMYFUNCTION("""COMPUTED_VALUE"""),"birds aren't real") -> birds aren't real | D79: =IFERROR(__xludf.DUMMYFUNCTION("""COMPUTED_VALUE"""),"Warthogs") -> Warthogs | E79: =IFERROR(__xludf.DUMMYFUNCTION("""COMPUTED_VALUE"""),"Lunar") -> Lunar | F79: =IFERROR(__xludf.DUMMYFUNCTION("""COMPUTED_VALUE"""),61.894204014989555) -> 61.894204 | G79: =IFERROR(__xludf.DUMMYFUNCTION("""COMPUTED_VALUE"""),68.21061634226848) -> 68.210616 | H79: =IFERROR(__xludf.DUMMYFUNCTION("""COMPUTED_VALUE"""),65.05241017862902) -> 65.05241 | I79: =IFERROR(__xludf.DUMMYFUNCTION("""COMPUTED_VALUE"""),24.0) -> 24 | J79: =IFERROR(__xludf.DUMMYFUNCTION("IFERROR(FILTER(Stats!$F:$Z,(Stats!$A:$A=$A79)*(Stats!$B:$B=$B79)))"),12.0) -> 12 | K79: =IFERROR(__xludf.DUMMYFUNCTION("""COMPUTED_VALUE"""),12.0) -> 12 | L79: =IFERROR(__xludf.DUMMYFUNCTION("""COMPUTED_VALUE"""),0.5) -> 0.5 | M79: =IFERROR(__xludf.DUMMYFUNCTION("""COMPUTED_VALUE"""),3.0) -> 3 | N79: =IFERROR(__xludf.DUMMYFUNCTION("""COMPUTED_VALUE"""),8342.0) -> 8342 | O79: =IFERROR(__xludf.DUMMYFUNCTION("""COMPUTED_VALUE"""),22.0) -> 22 | P79: =IFERROR(__xludf.DUMMYFUNCTION("""COMPUTED_VALUE"""),14.0) -> 14 | Q79: =IFERROR(__xludf.DUMMYFUNCTION("""COMPUTED_VALUE"""),28.0) -> 28 | R79: =IFERROR(__xludf.DUMMYFUNCTION("""COMPUTED_VALUE"""),68.0) -> 68 | S79: =IFERROR(__xludf.DUMMYFUNCTION("""COMPUTED_VALUE"""),0.3235294117647059) -> 0.32352941 | T79: =IFERROR(__xludf.DUMMYFUNCTION("""COMPUTED_VALUE"""),347.5833333333333) -> 347.58333 | U79: =IFERROR(__xludf.DUMMYFUNCTION("""COMPUTED_VALUE"""),0.9166666666666666) -> 0.91666667 | V79: =IFERROR(__xludf.DUMMYFUNCTION("""COMPUTED_VALUE"""),0.5833333333333334) -> 0.58333333 | W79: =IFERROR(__xludf.DUMMYFUNCTION("""COMPUTED_VALUE"""),1.1666666666666667) -> 1.1666667 | X79: =IFERROR(__xludf.DUMMYFUNCTION("""COMPUTED_VALUE"""),2.8333333333333335) -> 2.8333333 | Y79: =IFERROR(__xludf.DUMMYFUNCTION("""COMPUTED_VALUE"""),6.0) -> 6 | Z79: =IFERROR(__xludf.DUMMYFUNCTION("""COMPUTED_VALUE"""),1.0) -> 1 | AA79: =IFERROR(__xludf.DUMMYFUNCTION("""COMPUTED_VALUE"""),0.0) -> 0 | AB79: =IFERROR(__xludf.DUMMYFUNCTION("""COMPUTED_VALUE"""),3.0) -> 3 | AC79: =IFERROR(__xludf.DUMMYFUNCTION("""COMPUTED_VALUE"""),19.0) -> 19 | AD79: =IFERROR(__xludf.DUMMYFUNCTION("""COMPUTED_VALUE"""),32.0) -> 32
A80: =IFERROR(__xludf.DUMMYFUNCTION("""COMPUTED_VALUE"""),"Challenger") -> Challenger | B80: =IFERROR(__xludf.DUMMYFUNCTION("""COMPUTED_VALUE"""),"RSC008340") -> RSC008340 | C80: =IFERROR(__xludf.DUMMYFUNCTION("""COMPUTED_VALUE"""),"Slowsociety") -> Slowsociety | D80: =IFERROR(__xludf.DUMMYFUNCTION("""COMPUTED_VALUE"""),"Void") -> Void | E80: =IFERROR(__xludf.DUMMYFUNCTION("""COMPUTED_VALUE"""),"Solar") -> Solar | F80: =IFERROR(__xludf.DUMMYFUNCTION("""COMPUTED_VALUE"""),58.456781725834134) -> 58.456782 | G80: =IFERROR(__xludf.DUMMYFUNCTION("""COMPUTED_VALUE"""),69.30853915403655) -> 69.308539 | H80: =IFERROR(__xludf.DUMMYFUNCTION("""COMPUTED_VALUE"""),63.88266043993534) -> 63.88266 | I80: =IFERROR(__xludf.DUMMYFUNCTION("""COMPUTED_VALUE"""),40.0) -> 40 | J80: =IFERROR(__xludf.DUMMYFUNCTION("IFERROR(FILTER(Stats!$F:$Z,(Stats!$A:$A=$A80)*(Stats!$B:$B=$B80)))"),22.0) -> 22 | K80: =IFERROR(__xludf.DUMMYFUNCTION("""COMPUTED_VALUE"""),18.0) -> 18 | L80: =IFERROR(__xludf.DUMMYFUNCTION("""COMPUTED_VALUE"""),0.55) -> 0.55 | M80: =IFERROR(__xludf.DUMMYFUNCTION("""COMPUTED_VALUE"""),6.0) -> 6 | N80: =IFERROR(__xludf.DUMMYFUNCTION("""COMPUTED_VALUE"""),14311.0) -> 14311 | O80: =IFERROR(__xludf.DUMMYFUNCTION("""COMPUTED_VALUE"""),38.0) -> 38 | P80: =IFERROR(__xludf.DUMMYFUNCTION("""COMPUTED_VALUE"""),23.0) -> 23 | Q80: =IFERROR(__xludf.DUMMYFUNCTION("""COMPUTED_VALUE"""),55.0) -> 55 | R80: =IFERROR(__xludf.DUMMYFUNCTION("""COMPUTED_VALUE"""),108.0) -> 108 | S80: =IFERROR(__xludf.DUMMYFUNCTION("""COMPUTED_VALUE"""),0.35185185185185186) -> 0.35185185 | T80: =IFERROR(__xludf.DUMMYFUNCTION("""COMPUTED_VALUE"""),357.775) -> 357.775 | U80: =IFERROR(__xludf.DUMMYFUNCTION("""COMPUTED_VALUE"""),0.95) -> 0.95 | V80: =IFERROR(__xludf.DUMMYFUNCTION("""COMPUTED_VALUE"""),0.575) -> 0.575 | W80: =IFERROR(__xludf.DUMMYFUNCTION("""COMPUTED_VALUE"""),1.375) -> 1.375 | X80: =IFERROR(__xludf.DUMMYFUNCTION("""COMPUTED_VALUE"""),2.7) -> 2.7 | Y80: =IFERROR(__xludf.DUMMYFUNCTION("""COMPUTED_VALUE"""),7.0) -> 7 | Z80: =IFERROR(__xludf.DUMMYFUNCTION("""COMPUTED_VALUE"""),3.0) -> 3 | AA80: =IFERROR(__xludf.DUMMYFUNCTION("""COMPUTED_VALUE"""),1.0) -> 1 | AB80: =IFERROR(__xludf.DUMMYFUNCTION("""COMPUTED_VALUE"""),6.0) -> 6 | AC80: =IFERROR(__xludf.DUMMYFUNCTION("""COMPUTED_VALUE"""),62.0) -> 62 | AD80: =IFERROR(__xludf.DUMMYFUNCTION("""COMPUTED_VALUE"""),37.0) -> 37
A81: =IFERROR(__xludf.DUMMYFUNCTION("""COMPUTED_VALUE"""),"Challenger") -> Challenger | B81: =IFERROR(__xludf.DUMMYFUNCTION("""COMPUTED_VALUE"""),"RSC008216") -> RSC008216 | C81: =IFERROR(__xludf.DUMMYFUNCTION("""COMPUTED_VALUE"""),"oBlueyRL") -> oBlueyRL | D81: =IFERROR(__xludf.DUMMYFUNCTION("""COMPUTED_VALUE"""),"Warbirds") -> Warbirds | E81: =IFERROR(__xludf.DUMMYFUNCTION("""COMPUTED_VALUE"""),"Lunar") -> Lunar | F81: =IFERROR(__xludf.DUMMYFUNCTION("""COMPUTED_VALUE"""),55.05261290593055) -> 55.052613 | G81: =IFERROR(__xludf.DUMMYFUNCTION("""COMPUTED_VALUE"""),72.69726775491077) -> 72.697268 | H81: =IFERROR(__xludf.DUMMYFUNCTION("""COMPUTED_VALUE"""),63.87494033042066) -> 63.87494 | I81: =IFERROR(__xludf.DUMMYFUNCTION("""COMPUTED_VALUE"""),19.0) -> 19 | J81: =IFERROR(__xludf.DUMMYFUNCTION("IFERROR(FILTER(Stats!$F:$Z,(Stats!$A:$A=$A81)*(Stats!$B:$B=$B81)))"),10.0) -> 10 | K81: =IFERROR(__xludf.DUMMYFUNCTION("""COMPUTED_VALUE"""),9.0) -> 9 | L81: =IFERROR(__xludf.DUMMYFUNCTION("""COMPUTED_VALUE"""),0.5263157894736842) -> 0.52631579 | M81: =IFERROR(__xludf.DUMMYFUNCTION("""COMPUTED_VALUE"""),0.0) -> 0 | N81: =IFERROR(__xludf.DUMMYFUNCTION("""COMPUTED_VALUE"""),6255.0) -> 6255 | O81: =IFERROR(__xludf.DUMMYFUNCTION("""COMPUTED_VALUE"""),13.0) -> 13 | P81: =IFERROR(__xludf.DUMMYFUNCTION("""COMPUTED_VALUE"""),16.0) -> 16 | Q81: =IFERROR(__xludf.DUMMYFUNCTION("""COMPUTED_VALUE"""),19.0) -> 19 | R81: =IFERROR(__xludf.DUMMYFUNCTION("""COMPUTED_VALUE"""),52.0) -> 52 | S81: =IFERROR(__xludf.DUMMYFUNCTION("""COMPUTED_VALUE"""),0.25) -> 0.25 | T81: =IFERROR(__xludf.DUMMYFUNCTION("""COMPUTED_VALUE"""),329.2105263157895) -> 329.21053 | U81: =IFERROR(__xludf.DUMMYFUNCTION("""COMPUTED_VALUE"""),0.6842105263157895) -> 0.68421053 | V81: =IFERROR(__xludf.DUMMYFUNCTION("""COMPUTED_VALUE"""),0.8421052631578947) -> 0.84210526 | W81: =IFERROR(__xludf.DUMMYFUNCTION("""COMPUTED_VALUE"""),1.0) -> 1 | X81: =IFERROR(__xludf.DUMMYFUNCTION("""COMPUTED_VALUE"""),2.736842105263158) -> 2.7368421 | Y81: =IFERROR(__xludf.DUMMYFUNCTION("""COMPUTED_VALUE"""),2.0) -> 2 | Z81: =IFERROR(__xludf.DUMMYFUNCTION("""COMPUTED_VALUE"""),0.0) -> 0 | AA81: =IFERROR(__xludf.DUMMYFUNCTION("""COMPUTED_VALUE"""),0.0) -> 0 | AB81: =IFERROR(__xludf.DUMMYFUNCTION("""COMPUTED_VALUE"""),1.0) -> 1 | AC81: =IFERROR(__xludf.DUMMYFUNCTION("""COMPUTED_VALUE"""),12.0) -> 12 | AD81: =IFERROR(__xludf.DUMMYFUNCTION("""COMPUTED_VALUE"""),24.0) -> 24
A82: =IFERROR(__xludf.DUMMYFUNCTION("""COMPUTED_VALUE"""),"Challenger") -> Challenger | B82: =IFERROR(__xludf.DUMMYFUNCTION("""COMPUTED_VALUE"""),"RSC003109") -> RSC003109 | C82: =IFERROR(__xludf.DUMMYFUNCTION("""COMPUTED_VALUE"""),"Kflip11") -> Kflip11 | D82: =IFERROR(__xludf.DUMMYFUNCTION("""COMPUTED_VALUE"""),"Stingrays") -> Stingrays | E82: =IFERROR(__xludf.DUMMYFUNCTION("""COMPUTED_VALUE"""),"Lunar") -> Lunar | F82: =IFERROR(__xludf.DUMMYFUNCTION("""COMPUTED_VALUE"""),56.73000694422143) -> 56.730007 | G82: =IFERROR(__xludf.DUMMYFUNCTION("""COMPUTED_VALUE"""),70.64278830781464) -> 70.642788 | H82: =IFERROR(__xludf.DUMMYFUNCTION("""COMPUTED_VALUE"""),63.686397626018035) -> 63.686398 | I82: =IFERROR(__xludf.DUMMYFUNCTION("""COMPUTED_VALUE"""),55.0) -> 55 | J82: =IFERROR(__xludf.DUMMYFUNCTION("IFERROR(FILTER(Stats!$F:$Z,(Stats!$A:$A=$A82)*(Stats!$B:$B=$B82)))"),29.0) -> 29 | K82: =IFERROR(__xludf.DUMMYFUNCTION("""COMPUTED_VALUE"""),26.0) -> 26 | L82: =IFERROR(__xludf.DUMMYFUNCTION("""COMPUTED_VALUE"""),0.5272727272727272) -> 0.52727273 | M82: =IFERROR(__xludf.DUMMYFUNCTION("""COMPUTED_VALUE"""),12.0) -> 12 | N82: =IFERROR(__xludf.DUMMYFUNCTION("""COMPUTED_VALUE"""),18940.0) -> 18940 | O82: =IFERROR(__xludf.DUMMYFUNCTION("""COMPUTED_VALUE"""),42.0) -> 42 | P82: =IFERROR(__xludf.DUMMYFUNCTION("""COMPUTED_VALUE"""),40.0) -> 40 | Q82: =IFERROR(__xludf.DUMMYFUNCTION("""COMPUTED_VALUE"""),64.0) -> 64 | R82: =IFERROR(__xludf.DUMMYFUNCTION("""COMPUTED_VALUE"""),156.0) -> 156 | S82: =IFERROR(__xludf.DUMMYFUNCTION("""COMPUTED_VALUE"""),0.2692307692307692) -> 0.26923077 | T82: =IFERROR(__xludf.DUMMYFUNCTION("""COMPUTED_VALUE"""),344.3636363636364) -> 344.36364 | U82: =IFERROR(__xludf.DUMMYFUNCTION("""COMPUTED_VALUE"""),0.7636363636363637) -> 0.76363636 | V82: =IFERROR(__xludf.DUMMYFUNCTION("""COMPUTED_VALUE"""),0.7272727272727273) -> 0.72727273 | W82: =IFERROR(__xludf.DUMMYFUNCTION("""COMPUTED_VALUE"""),1.1636363636363636) -> 1.1636364 | X82: =IFERROR(__xludf.DUMMYFUNCTION("""COMPUTED_VALUE"""),2.8363636363636364) -> 2.8363636 | Y82: =IFERROR(__xludf.DUMMYFUNCTION("""COMPUTED_VALUE"""),9.0) -> 9 | Z82: =IFERROR(__xludf.DUMMYFUNCTION("""COMPUTED_VALUE"""),4.0) -> 4 | AA82: =IFERROR(__xludf.DUMMYFUNCTION("""COMPUTED_VALUE"""),2.0) -> 2 | AB82: =IFERROR(__xludf.DUMMYFUNCTION("""COMPUTED_VALUE"""),6.0) -> 6 | AC82: =IFERROR(__xludf.DUMMYFUNCTION("""COMPUTED_VALUE"""),42.0) -> 42 | AD82: =IFERROR(__xludf.DUMMYFUNCTION("""COMPUTED_VALUE"""),60.0) -> 60
A83: =IFERROR(__xludf.DUMMYFUNCTION("""COMPUTED_VALUE"""),"Challenger") -> Challenger | B83: =IFERROR(__xludf.DUMMYFUNCTION("""COMPUTED_VALUE"""),"RSC005859") -> RSC005859 | C83: =IFERROR(__xludf.DUMMYFUNCTION("""COMPUTED_VALUE"""),"LedTasso") -> LedTasso | D83: =IFERROR(__xludf.DUMMYFUNCTION("""COMPUTED_VALUE"""),"Apple Associates") -> Apple Associates | E83: =IFERROR(__xludf.DUMMYFUNCTION("""COMPUTED_VALUE"""),"Lunar") -> Lunar | F83: =IFERROR(__xludf.DUMMYFUNCTION("""COMPUTED_VALUE"""),59.87717894906284) -> 59.877179 | G83: =IFERROR(__xludf.DUMMYFUNCTION("""COMPUTED_VALUE"""),66.86209442210983) -> 66.862094 | H83: =IFERROR(__xludf.DUMMYFUNCTION("""COMPUTED_VALUE"""),63.369636685586336) -> 63.369637 | I83: =IFERROR(__xludf.DUMMYFUNCTION("""COMPUTED_VALUE"""),56.0) -> 56 | J83: =IFERROR(__xludf.DUMMYFUNCTION("IFERROR(FILTER(Stats!$F:$Z,(Stats!$A:$A=$A83)*(Stats!$B:$B=$B83)))"),33.0) -> 33 | K83: =IFERROR(__xludf.DUMMYFUNCTION("""COMPUTED_VALUE"""),23.0) -> 23 | L83: =IFERROR(__xludf.DUMMYFUNCTION("""COMPUTED_VALUE"""),0.5892857142857143) -> 0.58928571 | M83: =IFERROR(__xludf.DUMMYFUNCTION("""COMPUTED_VALUE"""),5.0) -> 5 | N83: =IFERROR(__xludf.DUMMYFUNCTION("""COMPUTED_VALUE"""),18707.0) -> 18707 | O83: =IFERROR(__xludf.DUMMYFUNCTION("""COMPUTED_VALUE"""),47.0) -> 47 | P83: =IFERROR(__xludf.DUMMYFUNCTION("""COMPUTED_VALUE"""),36.0) -> 36 | Q83: =IFERROR(__xludf.DUMMYFUNCTION("""COMPUTED_VALUE"""),55.0) -> 55 | R83: =IFERROR(__xludf.DUMMYFUNCTION("""COMPUTED_VALUE"""),139.0) -> 139 | S83: =IFERROR(__xludf.DUMMYFUNCTION("""COMPUTED_VALUE"""),0.3381294964028777) -> 0.3381295 | T83: =IFERROR(__xludf.DUMMYFUNCTION("""COMPUTED_VALUE"""),334.05357142857144) -> 334.05357 | U83: =IFERROR(__xludf.DUMMYFUNCTION("""COMPUTED_VALUE"""),0.8392857142857143) -> 0.83928571 | V83: =IFERROR(__xludf.DUMMYFUNCTION("""COMPUTED_VALUE"""),0.6428571428571429) -> 0.64285714 | W83: =IFERROR(__xludf.DUMMYFUNCTION("""COMPUTED_VALUE"""),0.9821428571428571) -> 0.98214286 | X83: =IFERROR(__xludf.DUMMYFUNCTION("""COMPUTED_VALUE"""),2.482142857142857) -> 2.4821429 | Y83: =IFERROR(__xludf.DUMMYFUNCTION("""COMPUTED_VALUE"""),13.0) -> 13 | Z83: =IFERROR(__xludf.DUMMYFUNCTION("""COMPUTED_VALUE"""),4.0) -> 4 | AA83: =IFERROR(__xludf.DUMMYFUNCTION("""COMPUTED_VALUE"""),1.0) -> 1 | AB83: =IFERROR(__xludf.DUMMYFUNCTION("""COMPUTED_VALUE"""),2.0) -> 2 | AC83: =IFERROR(__xludf.DUMMYFUNCTION("""COMPUTED_VALUE"""),78.0) -> 78 | AD83: =IFERROR(__xludf.DUMMYFUNCTION("""COMPUTED_VALUE"""),48.0) -> 48
A84: =IFERROR(__xludf.DUMMYFUNCTION("""COMPUTED_VALUE"""),"Challenger") -> Challenger | B84: =IFERROR(__xludf.DUMMYFUNCTION("""COMPUTED_VALUE"""),"RSC006092") -> RSC006092 | C84: =IFERROR(__xludf.DUMMYFUNCTION("""COMPUTED_VALUE"""),"Mick") -> Mick | D84: =IFERROR(__xludf.DUMMYFUNCTION("""COMPUTED_VALUE"""),"Cooks") -> Cooks | E84: =IFERROR(__xludf.DUMMYFUNCTION("""COMPUTED_VALUE"""),"Solar") -> Solar | F84: =IFERROR(__xludf.DUMMYFUNCTION("""COMPUTED_VALUE"""),58.33092619122969) -> 58.330926 | G84: =IFERROR(__xludf.DUMMYFUNCTION("""COMPUTED_VALUE"""),68.33318473995313) -> 68.333185 | H84: =IFERROR(__xludf.DUMMYFUNCTION("""COMPUTED_VALUE"""),63.33205546559141) -> 63.332055 | I84: =IFERROR(__xludf.DUMMYFUNCTION("""COMPUTED_VALUE"""),52.0) -> 52 | J84: =IFERROR(__xludf.DUMMYFUNCTION("IFERROR(FILTER(Stats!$F:$Z,(Stats!$A:$A=$A84)*(Stats!$B:$B=$B84)))"),33.0) -> 33 | K84: =IFERROR(__xludf.DUMMYFUNCTION("""COMPUTED_VALUE"""),19.0) -> 19 | L84: =IFERROR(__xludf.DUMMYFUNCTION("""COMPUTED_VALUE"""),0.6346153846153846) -> 0.63461538 | M84: =IFERROR(__xludf.DUMMYFUNCTION("""COMPUTED_VALUE"""),12.0) -> 12 | N84: =IFERROR(__xludf.DUMMYFUNCTION("""COMPUTED_VALUE"""),17438.0) -> 17438 | O84: =IFERROR(__xludf.DUMMYFUNCTION("""COMPUTED_VALUE"""),50.0) -> 50 | P84: =IFERROR(__xludf.DUMMYFUNCTION("""COMPUTED_VALUE"""),28.0) -> 28 | Q84: =IFERROR(__xludf.DUMMYFUNCTION("""COMPUTED_VALUE"""),47.0) -> 47 | R84: =IFERROR(__xludf.DUMMYFUNCTION("""COMPUTED_VALUE"""),134.0) -> 134 | S84: =IFERROR(__xludf.DUMMYFUNCTION("""COMPUTED_VALUE"""),0.373134328358209) -> 0.37313433 | T84: =IFERROR(__xludf.DUMMYFUNCTION("""COMPUTED_VALUE"""),335.34615384615387) -> 335.34615 | U84: =IFERROR(__xludf.DUMMYFUNCTION("""COMPUTED_VALUE"""),0.9615384615384616) -> 0.96153846 | V84: =IFERROR(__xludf.DUMMYFUNCTION("""COMPUTED_VALUE"""),0.5384615384615384) -> 0.53846154 | W84: =IFERROR(__xludf.DUMMYFUNCTION("""COMPUTED_VALUE"""),0.9038461538461539) -> 0.90384615 | X84: =IFERROR(__xludf.DUMMYFUNCTION("""COMPUTED_VALUE"""),2.576923076923077) -> 2.5769231 | Y84: =IFERROR(__xludf.DUMMYFUNCTION("""COMPUTED_VALUE"""),7.0) -> 7 | Z84: =IFERROR(__xludf.DUMMYFUNCTION("""COMPUTED_VALUE"""),3.0) -> 3 | AA84: =IFERROR(__xludf.DUMMYFUNCTION("""COMPUTED_VALUE"""),0.0) -> 0 | AB84: =IFERROR(__xludf.DUMMYFUNCTION("""COMPUTED_VALUE"""),2.0) -> 2 | AC84: =IFERROR(__xludf.DUMMYFUNCTION("""COMPUTED_VALUE"""),53.0) -> 53 | AD84: =IFERROR(__xludf.DUMMYFUNCTION("""COMPUTED_VALUE"""),40.0) -> 40
A85: =IFERROR(__xludf.DUMMYFUNCTION("""COMPUTED_VALUE"""),"Challenger") -> Challenger | B85: =IFERROR(__xludf.DUMMYFUNCTION("""COMPUTED_VALUE"""),"RSC008556") -> RSC008556 | C85: =IFERROR(__xludf.DUMMYFUNCTION("""COMPUTED_VALUE"""),"jizko") -> jizko | D85: =IFERROR(__xludf.DUMMYFUNCTION("""COMPUTED_VALUE"""),"Scribes") -> Scribes | E85: =IFERROR(__xludf.DUMMYFUNCTION("""COMPUTED_VALUE"""),"Lunar") -> Lunar | F85: =IFERROR(__xludf.DUMMYFUNCTION("""COMPUTED_VALUE"""),71.03229317555906) -> 71.032293 | G85: =IFERROR(__xludf.DUMMYFUNCTION("""COMPUTED_VALUE"""),53.886765811691575) -> 53.886766 | H85: =IFERROR(__xludf.DUMMYFUNCTION("""COMPUTED_VALUE"""),62.45952949362532) -> 62.459529 | I85: =IFERROR(__xludf.DUMMYFUNCTION("""COMPUTED_VALUE"""),14.0) -> 14 | J85: =IFERROR(__xludf.DUMMYFUNCTION("IFERROR(FILTER(Stats!$F:$Z,(Stats!$A:$A=$A85)*(Stats!$B:$B=$B85)))"),6.0) -> 6 | K85: =IFERROR(__xludf.DUMMYFUNCTION("""COMPUTED_VALUE"""),8.0) -> 8 | L85: =IFERROR(__xludf.DUMMYFUNCTION("""COMPUTED_VALUE"""),0.42857142857142855) -> 0.42857143 | M85: =IFERROR(__xludf.DUMMYFUNCTION("""COMPUTED_VALUE"""),6.0) -> 6 | N85: =IFERROR(__xludf.DUMMYFUNCTION("""COMPUTED_VALUE"""),5033.0) -> 5033 | O85: =IFERROR(__xludf.DUMMYFUNCTION("""COMPUTED_VALUE"""),12.0) -> 12 | P85: =IFERROR(__xludf.DUMMYFUNCTION("""COMPUTED_VALUE"""),6.0) -> 6 | Q85: =IFERROR(__xludf.DUMMYFUNCTION("""COMPUTED_VALUE"""),20.0) -> 20 | R85: =IFERROR(__xludf.DUMMYFUNCTION("""COMPUTED_VALUE"""),41.0) -> 41 | S85: =IFERROR(__xludf.DUMMYFUNCTION("""COMPUTED_VALUE"""),0.2926829268292683) -> 0.29268293 | T85: =IFERROR(__xludf.DUMMYFUNCTION("""COMPUTED_VALUE"""),359.5) -> 359.5 | U85: =IFERROR(__xludf.DUMMYFUNCTION("""COMPUTED_VALUE"""),0.8571428571428571) -> 0.85714286 | V85: =IFERROR(__xludf.DUMMYFUNCTION("""COMPUTED_VALUE"""),0.42857142857142855) -> 0.42857143 | W85: =IFERROR(__xludf.DUMMYFUNCTION("""COMPUTED_VALUE"""),1.4285714285714286) -> 1.4285714 | X85: =IFERROR(__xludf.DUMMYFUNCTION("""COMPUTED_VALUE"""),2.9285714285714284) -> 2.9285714 | Y85: =IFERROR(__xludf.DUMMYFUNCTION("""COMPUTED_VALUE"""),3.0) -> 3 | Z85: =IFERROR(__xludf.DUMMYFUNCTION("""COMPUTED_VALUE"""),0.0) -> 0 | AA85: =IFERROR(__xludf.DUMMYFUNCTION("""COMPUTED_VALUE"""),0.0) -> 0 | AB85: =IFERROR(__xludf.DUMMYFUNCTION("""COMPUTED_VALUE"""),4.0) -> 4 | AC85: =IFERROR(__xludf.DUMMYFUNCTION("""COMPUTED_VALUE"""),13.0) -> 13 | AD85: =IFERROR(__xludf.DUMMYFUNCTION("""COMPUTED_VALUE"""),7.0) -> 7
